Workbook

Sheet README
B2: Index of this spreadsheet
B4: Electricity prices | C4: =HYPERLINK("#'" & B4 & "'!A1", B4) -> Electricity prices
B5: Gas prices | C5: =HYPERLINK("#'" & B5 & "'!A1", B5) -> Gas prices
B18: Other references
B20: Rewiring Aotearoa model | C20: https://docs.google.com/spreadsheets/d/1huoy4UncVW_fkBJAA0xj_LGKF6sLm3SWd1cHOTh1kAA/edit?gid=0#gid=0
B22: EECA review and checks | C22: Final checks on technical report - March 2024.xlsx
C23: See "Wood" tab for pricing, density and NCV data used in the calculator
B31: Powerswitch data | C31: tariffDataReport_240903__EECA_analysis.xlsx
B33: Moneyhub data | C33: moneyhub_power_comparison_july_2024_updated.xlsx
B37: Space heating
B39: COPs for air-air HPs | C39: 20240805 - AC HSPF vs climate.xlsx
B42: Hot water
B44: Gas water heater registration data | C44: 20241031 - Gas water heater product data for Gareth.xlsx
B49: Driving
B51: Gen Less EV page | C51: https://genless.govt.nz/for-everyone/on-the-move/consider-electric-vehicles/why-buy-an-ev/
C52: https://genless.govt.nz/assets/Shared-Resources/electric-vehicle-running-cost-calculations.xlsx
B54: MVR data | C54: MVR--12-fields--2023-and-2024-to-September.xlsx
B56: MIA segmentation report | C56: MIA Common Segmentation Report October 2024.xlsx
B58: Webstructure fuel economy data | C58: CurrentNZnewFC_20241118.xlsx
B61: Number of residents vs number of rooms
B63: Ad-hoc analysis | C63: Census 2018 - Number of usual residents in household by number of rooms.xlsx

Sheet Back end
C3: TIMES-NZ residential energy use paper | D3: Rewiring
B4: Space heating | C4: Regionalisation based on floor area (detached/joined) and climate HDD | D4: Percentage according to climate. How derived?
B5: Water heating | C5: Regionalisation based on occupancy | D5: Assumed percentage
B6: Cooking | C6: None | D6: Assumed percentage
B7: Vehicle | C7: N/A | D7: Number of cars and assumed percentage
B15: Space heating | C15: Impact = Medium
B17: Energy service demand | C17: Warm house
C18: Temperature x time x floor area
C19: Climate
B21: Efficiency | C21: Thermal envelope
C22: Heater efficiency
B24: Fuel use | C24: Unknown
B26: Determinant | C26: Include (yes/no/maybe/comment) | D26: Question | E26: Algorithm | F26: Evidence | G26: Discussion
B27: Interior temperature | C27: No - most houses close to average
B28: Climate | C28: Yes | D28: Region | E28: HDD relative to NZ average HDD | F28: Theory (linear relationship)
B29: Time i.e. heating schedules | C29: Yes/maybe | D29: Home during day? | E29: ? | F29: eCubed H1/deep retrofit
B30: Floor area | C30: Maybe | D30: Area or number of bedrooms | E30: Linear scaling? | F30: Theory (linear relationship)
B31: Thermal envelope quality | C31: Maybe | D31: Age and/or characteristics of house | E31: ? | F31: eCubed H1/deep retrofit
B32: Number of people | C32: Maybe/no | D32: How many people | E32: Assume correlation with area heated? | F32: ?
B34: Notes
B36: Lowest cost space heating option is generally HP, so limited value in high fidelity here?
B37: How many heat pumps do we assume? Mix of HPs and electric?
B38: If being explicit about main living area, develop standard model and run through heating assessment tool.
B40: More sophisticated tools
B42: Tenancy services heating assessment tool (for deisgn loads)
B43: EECA/E3 HP seasonal efficiency algorithm
B45: Water heating | C45: Impact = Medium
B47: Energy service demand | C47: Showering/washing
C48: Temperature x volume
C49: Climate?
B51: Efficiency | C51: Appliance efficiency (inc shower head)
B53: Fuel use | C53: Largely unknown. 45 kg gas bottle use would be closest
B55: Determinant | C55: Include (yes/no/maybe/comment) | D55: Question | E55: Algorithm | F55: Evidence | G55: Discussion
B56: Number of people | C56: Yes | D56: As per determinant
B57: Number of showers per day (per person, or just total) | C57: Yes | D57: As per determinant | E57: Linear scaling from assumed average? Via top down/bottom up reconciliation? | F57: BRANZ SR469/UoA
B58: Duration of shower | C58: Maybe | D58: Lump into high/low/average question? | E58: Percentage scaling | F58: BRANZ SR469/UoA | G58: Natural language questions rather than qualititative answers (Do you use a lot of hot water? Low / Medium / High user)
B59: Shower flow rate | C59: Maybe
B60: Number of baths | C60: Yes/maybe | E60: Assume bath = 2x shower?
B61: Other water use (e.g. laundry) | C61: Maybe
B62: Climate | C62: Yes | D62: Region | E62: TBC. From old tool or standard? | F62: Theory (linear relationship)
B64: Notes
B66: No data on bath use in SR469/UoA
B67: Pre-populate an assumed average e.g. 1 shower per person per day, 1 bath per week etc.?
B68: Add hot water amplifiers like wetbacks and rooftop solar pipes in phase 2?
B70: More sophisticated tools
B72: EECA hot water tool
B73: How would industry size a cylinder? Number of bedrooms and/or bathrooms? (First is proxy for number of people, second is proxy for max demand.)
B75: Cooking | C75: Impact = Low
B77: Energy service demand | C77: Temperature x time
B79: Efficiency | C79: Gas vs electric
B81: Fuel use | C81: Unknown
B83: Determinant | C83: Include (yes/no/maybe/comment) | D83: Question | E83: Algorithm | F83: Evidence | G83: Discussion
B84: Number of people | C84: Yes - small effect, but reasonable hypothesis | D84: As per determinant | E84: Scaling | F84: Reasonable assumption
B87: Vehicles | C87: Impact = High
B89: Energy service demand | C89: Number of cars x VKT. May be known/can be estimated.
B91: Efficiency | C91: Varies. Can estimate.
B93: Fuel use | C93: Relatively well known based on how frequently car filled up and quantity per fill (i.e. quarter/half/full tank)?
B95: Determinant | C95: Include (yes/no/maybe/comment) | D95: Question | E95: Algorithm | F95: Evidence | G95: Discussion
B96: Number of cars | C96: Yes | D96: As per determinant | E96: N/A | F96: N/A | G96: To include motoribikes and other vehicles? Probably no. Just do the "passenger vehicles", don't include boats and farm vehicles.
B97: Distance driven (per car) | C97: Yes | D97: How frequently do you drive your car and how far? High/low/average based on personas? Alternatively ask for fuel use | G97: Ask DNA to user test "How much do you think you spend on fuel per week / month?" vs "How far do you drive per week?
B98: Type/size of car (per car) | C98: Yes | D98: As per determinant | E98: Average efficiency values from earlier work (RA/EECA RUC) | G98: Have vehicles as a separate display in the tool. A new car is such a
B100: Notes
B102: In comparison to space heating, water heating and cooking, users are likely to have some sense of both energy service demand (vehicle kilometres) *and* fuel use.
B104: More sophisticated tools
B106: EECA TCO tool (note personal and business ones are different)
B108: Fuel bills
B110: Enter separate or combined electricity and gas bills?
B111: Monthly electricity bill
B112: Monthly gas bill
B113: Weekly/monthly fuel (petrol/diesel) bill
B116: Energy prices
B118: Regional data as per QSDEP / Solar Power Calculator?
B121: Solar
B124: Determinant | C124: Include (yes/no/maybe/comment) | D124: Question | E124: Algorithm | F124: Evidence | G124: Discussion
B125: Capacity factor | C125: Yes | D125: Region | E125: Calculate capacity factor from EECA solar tool | F125: Solar tool
B127: Notes
B129: If "full" regionalisation is being used for climate (NIWA) then use capacity factors from EECA solar tool. Assume e.g. north orientation and 30 degree pitch (?) and state assumptions on page/in report.
B130: Include as toggle or show side-by-side? (Results with/without solar.)
B131: 15 or 30 year term for LCOE?
B133: More sophisticated tools
B135: EECA solar power calculator
B137: Batteries
B139: What have Rewiring assumed here? | G139: Batteries for phase 2. Have DNA test including batteries at this stage, knowing full well that we won’t include it in the Oct 1st build.

Sheet Front end
A1: Options | B1: Question | C1: Answer options | D1: Algorithm impact | E1: Notes/Consideration
B2: How many people in your house | C2: 1 | D2: Hot water | E2: EECA to confirm the max household number should be.
C3: 2 | D3: Cooking
C4: 3 | D4: Heating
C5: 4
C6: 5
C7: 6+
B9: Where do you live? | C9: Region (list) | D9: Heating | E9: EECA to confirm whether this will also have an overall impact via power bill pricing.
D10: Hot water
B12: What best describes your house? | C12: Well insulated | D12: Heating | E12: Alternative answers: Warm and dry, Cold and drafty, Somewhere in between.
C13: Not well insulated
C14: Somewhere in between
B16: What are your main appliances? | C16: Heating: | D16: Heating | E16: This could alternatively be framed fuel first and appliances second. Note that there are some technologies not covered in the tool, so if a user can’t answer a question they must still be able to get to the end (eg, solar hot water systems) – need to figure out how this situation is shown in results/what assumptions are.
C17: Piped gas | D17: Hot water
C18: Bottled gas (LPG) | D18: Cooking
C19: Heat pump
C20: Other electric | E20: Wording to be finalised
C21: Wood
C22: Hot water:
C23: Piped gas
C24: Bottled gas (LPG)
C25: Hot water heat pump
C26: Traditional electric hot water cylinder
C27: Cooking:
C28: Piped gas
C29: Bottled gas (LPG)
C30: Electric induction
C31: Other electric | E31: Could have "Electric resistance" and Electric induction" here but have a tooltip here explaining the difference: "If your electric stove glows red hot while cooking = electric resistance, if it doesn't = electric induction".
B33: Are people in your household home during the day during the week? (eg, working from home) | C33: Rarely | D33: Heating, and potentially solar | E33: Question and answer to be user tested (algorithm can be adapted to suit)
C34: Sometimes
C35: Often
C36: Always
B38: Hot water use: | C38: Low | D38: Hot water | E38: EECA can provide text on what low/medium/high usage looks like on per person basis. Could alternatively be "Household shower/bath use"
C39: Medium
C40: High
B42: How many cars | C42: 1 | D42: Driving | E42: EECA to confirm the max number of cars.
C43: 2
C44: etc.
B46: What type of fuel | C46: Petrol | D46: Driving | E46: For each car
C47: Diesel
C48: Electric
C49: Hybrid
C50: PHEV
B52: What type of car / Car size | C52: Small | D52: Driving | E52: The answer to this will change the assumed upfront cost of the EV
C53: Medium | E53: We need to define what each of these means.
C54: Large | E54: A visual prompt would help.
A56: 1 | B56: How much do you spend on fuel per month (week)? | C56: Low | D56: Driving | E56: For each car?
C57: Medium
C58: High
A60: 2a | B60: How often do you top up your fuel tank? | C60: Weekly | D60: Driving | E60: For each car? We probably wouldn't ask both about how much you spend and how often you top up - let's test with users which is easier to answer
C61: Monthly
A63: 2b | B63: How much do you top up your tank each time? | C63: Quarter | D63: Driving | E63: For each car?
C64: Half
C65: Full
A67: 3 | B67: How many kms do you travel per week? | C67: Number | D67: Driving
B69: Do you have solar? | C69: Yes | D69: Blanket impact | E69: Not sure about including battery storage in the tool – can we test appetite for this with users?
C70: No
B73: General notes
B75: Vehicles: Results to be calculated and presented separately to in-home appliances.
B76: Solar: To be treated as an add-on to the entire package (both vehicle and in-home). Ie, ability to toggle ‘solar’ on or off and see the impact to savings. | C76: i

Sheet Front end (V2)
A1: Question | B1: Answer options | C1: Tooltip | D1: Notes/Consideration
A2: Your home
A4: Where do you live? | B4: Postcode or Address Lookup | C4: We use this information to estimate electricity prices in your area, and to estimate energy use for heating and hot water.
A6: How many people in your house | B6: 1 | C6: We use this information to estimate energy use for hot water and cooking.
B7: 2
B8: 3
B9: 4
B10: 5
B11: 6+
A13: Do you currently have solar panels? | B13: Yes | C13: This tool only considers solar panels which produce electricity | D13: Defaults to no. If users leave as no, then there needs to be a toggle button that is persistent that allows users to 'add solar' to the results displayed for each appliance.
B14: No
A16: Heating
A18: How do you heat your main living area? | B18: Piped gas heater
B19: Bottled gas heater
B20: Heat pump
B21: Heat pump (ducted)
B22: Electric heater(s)
B23: Wood burner
A25: What best describes the insulation in your house? | B25: Well insulated | C25: A modern house with full insulation and double glazing. This will have been built after 2008, or upgraded to an equivalent standard.
B26: Not well insulated | C26: An old house that has full coverage of floor and ceiling insulation, but no wall insulation and single glazing.
B27: Somewhere in between | C27: An old house with some floor and ceiling insulation but no wall insulation and single glazing.
A29: Do you have heating on during the day? | B29: Yes - weekdays and weekends | C29: In all cases we assume that you have the heating on most mornings and evenings during the colder months.
B30: Weekends only
B31: Only occasionally
A33: Water heating
A35: How do you heat your water? | B35: Piped gas instantaneous | C35: Many people call instantaneous gas systems continuous flow or 'infinity' systems.
B36: Bottled gas instantaneous
B37: Gas hot water cylinder
B38: Electric hot water cylinder
B39: Hot water heat pump
A41: Would you describe your hot water use as low, medium or high? | B41: Low | C41: Less frequent and/or shorter showers
B42: Medium | C42: Approximately 1 average length shower (7 minutes) per person per day
B43: High | C43: More frequent and/or longer showers
A45: Cooking
A47: What kind of cooktop do you use? | B47: Piped gas | C47: This tool doesn't consider gas ovens.
B48: Bottled gas (LPG)
B49: Electric induction | C49: Induction cooktops need magnetic pans.
B50: Electric coil or radiant ceramic | C50: Could have "Electric resistance" and Electric induction" here but have a tooltip here explaining the difference: "If your electric stove glows red hot while cooking = electric resistance, if it doesn't = electric induction".
A52: Driving
A54: What type of car / Car size | B54: Small | C54: Hatchback or compact car | D54: A visual prompt would help.
B55: Medium | C55: Station wagon or crossover/small SUV
B56: Large | C56: Large SUV or ute
A58: What type of fuel | B58: Petrol
B59: Diesel
B60: Hybrid
B61: PHEV
B62: Electric
A64: How many kms do you travel per week? | B64: 50 | C64: 2500 km per year | F64: =B64 * 52 -> 2600
B65: 100 | C65: 5000 km per year | F65: =B65 * 52 -> 5200
B66: 150 | C66: 8000 km per year | F66: =B66 * 52 -> 7800
B67: 200 | C67: 10000 km per year | F67: =B67 * 52 -> 10400
B68: 250 | C68: 13000 km per year | F68: =B68 * 52 -> 13000
B69: 300 | C69: 16000 km per year | F69: =B69 * 52 -> 15600
B70: 350 | C70: 18000 km per year | F70: =B70 * 52 -> 18200
A72: If you're not sure how far you drive, tell us how often you fill up at the pump, and how much, and we'll use this to estimate how many km you drive
A74: How often do you top up your fuel tank? | B74: Twice weekly | D74: Could/should display estimated weekly and annual km based on these answers.
B75: Weekly
B76: Fortnightly
B77: Monthly
A79: How much do you top up your tank each time? | B79: Quarter
B80: Half
B81: Full

Sheet Copy of earlier ideation
A1: Parameters | B1: Variables | C1: Modifiers
A2: Driving | B2: How far do you drive, # of vehicles, vehicle type (EV, ICE, Hybrid), charging type, frequency of use / distance driven per day. | C2: Age of car, possibly? Power plan.
A3: Home heating | B3: Region, climate data, # of people in house, sq/footage of house; type (LPG, piped gas, electric resistance, electric heat pump, wood burner), age of house (pre-200 or post-2000), insulation level (ceiling, walls, underfloor, glazing). Do you have a fire? | C3: how many heat pumps added impact of turning off gas supply completely
A4: Water heating | B4: # of people in house, type (LPG, piped gas, electric resistance, electric heat pump); how long spent in shower, how often you use shower/bath. High or low water use? | C4: added impact of turning off gas supply completely. Size of water cylinder could be a factor.
A5: Cooking | B5: Type (LPG, piped gas, electric resistance, induction) | C5: added impact of turning off gas supply completely
A6: Rooftop solar | C6: Not taking into account panels' age/degradation/inverter age etc.
A7: Power plan | B7: Off peak rates, overnight rates, fixed/variable | C7: Compare optimal current plan versus your optimal power plan (given new electrified appliances). Powerswitch partnership? MBIE partnership?
A8: Battery | B8: Yes / no | C8: For phase 2?
A9: Modifiers on all parameters | B9: Time as a factor (15 year versus 1 year), Upfront costs (include or not include), Gas line/bottle charges. Replacement of appliance opportunity (doing renovations etc). Age of appliances. Emissions influence ($12 billion cost of offsets if we don't meet Paris argets). | C9: Emissions - this may persuade some people to change when cost savings are otherwise negligible.

Sheet SH - Ideas
B2: Space heating calculation
B4: Utilise some of the concepts previously used for the WKH HP sizing methodology. See files in this folder:
B6: Residential - Space Heating - Heat Load Calculation
B8: In particular:
B10: Heat Pump Sizing Method Report.docx
B11: Scenarios for WKH Heat Pump sizing.docx
B12: HP sizing v2.xlsx
B13: WKH Sizing Table Scenarios.xlsx
B15: Central case was:
B17: 40 m^2 floor area
B18: 2.4 m ceiling height
B19: Two external walls
... B22: For electrify tool:
C24: "Well insulated" | D24: "Somewhere in between" | E24: "Not well insulated"
B25: Floor | C25: 1.3 | D25: 1.3 | E25: 0.5
B26: Wall | C26: 1.9 | D26: 0.5 | E26: 0.5
B27: Ceiling | C27: 2.9 | D27: 2.9 | E27: 1.9
B28: Windows | C28: 0.26 | D28: 0.15 | E28: 0.15
B30: "Well insulated" = 2008 Building Code
B31: "Somewhere in between" = WKH retrofit (based on 2008 Building Code) to pre-1978 building with single glazing.
B32: "Not well insulated" = pre-1978 but with retrofit ceiling insulation to 1978 standard.
B34: Tool tip descriptions:
B36: Well insulated | E36: A modern house with full insulation and double glazing. This will have been built after 2008, or upgraded to an equivalent standard.
B37: Somewhere in between | E37: An old house that has full coverage of floor and ceiling insulation, but no wall insulation and single glazing.
B38: Not well insulated | E38: An old house with some floor and ceiling insulation but no wall insulation and single glazing.
B40: Notes
B42: Climate zones
B44: 16 Regional Council regions or 18 NIWA climate zones
B45: Preferably 18 to align with other tools?
B46: … but climate zones are less obvious e.g. how do we get Upper Hutt residents to identify as being in Wairarapa climate zone?
B47: Note Heating Assessment Tool asks for Region, and then "Council Area". Could do something like this?
B49: Heating Degree Days and bottom-up to top-down reconciliation
B51: Alignment with Heating Assessment Tool - Not critical given scaling which will be used for reconciliation?
B52: Alignment with ZERL?
B54: Default R-values copied from "Default R-values" tab of:
B56: Heater sizing spreadsheet v1.0.xlsm
B58: Climate zone | C58: 1 or 2 | D58: 1 or 2 | E58: 1 or 2 | F58: 1 or 2
B59: Building element | C59: 1977 or earlier | D59: From 1978 to 2000 | E59: From 2001 to 2008 | F59: From 2009 onwards
B60: Ext Floor | C60: 0.5 | D60: 0.9 | E60: 1.3 | F60: 1.3
B61: Int Floor | C61: 0.5 | D61: 0.5 | E61: 0.5 | F61: 0.5
B62: Ext Ceil | C62: 0.35 | D62: 1.9 | E62: 1.9 | F62: 2.9
B63: Int Ceil | C63: 0.5 | D63: 0.5 | E63: 0.5 | F63: 0.5
B64: Ext Wall | C64: 0.5 | D64: 1 | E64: 1.5 | F64: 1.9
B65: Int Wall | C65: 0.4 | D65: 0.4 | E65: 0.4 | F65: 0.4
B66: Window | C66: 0.15 | D66: 0.15 | E66: 0.15 | F66: 0.26
B67: Skylight | C67: 0.15 | D67: 0.15 | E67: 0.15 | F67: 0.26
B69: Note 0.15 and 0.26 apply to SG/DG aluminium as per snip below.
B70: Equivalent values for wood/PVC are 0.19 and 0.36.
B84: Miscellaneous questions
B86: Might people interpret result as "buy a HP but don't worry about the insulation"?

Sheet SH - Time bands
B2: Time bands used for heating schedules in Deep Retrofit study
B4: The following Python script is used to segment the hourly data into time bands
B5: Analyse_baseline_for_electrify_tool__v4.py
B8: NZST OR NZDT | F8: NZST | I8: NZDT | L8: Logic of eso file is effectively:
B10: Start time | C10: End time | D10: Heating time period | F10: Hour (as per eso) | I10: Hour (as per eso) | L10: Simulation runs in NZST throughout year.
B11: 0 | C11: =B11 + 1 / 24 -> 0.041666667 | F11: 1 | I11: 1 | L11: When daylight saving time is in effect, the heating schedule shifts an hour earlier.
B12: =B11 + 1 / 24 -> 0.041666667 | C12: =B12 + 1 / 24 -> 0.083333333 | F12: 2 | I12: 2
B13: =B12 + 1 / 24 -> 0.083333333 | C13: =B13 + 1 / 24 -> 0.125 | F13: 3 | I13: 3
B14: =B13 + 1 / 24 -> 0.125 | C14: =B14 + 1 / 24 -> 0.16666667 | F14: 4 | I14: 4
B15: =B14 + 1 / 24 -> 0.16666667 | C15: =B15 + 1 / 24 -> 0.20833333 | F15: 5 | I15: 5
B16: =B15 + 1 / 24 -> 0.20833333 | C16: =B16 + 1 / 24 -> 0.25 | F16: 6 | I16: 6
B17: =B16 + 1 / 24 -> 0.25 | C17: =B17 + 1 / 24 -> 0.29166667 | F17: 7 | I17: 7 | J17: Morning
B18: =B17 + 1 / 24 -> 0.29166667 | C18: =B18 + 1 / 24 -> 0.33333333 | D18: Morning | F18: 8 | G18: Morning | I18: 8 | J18: Morning
B19: =B18 + 1 / 24 -> 0.33333333 | C19: =B19 + 1 / 24 -> 0.375 | D19: Morning | F19: 9 | G19: Morning | I19: 9 | J19: Day
B20: =B19 + 1 / 24 -> 0.375 | C20: =B20 + 1 / 24 -> 0.41666667 | D20: Day | F20: 10 | G20: Day | I20: 10 | J20: Day
B21: =B20 + 1 / 24 -> 0.41666667 | C21: =B21 + 1 / 24 -> 0.45833333 | D21: Day | F21: 11 | G21: Day | I21: 11 | J21: Day
B22: =B21 + 1 / 24 -> 0.45833333 | C22: =B22 + 1 / 24 -> 0.5 | D22: Day | F22: 12 | G22: Day | I22: 12 | J22: Day
B23: =B22 + 1 / 24 -> 0.5 | C23: =B23 + 1 / 24 -> 0.54166667 | D23: Day | F23: 13 | G23: Day | I23: 13 | J23: Day
B24: =B23 + 1 / 24 -> 0.54166667 | C24: =B24 + 1 / 24 -> 0.58333333 | D24: Day | F24: 14 | G24: Day | I24: 14 | J24: Day
B25: =B24 + 1 / 24 -> 0.58333333 | C25: =B25 + 1 / 24 -> 0.625 | D25: Day | F25: 15 | G25: Day | I25: 15 | J25: Day
B26: =B25 + 1 / 24 -> 0.625 | C26: =B26 + 1 / 24 -> 0.66666667 | D26: Day | F26: 16 | G26: Day | I26: 16 | J26: Day
B27: =B26 + 1 / 24 -> 0.66666667 | C27: =B27 + 1 / 24 -> 0.70833333 | D27: Day | F27: 17 | G27: Day | I27: 17 | J27: Evening
B28: =B27 + 1 / 24 -> 0.70833333 | C28: =B28 + 1 / 24 -> 0.75 | D28: Evening | F28: 18 | G28: Evening | I28: 18 | J28: Evening
B29: =B28 + 1 / 24 -> 0.75 | C29: =B29 + 1 / 24 -> 0.79166667 | D29: Evening | F29: 19 | G29: Evening | I29: 19 | J29: Evening
... B32: =B31 + 1 / 24 -> 0.875 | C32: =B32 + 1 / 24 -> 0.91666667 | D32: Evening | F32: 22 | G32: Evening | I32: 22 | J32: Evening
B33: =B32 + 1 / 24 -> 0.91666667 | C33: =B33 + 1 / 24 -> 0.95833333 | D33: Evening | F33: 23 | G33: Evening | I33: 23
B34: =B33 + 1 / 24 -> 0.95833333 | C34: =B34 + 1 / 24 -> 1 | F34: 24 | I34: 24

Sheet SH - Final
B2: Space heating calculation
B4: Need to factor Rewiring Aotearoa numbers by:
B6: Living area
B7: Climate zone
B8: Home insulation standard
B9: Time slices
B11: Regional COP data (HSPF) is from this spreadsheet:
B12: 20240805 - AC HSPF vs climate.xlsx
B15: Data from Machines tab of Rewiring spreadsheet and EEUD
B17: Note 365.25 days per year in calculation
B19: Options for homes > | C19: If Ngas | D19: If LPG | E19: If Wood | F19: If diesel boiler | G19: If resistive | H19: If heat pump on grid
B20: kWh/day | C20: 11.644 | D20: 11.644 | E20: 14.331 | F20: 12.849 | G20: 9.315 | H20: 2.662
B21: kWh/year | C21: 4253 | D21: 4253 | E21: 5234 | F21: 4693 | G21: 3402 | H21: 972
B23: Efficiency | C23: 0.8 | D23: 0.8 | E23: 0.65 | G23: 1 | H23: 3.5
B25: ESD | C25: =C21 * C23 -> 3402.4 | D25: =D21 * D23 -> 3402.4 | E25: =E21 * E23 -> 3402.1 | F25: =F21 * F23 -> 0 | G25: =G21 * G23 -> 3402 | H25: =H21 * H23 -> 3402
B27: Values above are determined from RBS and:
B29: Number of homes | C29: 1920300 | D29: Misc tab, cell B2
B31: National ESD | C31: =C25 * C29 / 1000000 -> 6533.6287 | D31: GWh
C32: =C31 * 3.6 -> 23521.063 | D32: TJ | E32: EEUD has 20,524 TJ of fuel use for residential space heating in 2022. Given heat pump usage, makes sense that ESD > fuel use.
B35: Proportion of heat used for living areas
B37: Values above are for a whole home
B38: Proportion of this which is living area (inc kitchen and dining) is derived from Deep Retrofit report via this Python script:
B39: Analyse_baseline_for_electrify_tool__v4.py
B41: LKD | C41: 0.62925887 | E41: This is heat (energy service demand) proportion.
B44: Climate zone
B46: Data tables from TIMES-NZ paper
B48: Detached dwelling floor area | D48: 171 | E48: m^2
B49: Joined dwelling floor area | D49: 115 | E49: m^2
B51: Climate zone | C51: Climate zone code | D51: HDD (Tref = 18 OC) | E51: HDD (Tref = 16 OC) | F51: HDD (Tref = 14 OC) | I51: Climate zone | J51: Number of detached dwellings | K51: Number of joined dwellings | L51: Total by climate zone
B52: Northland | C52: NL | D52: 1024 | E52: 543 | F52: 220 | I52: Northland | J52: 59960 | K52: 7848 | L52: 67808 | O52: =J52 * $D$48 * D52 -> 10499235840 | P52: =K52 * $D$49 * D52 -> 924180480 | Q52: =O52 + P52 -> 11423416320
B53: Auckland | C53: AK | D53: 1165 | E53: 674 | F53: 317 | I53: Auckland | J53: 390206 | K53: 128320 | L53: 518526 | O53: =J53 * $D$48 * D53 -> 77734888290 | P53: =K53 * $D$49 * D53 -> 17191672000 | Q53: =O53 + P53 -> 94926560290
B54: Hamilton | C54: HN | D54: 1710 | E54: 1133 | F54: 693 | I54: Hamilton | J54: 117120 | K54: 15016 | L54: 132136 | O54: =J54 * $D$48 * D54 -> 34247059200 | P54: =K54 * $D$49 * D54 -> 2952896400 | Q54: =O54 + P54 -> 37199955600
B55: Bay of Plenty | C55: BP | D55: 1274 | E55: 798 | F55: 438 | I55: Bay of Plenty | J55: 79726 | K55: 10974 | L55: 90700 | O55: =J55 * $D$48 * D55 -> 17368628004 | P55: =K55 * $D$49 * D55 -> 1607800740 | Q55: =O55 + P55 -> 18976428744
B56: Rotorua | C56: RR | D56: 2146 | E56: 1511 | F56: 974 | I56: Rotorua | J56: 24057 | K56: 2306 | L56: 26363 | O56: =J56 * $D$48 * D56 -> 8828101062 | P56: =K56 * $D$49 * D56 -> 569097740 | Q56: =O56 + P56 -> 9397198802
B57: Taupo | C57: TP | D57: 2365 | E57: 1718 | F57: 1162 | I57: Taupo | J57: 27293 | K57: 2119 | L57: 29412 | O57: =J57 * $D$48 * D57 -> 11037698595 | P57: =K57 * $D$49 * D57 -> 576315025 | Q57: =O57 + P57 -> 11614013620
B58: New Plymouth | C58: NP | D58: 1646 | E58: 1028 | F58: 552 | I58: New Plymouth | J58: 58471 | K58: 7864 | L58: 66335 | O58: =J58 * $D$48 * D58 -> 16457598486 | P58: =K58 * $D$49 * D58 -> 1488576560 | Q58: =O58 + P58 -> 17946175046
B59: East Coast | C59: EC | D59: 1604 | E59: 1059 | F59: 636 | I59: East Coast | J59: 57600 | K59: 11677 | L59: 69277 | O59: =J59 * $D$48 * D59 -> 15798758400 | P59: =K59 * $D$49 * D59 -> 2153939420 | Q59: =O59 + P59 -> 17952697820
B60: Manawatu | C60: MW | D60: 1821 | E60: 1195 | F60: 689 | I60: Manawatu | J60: 67775 | K60: 11101 | L60: 78876 | O60: =J60 * $D$48 * D60 -> 21104525025 | P60: =K60 * $D$49 * D60 -> 2324715915 | Q60: =O60 + P60 -> 23429240940
B61: Wairarapa | C61: WI | D61: 2100 | E61: 1495 | F61: 994 | I61: Wairarapa | J61: 35692 | K61: 5284 | L61: 40976 | O61: =J61 * $D$48 * D61 -> 12816997200 | P61: =K61 * $D$49 * D61 -> 1276086000 | Q61: =O61 + P61 -> 14093083200
B62: Wellington | C62: WN | D62: 1930 | E62: 1289 | F62: 770 | I62: Wellington | J62: 90748 | K62: 38361 | L62: 129109 | O62: =J62 * $D$48 * D62 -> 29949562440 | P62: =K62 * $D$49 * D62 -> 8514223950 | Q62: =O62 + P62 -> 38463786390
B63: Nelson-Marlborough | C63: NM | D63: 1912 | E63: 1318 | F63: 838 | I63: Nelson-Marlborough | J63: 55416 | K63: 8716 | L63: 64132 | O63: =J63 * $D$48 * D63 -> 18118372032 | P63: =K63 * $D$49 * D63 -> 1916474080 | Q63: =O63 + P63 -> 20034846112
... B69: Invercargill | C69: IN | D69: 2937 | E69: 2227 | F69: 1562 | I69: Invercargill | J69: 32626 | K69: 4196 | L69: 36822 | O69: =J69 * $D$48 * D69 -> 16385658102 | P69: =K69 * $D$49 * D69 -> 1417219980 | Q69: =O69 + P69 -> 17802878082
I70: Total by dwelling type | J70: 1380353 | K70: 318577 | L70: 1698930 | Q70: =SUM( Q52:Q69 ) -> 477541605828
B72: ( 1 / N ) * Sum N_ij * A_j * HDD_i | C72: =Q70 / L70 -> 281083.74 | E72: From above
B73: Average ESD | C73: =C25 -> 3402.4 | E73: From above
B74: Factor | C74: =C73 / C72 -> 0.012104578 | E74: To go from A * HDD to ESD
B76: Weighted average floor area | C76: =( J70 * D48 + K70 * D49 ) / L70 -> 160.49909
B78: ( 1 / N A ) * Sum N_ij * A_j * HDD_i | C78: =C72 / C76 -> 1751.3105
B79: Average ESD | C79: =C73 -> 3402.4
B80: Factor | C80: =C79 / C78 -> 1.9427737 | E80: To go from HDD to ESD
B82: Typology | C82: Location | D82: Bedroom Heater LOAD Annual kWh | E82: Living HP LOAD Annual kWh | F82: TOTAL HEATING LOAD Annual kWh | G82: Living area fraction
B83: VillaBungalow | C83: Auckland | D83: 1500 | E83: 2016 | F83: 3517 | G83: =E83 / F83 -> 0.57321581
B84: VillaBungalow | C84: Wellington | D84: 2830 | E84: 3469 | F84: 6299 | G84: =E84 / F84 -> 0.55072234
B85: VillaBungalow | C85: Christchurch | D85: 4264 | E85: 4028 | F85: 8292 | G85: =E85 / F85 -> 0.48576942
B86: VillaBungalow | C86: Queenstown | D86: 5435 | E86: 4702 | F86: 10137 | G86: =E86 / F86 -> 0.46384532
B87: State House | C87: Auckland | D87: 589 | E87: 1565 | F87: 2154 | G87: =E87 / F87 -> 0.72655525
B88: State House | C88: Wellington | D88: 1346 | E88: 2923 | F88: 4269 | G88: =E88 / F88 -> 0.68470368
B89: State House | C89: Christchurch | D89: 2074 | E89: 3461 | F89: 5534 | G89: =E89 / F89 -> 0.62540658
B90: State House | C90: Queenstown | D90: 2624 | E90: 4028 | F90: 6653 | G90: =E90 / F90 -> 0.60544115
B91: 1970s House | C91: Auckland | D91: 1189 | E91: 2082 | F91: 3271 | G91: =E91 / F91 -> 0.6365026
B92: 1970s House | C92: Wellington | D92: 2447 | E92: 3818 | F92: 6266 | G92: =E92 / F92 -> 0.60932014
B93: 1970s House | C93: Christchurch | D93: 3834 | E93: 4995 | F93: 8829 | G93: =E93 / F93 -> 0.56574924
B94: 1970s House | C94: Queenstown | D94: 4538 | E94: 5473 | F94: 10011 | G94: =E94 / F94 -> 0.54669863
... B98: Post 1978 House | C98: Queenstown | D98: 3486 | E98: 6201 | F98: 9686 | G98: =E98 / F98 -> 0.64020235
B100: =B82 -> Typology | C100: =C82 -> Location | D100: =D82 -> Bedroom Heater LOAD Annual kWh | E100: =E82 -> Living HP LOAD Annual kWh | F100: =F82 -> TOTAL HEATING LOAD Annual kWh | G100: =G82 -> Living area fraction
B101: VillaBungalow | C101: - | D101: =SUMIF( $B$83:$B$98, $B101, D$83:D$98 ) / COUNTIF( $B$83:$B$98, $B101 ) -> 3507.25 | E101: =SUMIF( $B$83:$B$98, $B101, E$83:E$98 ) / COUNTIF( $B$83:$B$98, $B101 ) -> 3553.75 | F101: =SUMIF( $B$83:$B$98, $B101, F$83:F$98 ) / COUNTIF( $B$83:$B$98, $B101 ) -> 7061.25 | G101: =SUMIF( $B$83:$B$98, $B101, G$83:G$98 ) / COUNTIF( $B$83:$B$98, $B101 ) -> 0.51838822
B102: State House | C102: - | D102: =SUMIF( $B$83:$B$98, $B102, D$83:D$98 ) / COUNTIF( $B$83:$B$98, $B102 ) -> 1658.25 | E102: =SUMIF( $B$83:$B$98, $B102, E$83:E$98 ) / COUNTIF( $B$83:$B$98, $B102 ) -> 2994.25 | F102: =SUMIF( $B$83:$B$98, $B102, F$83:F$98 ) / COUNTIF( $B$83:$B$98, $B102 ) -> 4652.5 | G102: =SUMIF( $B$83:$B$98, $B102, G$83:G$98 ) / COUNTIF( $B$83:$B$98, $B102 ) -> 0.66052666
B103: 1970s House | C103: - | D103: =SUMIF( $B$83:$B$98, $B103, D$83:D$98 ) / COUNTIF( $B$83:$B$98, $B103 ) -> 3002 | E103: =SUMIF( $B$83:$B$98, $B103, E$83:E$98 ) / COUNTIF( $B$83:$B$98, $B103 ) -> 4092 | F103: =SUMIF( $B$83:$B$98, $B103, F$83:F$98 ) / COUNTIF( $B$83:$B$98, $B103 ) -> 7094.25 | G103: =SUMIF( $B$83:$B$98, $B103, G$83:G$98 ) / COUNTIF( $B$83:$B$98, $B103 ) -> 0.58956765
B104: Post 1978 House | C104: - | D104: =SUMIF( $B$83:$B$98, $B104, D$83:D$98 ) / COUNTIF( $B$83:$B$98, $B104 ) -> 2286.25 | E104: =SUMIF( $B$83:$B$98, $B104, E$83:E$98 ) / COUNTIF( $B$83:$B$98, $B104 ) -> 4655 | F104: =SUMIF( $B$83:$B$98, $B104, F$83:F$98 ) / COUNTIF( $B$83:$B$98, $B104 ) -> 6941 | G104: =SUMIF( $B$83:$B$98, $B104, G$83:G$98 ) / COUNTIF( $B$83:$B$98, $B104 ) -> 0.68332756
K105: Modelled vs HDD calibrated to observed
B106: =B82 -> Typology | C106: =C82 -> Location | D106: =D82 -> Bedroom Heater LOAD Annual kWh | E106: =E82 -> Living HP LOAD Annual kWh | F106: =F82 -> TOTAL HEATING LOAD Annual kWh | G106: =G82 -> Living area fraction
B107: - | C107: Auckland | D107: =SUMIF( $C$83:$C$98, $C107, D$83:D$98 ) / COUNTIF( $C$83:$C$98, $C107 ) -> 1028.75 | E107: =SUMIF( $C$83:$C$98, $C107, E$83:E$98 ) / COUNTIF( $C$83:$C$98, $C107 ) -> 1975.25 | F107: =SUMIF( $C$83:$C$98, $C107, F$83:F$98 ) / COUNTIF( $C$83:$C$98, $C107 ) -> 3004.25 | G107: =SUMIF( $C$83:$C$98, $C107, G$83:G$98 ) / COUNTIF( $C$83:$C$98, $C107 ) -> 0.66601963 | I107: =$C$80 * D53 -> 2263.3313 | K107: =F107 / I107 -> 1.3273576
B108: - | C108: Wellington | D108: =SUMIF( $C$83:$C$98, $C108, D$83:D$98 ) / COUNTIF( $C$83:$C$98, $C108 ) -> 2105.5 | E108: =SUMIF( $C$83:$C$98, $C108, E$83:E$98 ) / COUNTIF( $C$83:$C$98, $C108 ) -> 3622.25 | F108: =SUMIF( $C$83:$C$98, $C108, F$83:F$98 ) / COUNTIF( $C$83:$C$98, $C108 ) -> 5728 | G108: =SUMIF( $C$83:$C$98, $C108, G$83:G$98 ) / COUNTIF( $C$83:$C$98, $C108 ) -> 0.63719016 | I108: =$C$80 * D62 -> 3749.5532 | K108: =F108 / I108 -> 1.5276487
B109: - | C109: Christchurch | D109: =SUMIF( $C$83:$C$98, $C109, D$83:D$98 ) / COUNTIF( $C$83:$C$98, $C109 ) -> 3298.75 | E109: =SUMIF( $C$83:$C$98, $C109, E$83:E$98 ) / COUNTIF( $C$83:$C$98, $C109 ) -> 4596.5 | F109: =SUMIF( $C$83:$C$98, $C109, F$83:F$98 ) / COUNTIF( $C$83:$C$98, $C109 ) -> 7895 | G109: =SUMIF( $C$83:$C$98, $C109, G$83:G$98 ) / COUNTIF( $C$83:$C$98, $C109 ) -> 0.58455344 | I109: =$C$80 * D65 -> 4837.5065 | K109: =F109 / I109 -> 1.6320392
B110: - | C110: Queenstown | D110: =SUMIF( $C$83:$C$98, $C110, D$83:D$98 ) / COUNTIF( $C$83:$C$98, $C110 ) -> 4020.75 | E110: =SUMIF( $C$83:$C$98, $C110, E$83:E$98 ) / COUNTIF( $C$83:$C$98, $C110 ) -> 5101 | F110: =SUMIF( $C$83:$C$98, $C110, F$83:F$98 ) / COUNTIF( $C$83:$C$98, $C110 ) -> 9121.75 | G110: =SUMIF( $C$83:$C$98, $C110, G$83:G$98 ) / COUNTIF( $C$83:$C$98, $C110 ) -> 0.56404686 | I110: =$C$80 * D66 -> 6063.3967 | K110: =F110 / I110 -> 1.504396
B112: Deep retrofit, p. 36:
B113: "The average modelled quantity of demand needing to be scaled down by 15%, in order to give average heating electricity demand levels consistent with those reported by EECA’s EEUD"
B115: Above analysis suggest scaling down between 33% and 66%. Approximate, but OK.
B117: Missing piece of puzzle is knowing actual heating behaviour, but observed (calibrated HDD model) could arguably be scaled *up* to reflect deep retrofit modelling of actual schedules.
B118: Holidays could be partial explanation i.e. heating off when it would otherwise be on 15% of time.
B120: Interim decision: Use observed (calibrated HDD).
B123: Home insulation standard
B125: Floor area | C125: 40 | D125: m^2
B126: Width = length of room | C126: =SQRT( C125 ) -> 6.3245553 | D126: m
B127: Wall height | C127: 2.4 | D127: m^2
B128: Window area | C128: 0.25 | E128: Percentage of wall, or percentage of wall + window? Assume latter here (i.e., for a 10 m^2 'wall' there is 2.5 m^2 of window and 7.5 m^2 of opaque surface).
C130: Area | E130: "Well insulated" | F130: "Somewhere in between" | G130: "Not well insulated" | I130: "Well insulated" | J130: "Somewhere in between" | K130: "Not well insulated"
B131: Floor | C131: 40 | E131: 1.3 | F131: 1.3 | G131: 0.5 | I131: =( 1 / E131 ) * $C131 -> 30.769231 | J131: =( 1 / F131 ) * $C131 -> 30.769231 | K131: =( 1 / G131 ) * $C131 -> 80
B132: Wall | C132: =2 * C126 * C127 * ( 1 - C128 ) -> 22.768399 | E132: 1.9 | F132: 0.5 | G132: 0.5 | I132: =( 1 / E132 ) * $C132 -> 11.983368 | J132: =( 1 / F132 ) * $C132 -> 45.536798 | K132: =( 1 / G132 ) * $C132 -> 45.536798
B133: Ceiling | C133: =C125 -> 40 | E133: 2.9 | F133: 2.9 | G133: 1.9 | I133: =( 1 / E133 ) * $C133 -> 13.793103 | J133: =( 1 / F133 ) * $C133 -> 13.793103 | K133: =( 1 / G133 ) * $C133 -> 21.052632
B134: Windows | C134: =2 * C126 * C127 * C128 -> 7.5894664 | E134: 0.26 | F134: 0.15 | G134: 0.15 | I134: =( 1 / E134 ) * $C134 -> 29.190255 | J134: =( 1 / F134 ) * $C134 -> 50.596443 | K134: =( 1 / G134 ) * $C134 -> 50.596443
I135: =SUM( I131:I134 ) -> 85.735958 | J135: =SUM( J131:J134 ) -> 140.69558 | K135: =SUM( K131:K134 ) -> 197.18587
B137: Factors to apply. These feel about right in that they are meaningfully different. | I137: =I135 / $J$135 -> 0.6093721 | J137: =J135 / $J$135 -> 1 | K137: =K135 / $J$135 -> 1.4015073
B140: Time slices
B142: Time slice data is the mean across 4 typologies and 3 climates (Auckland, Wellington, and Christchurch) for baseline thermal envelope standard and realistic heating schedule. No weighting.
B143: All data is for weekend, which represents a continuous period of heating from morning through to evening.
B144: Analysis is in:
B145: Analyse_baseline_for_electrify_tool__v4.py
E147: Start | F147: End | G147: Hours
B148: Morning | C148: 0.11332227 | E148: 7 | F148: 9 | G148: =F148 - E148 -> 2
...

Sheet SH - Regression model
A2: Typology | B2: Location | C2: source | D2: regression_local | E2: delta_local
A3: VillaBungalow | B3: Auckland | C3: 2016.3926 | D3: 2240.6126 | E3: 224.22007
B4: Wellington | C4: 3469.1661 | D4: 3621.1699 | E4: 152.00388
B5: Christchurch | C5: 4027.7029 | D5: 4331.1496 | E5: 303.44673
B6: Queenstown | C6: 4702.1604 | D6: 4806.8415 | E6: 104.68107
A7: State House | B7: Auckland | C7: 1564.6935 | D7: 1886.0484 | E7: 321.35494
B8: Wellington | C8: 2923.0018 | D8: 3125.7736 | E8: 202.77174
B9: Christchurch | C9: 3460.5967 | D9: 3837.8857 | E9: 377.28903
B10: Queenstown | C10: 4028.3862 | D10: 4153.8785 | E10: 125.49231
A11: 1970s House | B11: Auckland | C11: 2082.0463 | D11: 2408.802 | E11: 326.75572
B12: Wellington | C12: 3818.3389 | D12: 4079.7362 | E12: 261.39736
B13: Christchurch | C13: 4995.3102 | D13: 5412.0899 | E13: 416.77972
B14: Queenstown | C14: 5472.7823 | D14: 5426.5075 | E14: -46.274876
A15: Post 1978 House | B15: Auckland | C15: 2238.2604 | D15: 2695.3523 | E15: 457.09192
B16: Wellington | C16: 4278.7021 | D16: 4630.2924 | E16: 351.5903
B17: Christchurch | C17: 5901.7451 | D17: 6421.3985 | E17: 519.65339
B18: Queenstown | C18: 6200.524 | D18: 6534.7752 | E18: 334.25116
A21: Typology | B21: Location | C21: source | D21: regression_combined | E21: delta_combined
A22: VillaBungalow | B22: Auckland | C22: 2016.3926 | D22: 2181.453 | E22: 165.06047
B23: Wellington | C23: 3469.1661 | D23: 3558.7436 | E23: 89.577504
B24: Christchurch | C24: 4027.7029 | D24: 4270.4814 | E24: 242.77853
B25: Queenstown | C25: 4702.1604 | D25: 5004.5311 | E25: 302.37067
A26: State House | B26: Auckland | C26: 1564.6935 | D26: 1804.6402 | E26: 239.94669
B27: Wellington | C27: 2923.0018 | D27: 3048.4812 | E27: 125.47936
B28: Christchurch | C28: 3460.5967 | D28: 3727.2534 | E28: 266.65672
B29: Queenstown | C29: 4028.3862 | D29: 4420.9393 | E29: 392.55307
A30: 1970s House | B30: Auckland | C30: 2082.0463 | D30: 2461.5777 | E30: 379.53144
B31: Wellington | C31: 3818.3389 | D31: 4066.978 | E31: 248.63916
B32: Christchurch | C32: 4995.3102 | D32: 4928.4299 | E32: -66.880235
B33: Queenstown | C33: 5472.7823 | D33: 5753.7391 | E33: 280.95679
A34: Post 1978 House | B34: Auckland | C34: 2238.2604 | D34: 2974.2613 | E34: 736.00094
B35: Wellington | C35: 4278.7021 | D35: 4797.0363 | E35: 518.3342
B36: Christchurch | C36: 5901.7451 | D36: 5673.6424 | E36: -228.10277
B37: Queenstown | C37: 6200.524 | D37: 6521.2116 | E37: 320.6876
A40: Typology | B40: Location | C40: source | D40: regression_local | E40: regression_combined
A41: VillaBungalow | B41: Auckland | C41: 2016.3926 | D41: 2240.6126 | E41: 2181.453
B42: Wellington | C42: 3469.1661 | D42: 3621.1699 | E42: 3558.7436
B43: Christchurch | C43: 4027.7029 | D43: 4331.1496 | E43: 4270.4814
B44: Queenstown | C44: 4702.1604 | D44: 4806.8415 | E44: 5004.5311
A45: State House | B45: Auckland | C45: 1564.6935 | D45: 1886.0484 | E45: 1804.6402
B46: Wellington | C46: 2923.0018 | D46: 3125.7736 | E46: 3048.4812
B47: Christchurch | C47: 3460.5967 | D47: 3837.8857 | E47: 3727.2534
B48: Queenstown | C48: 4028.3862 | D48: 4153.8785 | E48: 4420.9393
A49: 1970s House | B49: Auckland | C49: 2082.0463 | D49: 2408.802 | E49: 2461.5777
B50: Wellington | C50: 3818.3389 | D50: 4079.7362 | E50: 4066.978
B51: Christchurch | C51: 4995.3102 | D51: 5412.0899 | E51: 4928.4299
B52: Queenstown | C52: 5472.7823 | D52: 5426.5075 | E52: 5753.7391
A53: Post 1978 House | B53: Auckland | C53: 2238.2604 | D53: 2695.3523 | E53: 2974.2613
B54: Wellington | C54: 4278.7021 | D54: 4630.2924 | E54: 4797.0363
B55: Christchurch | C55: 5901.7451 | D55: 6421.3985 | E55: 5673.6424
B56: Queenstown | C56: 6200.524 | D56: 6534.7752 | E56: 6521.2116

Sheet WH - Evidence
B2: Whittaker et al. (2022) Residential Water Use in New Zealand – End Use Disaggregation 2.0
B4: https://www.waternz.org.nz/Resources/Article?Action=View&Article_id=2243
B6: P. 23: "An additional “high flow or outdoor use” category was also created, as it is difficult to differentiate between outdoor use and high-flow taps such as in a laundry tub."
B8: P. 35: "The increase in outdoor use in Spring and Summer is also to be expected, as is the increase in absolute volumes used for showers in these months (even if the relative contribution of shower events remained unchanged)."
B9: Above is opposite to GG's previous understanding that shower use went up in winter. May be specific demographic factors in that high shower use in winter was understood to be related to colder homes.
B11: Searched document for "bath". No references. Assume bath is in the "high flow" bucket.
K15: Use type | L15: Mean daily volume (litres) | M15: Median daily volume (litres) | N15: Standard Deviation (litres) | O15: 95% confidence interval in mean (litres)
K16: Dishwasher | L16: 6.1 | M16: 4.1 | N16: 6.1 | O16: [4.1, 8.1] | Q16: Dishwashers are most often internally heated so no draw from HW system.
K17: Washing Machine | L17: 54.1 | M17: 37.2 | N17: 51.9 | O17: [37.0, 71.1] | Q17: Normal/warm wash is 35 deg. Assume 50% of water use is cold (for e.g. rinse) and 50% is 35 degC.
K18: Toilet | L18: 80.7 | M18: 56.5 | N18: 55.2 | O18: [62.6, 98.8] | Q18: All cold
K19: Shower | L19: 102.1 | M19: 99.9 | N19: 61.5 | O19: [81.9, 122.3] | Q19: All 37 degC.
K20: Tap | L20: 46.3 | M20: 41.7 | N20: 31.9 | O20: [35.8, 56.8] | Q20: Assume 50/50 cold/40 degC.
K21: High Flow/Outdoor | L21: 54.2 | M21: 17.4 | N21: 87 | O21: [25.6, 82.8] | Q21: Assume winter use is laundry tubs/baths i.e. 0% outdoor. Assume this is constant through the year. Assume 50% is at 37 degC.
K22: Undefined | L22: 8.3 | M22: 1.2 | N22: 27.2 | O22: [-1.6, 18.1] | Q22: Ignore.
K29: Table 10 data reordered as per Table 9 data
L31: Average use frequency | N31: Per day | O31: Per week | Q31: Median use frequency | S31: Per day | T31: Per week | V31: Standard deviation | W31: 95% confidence interval in mean
K32: Dishwasher | L32: 4.2 | M32: per week | N32: =L32 / 7 -> 0.6 | O32: =N32 * 7 -> 4.2 | Q32: 2.9 | R32: per week | S32: =Q32 / 7 -> 0.41428571 | T32: =S32 * 7 -> 2.9 | V32: 3.4 | W32: [1.5, 4.2]
K33: Washing machine | L33: 3.4 | M33: per week | N33: =L33 / 7 -> 0.48571429 | O33: =N33 * 7 -> 3.4 | Q33: 2.2 | R33: per week | S33: =Q33 / 7 -> 0.31428571 | T33: =S33 * 7 -> 2.2 | V33: 3.5 | W33: [3.1, 5.2]
K34: Toilet | L34: 14.7 | M34: per day | N34: =L34 -> 14.7 | O34: =N34 * 7 -> 102.9 | Q34: 10.7 | R34: per day | S34: =Q34 -> 10.7 | T34: =S34 * 7 -> 74.9 | V34: 10.3 | W34: [11.5, 18.0]
K35: Shower | L35: 2 | M35: per day | N35: =L35 -> 2 | O35: =N35 * 7 -> 14 | Q35: 1.4 | R35: per day | S35: =Q35 -> 1.4 | T35: =S35 * 7 -> 9.8 | V35: 2.6 | W35: [1.2, 2.9]
K36: Tap | L36: 118.8 | M36: per day | N36: =L36 -> 118.8 | O36: =N36 * 7 -> 831.6 | Q36: 106.4 | R36: per day | S36: =Q36 -> 106.4 | T36: =S36 * 7 -> 744.8 | V36: 75.1 | W36: [95.1, 142.5]
K37: High Flow/Outdoor | L37: 2.8 | M37: per day | N37: =L37 -> 2.8 | O37: =N37 * 7 -> 19.6 | Q37: 2.9 | R37: per day | S37: =Q37 -> 2.9 | T37: =S37 * 7 -> 20.3 | V37: 3.4 | W37: [2.3, 4.5]
K40: Volume per use
K42: =K16 -> Dishwasher | L42: =L16 / N32 -> 10.166667
K43: =K17 -> Washing Machine | L43: =L17 / N33 -> 111.38235 | N43: "On average, an 8.5kg top loader uses nearly 135L of water per 3.5kg load, whereas an 8.5kg front loader swigs a more modest 64L."
K44: =K18 -> Toilet | L44: =L18 / N34 -> 5.4897959 | N44: https://www.consumer.org.nz/articles/how-to-save-water-in-the-laundry
K45: =K19 -> Shower | L45: =L19 / N35 -> 51.05
K46: =K20 -> Tap | L46: =L20 / N36 -> 0.38973064
K47: =K21 -> High Flow/Outdoor | L47: =L21 / N37 -> 19.357143
K50: Table 11 data reordered as per Table 9 data
L52: Average use frequency | N52: Per day | O52: Per week | Q52: Median use frequency | S52: Per day | T52: Per week | V52: Standard deviation | W52: 95% confidence interval in mean
K53: Dishwasher | L53: 1.6 | M53: per week | N53: =L53 / 7 -> 0.22857143 | O53: =N53 * 7 -> 1.6 | Q53: 1.2 | R53: per week | S53: =Q53 / 7 -> 0.17142857 | T53: =S53 * 7 -> 1.2 | V53: 1.4 | W53: [0.6, 1.5]
K54: Washing machine | L54: 1.3 | M54: per week | N54: =L54 / 7 -> 0.18571429 | O54: =N54 * 7 -> 1.3 | Q54: 1 | R54: per week | S54: =Q54 / 7 -> 0.14285714 | T54: =S54 * 7 -> 1 | V54: 1 | W54: [1.1, 2.1]
K55: Toilet | L55: 6.5 | M55: per day | N55: =L55 -> 6.5 | O55: =N55 * 7 -> 45.5 | Q55: 5.1 | R55: per day | S55: =Q55 -> 5.1 | T55: =S55 * 7 -> 35.7 | V55: 4.9 | W55: [4.8, 8.2]
K56: Shower | L56: 0.7 | M56: per day | N56: =L56 -> 0.7 | O56: =N56 * 7 -> 4.9 | Q56: 0.6 | R56: per day | S56: =Q56 -> 0.6 | T56: =S56 * 7 -> 4.2 | V56: 0.5 | W56: [0.5, 0.9]
K57: Tap | L57: 57.1 | M57: per day | N57: =L57 -> 57.1 | O57: =N57 * 7 -> 399.7 | Q57: 44.2 | R57: per day | S57: =Q57 -> 44.2 | T57: =S57 * 7 -> 309.4 | V57: 42.4 | W57: [42.3, 71.9]
K58: High Flow/Outdoor | L58: 1 | M58: per day | N58: =L58 -> 1 | O58: =N58 * 7 -> 7 | Q58: 1.2 | R58: per day | S58: =Q58 -> 1.2 | T58: =S58 * 7 -> 8.4 | V58: 1.4 | W58: [0.9, 1.6]
K61: Per dwelling (Table 10) divided by per person (Table 11)
K63: Dishwasher | L63: =L32 / L53 -> 2.625 | N63: Differences due to rounding, or source data?
K64: Washing machine | L64: =L33 / L54 -> 2.6153846
K65: Toilet | L65: =L34 / L55 -> 2.2615385
K66: Shower | L66: =L35 / L56 -> 2.8571429
K67: Tap | L67: =L36 / L57 -> 2.0805604
K68: High Flow/Outdoor | L68: =L37 / L58 -> 2.8
B69: Duration calculated from volume per use
B71: Flow | C71: Duration | D71: Volume
B72: L/min | C72: min | D72: L
B73: 7 | C73: =$L$45 / B73 -> 7.2928571 | D73: =B73 * C73 -> 51.05
B74: 8 | C74: =$L$45 / B74 -> 6.38125 | D74: =B74 * C74 -> 51.05
B75: 9 | C75: =$L$45 / B75 -> 5.6722222 | D75: =B75 * C75 -> 51.05
B76: 10 | C76: =$L$45 / B76 -> 5.105 | D76: =B76 * C76 -> 51.05
B77: 11 | C77: =$L$45 / B77 -> 4.6409091 | D77: =B77 * C77 -> 51.05
B79: 8.5 | C79: =$L$45 / B79 -> 6.0058824 | D79: =B79 * C79 -> 51.05
B82: Volume per use calculated from flow and duration
B84: Flow | C84: Duration
B85: L/min | C85: min
C86: 4 | D86: 5 | E86: 6 | F86: 7 | G86: 8 | H86: 9 | I86: 10
B87: 7 | C87: =$B87 * C$86 -> 28 | D87: =$B87 * D$86 -> 35 | E87: =$B87 * E$86 -> 42 | F87: =$B87 * F$86 -> 49 | G87: =$B87 * G$86 -> 56 | H87: =$B87 * H$86 -> 63 | I87: =$B87 * I$86 -> 70
B88: 8 | C88: =$B88 * C$86 -> 32 | D88: =$B88 * D$86 -> 40 | E88: =$B88 * E$86 -> 48 | F88: =$B88 * F$86 -> 56 | G88: =$B88 * G$86 -> 64 | H88: =$B88 * H$86 -> 72 | I88: =$B88 * I$86 -> 80
B89: 9 | C89: =$B89 * C$86 -> 36 | D89: =$B89 * D$86 -> 45 | E89: =$B89 * E$86 -> 54 | F89: =$B89 * F$86 -> 63 | G89: =$B89 * G$86 -> 72 | H89: =$B89 * H$86 -> 81 | I89: =$B89 * I$86 -> 90
B90: 10 | C90: =$B90 * C$86 -> 40 | D90: =$B90 * D$86 -> 50 | E90: =$B90 * E$86 -> 60 | F90: =$B90 * F$86 -> 70 | G90: =$B90 * G$86 -> 80 | H90: =$B90 * H$86 -> 90 | I90: =$B90 * I$86 -> 100
B91: 11 | C91: =$B91 * C$86 -> 44 | D91: =$B91 * D$86 -> 55 | E91: =$B91 * E$86 -> 66 | F91: =$B91 * F$86 -> 77 | G91: =$B91 * G$86 -> 88 | H91: =$B91 * H$86 -> 99 | I91: =$B91 * I$86 -> 110
B93: Per week | C93: Per shower | D93: Flow | E93: Volume | F93: Relative to average | H93: Other use | I93: Total use
B94: [] | C94: [min] | D94: [L/min] | E94: [L/week] | H94: [L/week] | I94: [L/week]
B95: =0.7 * 7 -> 4.9 | E95: =B95 * $L$45 -> 250.145 | H95: =( 1 - 0.62 ) * E95 / 0.62 -> 153.31468 | I95: =E95 + H95 -> 403.45968
B97: Occupants per house | E97: ='WH - Final'!C74 -> 2.7
B98: kWh / (kg K ) | E98: ='WH - Final'!C69 -> 0.0011622222
B99: Delta T | E99: ='WH - Final'!C77 -> 25
B101: Version 1
B102: 5 showers per week as per mean. L/shower rounded down to 48 from 51.
B104: Per week | C104: Per shower | D104: Flow | E104: Volume | F104: Volume | G104: Ratio | I104: Other use | J104: Total use | K104: Ratio | M104: kWh
B105: [] | C105: [min] | D105: [L/min] | E105: [L/use] | F105: [L/week] | I105: [L/week] | J105: [L/week]
B106: 4 | C106: 4 | D106: 6 | E106: =C106 * D106 -> 24 | F106: =B106 * C106 * D106 -> 96 | G106: =F106 / $F$107 -> 0.4 | I106: =I107 -> 147.09677 | J106: =F106 + I106 -> 243.09677 | K106: =J106 / $J$107 -> 0.628 | M106: =( 365.25 * J106 / 7 ) * $E$97 * $E$98 * $E$99 -> 995.09451
B107: 5 | C107: 6 | D107: 8 | E107: =C107 * D107 -> 48 | F107: =B107 * C107 * D107 -> 240 | G107: =F107 / $F$107 -> 1 | I107: =( 1 - 0.62 ) * F107 / 0.62 -> 147.09677 | J107: =F107 + I107 -> 387.09677 | K107: =J107 / $J$107 -> 1 | M107: =( 365.25 * J107 / 7 ) * $E$97 * $E$98 * $E$99 -> 1584.5454
B108: 6 | C108: 8 | D108: 10 | E108: =C108 * D108 -> 80 | F108: =B108 * C108 * D108 -> 480 | G108: =F108 / $F$107 -> 2 | I108: =I107 -> 147.09677 | J108: =F108 + I108 -> 627.09677 | K108: =J108 / $J$107 -> 1.62 | M108: =( 365.25 * J108 / 7 ) * $E$97 * $E$98 * $E$99 -> 2566.9635
B110: Version 2
B111: 5 showers per week. L/shower rounded up to 54 from 51.
B113: Per week | C113: Per shower | D113: Flow | E113: Volume | F113: Volume | G113: Ratio | I113: Other use | J113: Total use | K113: Ratio
B114: [] | C114: [min] | D114: [L/min] | E114: [L/use] | F114: [L/week] | I114: [L/week] | J114: [L/week]
B115: 4 | C115: 4 | D115: 7 | E115: =C115 * D115 -> 28 | F115: =B115 * C115 * D115 -> 112 | G115: =F115 / $F$116 -> 0.41481481 | I115: =I116 -> 165.48387 | J115: =F115 + I115 -> 277.48387 | K115: =J115 / $J$116 -> 0.63718519 | M115: =( 365.25 * J115 / 7 ) * $E$97 * $E$98 * $E$99 -> 1135.855
B116: 5 | C116: 6 | D116: 9 | E116: =C116 * D116 -> 54 | F116: =B116 * C116 * D116 -> 270 | G116: =F116 / $F$116 -> 1 | I116: =( 1 - 0.62 ) * F116 / 0.62 -> 165.48387 | J116: =F116 + I116 -> 435.48387 | K116: =J116 / $J$116 -> 1 | M116: =( 365.25 * J116 / 7 ) * $E$97 * $E$98 * $E$99 -> 1782.6136
B117: 6 | C117: 8 | D117: 11 | E117: =C117 * D117 -> 88 | F117: =B117 * C117 * D117 -> 528 | G117: =F117 / $F$116 -> 1.9555556 | I117: =I116 -> 165.48387 | J117: =F117 + I117 -> 693.48387 | K117: =J117 / $J$116 -> 1.5924444 | M117: =( 365.25 * J117 / 7 ) * $E$97 * $E$98 * $E$99 -> 2838.7131
B119: Version 3
B120: 5 showers per week. L/shower now 63 from average of 51.
B122: Per week | C122: Per shower | D122: Flow | E122: Volume | F122: Volume | G122: Ratio | I122: Other use | J122: Total use | K122: Ratio
B123: [] | C123: [min] | D123: [L/min] | E123: [L/use] | F123: [L/week] | I123: [L/week] | J123: [L/week]
B124: 4 | C124: 5 | D124: 7 | E124: =C124 * D124 -> 35 | F124: =B124 * C124 * D124 -> 140 | G124: =F124 / $F$125 -> 0.44444444 | I124: =I125 -> 193.06452 | J124: =F124 + I124 -> 333.06452 | K124: =J124 / $J$125 -> 0.65555556 | M124: =( 365.25 * J124 / 7 ) * $E$97 * $E$98 * $E$99 -> 1363.3693
B125: 5 | C125: 7 | D125: 9 | E125: =C125 * D125 -> 63 | F125: =B125 * C125 * D125 -> 315 | G125: =F125 / $F$125 -> 1 | I125: =( 1 - 0.62 ) * F125 / 0.62 -> 193.06452 | J125: =F125 + I125 -> 508.06452 | K125: =J125 / $J$125 -> 1 | M125: =( 365.25 * J125 / 7 ) * $E$97 * $E$98 * $E$99 -> 2079.7158
B126: 6 | C126: 9 | D126: 11 | E126: =C126 * D126 -> 99 | F126: =B126 * C126 * D126 -> 594 | G126: =F126 / $F$125 -> 1.8857143 | I126: =I125 -> 193.06452 | J126: =F126 + I126 -> 787.06452 | K126: =J126 / $J$125 -> 1.5491429 | M126: =( 365.25 * J126 / 7 ) * $E$97 * $E$98 * $E$99 -> 3221.7769
B128: Version 4 - FINAL
B131: Per week | C131: Per shower | D131: Flow | E131: Volume | F131: Volume | G131: Ratio | I131: Other use | J131: Total use | K131: Ratio
B132: [] | C132: [min] | D132: [L/min] | E132: [L/use] | F132: [L/week] | I132: [L/week] | J132: [L/week]
B133: 5 | C133: 5 | D133: 5 | E133: =C133 * D133 -> 25 | F133: =B133 * C133 * D133 -> 125 | G133: =F133 / $F$134 -> 0.42517007 | I133: =I134 -> 180.19355 | J133: =F133 + I133 -> 305.19355 | K133: =J133 / $J$134 -> 0.64360544 | M133: =( 365.25 * J133 / 7 ) * $E$97 * $E$98 * $E$99 -> 1249.282
B134: 6 | C134: 7 | D134: 7 | E134: =C134 * D134 -> 49 | F134: =B134 * C134 * D134 -> 294 | G134: =F134 / $F$134 -> 1 | I134: =( 1 - 0.62 ) * F134 / 0.62 -> 180.19355 | J134: =F134 + I134 -> 474.19355 | K134: =J134 / $J$134 -> 1 | M134: =( 365.25 * J134 / 7 ) * $E$97 * $E$98 * $E$99 -> 1941.0681
B135: 7 | C135: 9 | D135: 9 | E135: =C135 * D135 -> 81 | F135: =B135 * C135 * D135 -> 567 | G135: =F135 / $F$134 -> 1.9285714 | I135: =I134 -> 180.19355 | J135: =F135 + I135 -> 747.19355 | K135: =J135 / $J$134 -> 1.5757143 | M135: =( 365.25 * J135 / 7 ) * $E$97 * $E$98 * $E$99 -> 3058.5687
B153: Full table 9
K172: Season | L172: End use | M172: Mean | N172: Median | R172: Row Labels | S172: Average of Mean | V172: Row Labels | W172: Sum of Mean
K173: 1 - Spring | L173: Dishwasher | M173: 3.8 | N173: 2 | O173: 4.8 | P173: [2.0, 5.6] | R173: Dishwasher | S173: 4 | V173: 1 - Spring | W173: 238.8
K174: 1 - Spring | L174: Washing Machine | M174: 43.1 | N174: 22.4 | O174: 55 | P174: [22.4, 63.9] | R174: 1 - Spring | S174: 3.8 | V174: Dishwasher | W174: 3.8
K175: 1 - Spring | L175: Toilet | M175: 58 | N175: 20.5 | O175: 63.9 | P175: [33.9, 82.0] | R175: 2 - Summer | S175: 5.6 | V175: High Flow/Outdoor | W175: 31.9
...

Sheet WH
B2: Water heating calculation | O2: Electric storage water heater efficiency | R2: AS/NZS 4692 MEPS level with TPR
O3: Element = 100% | P3: Scenario | Q3: Tank size | R3: Standing loss (kWh/day) | S3: Standing heatloss per year
B4: Low | C4: 3 showers + X loads of laundry | O4: Standing losses | P4: Low | Q4: 130L | R4: 1.56 | S4: =R4*365 -> 569.4
B5: Medium | C5: 5 showers per person per week + Y loads of laundry | P5: Medium | Q5: 180L | R5: 1.76 | S5: =R5*365 -> 642.4
B6: High | C6: 5 showers + 2 baths per person per week + Z loads of laundry | P6: High | Q6: 250L | R6: 2.16 | S6: =R6*365 -> 788.4
B8: Or | P8: kJ | Q8: kWh
O9: Energy to heat 1L of water by 1 degree | P9: 4.128 | Q9: 0.0011466667
B10: Low | C10: 5 showers x 5 minutes per person per week + X loads of laundry
B11: Medium | C11: 5 showers x 10 minutes per person per week + Y loads of laundry
B12: High | C12: ? | O12: Gas cylinder | P12: Scenario | Q12: Tank size | R12: Standing loss (kWh/day) | S12: Standing heatloss per year
P13: Low | Q13: 130 | R13: =Q13^(0.3261)*0.6099 -> 2.9827411 | S13: =R13*365 -> 1088.7005
B14: Or | P14: Medium | Q14: 180 | R14: =Q14^(0.3261)*0.6099 -> 3.3166756 | S14: =R14*365 -> 1210.5866
P15: High | Q15: 250 | R15: =Q15^(0.3261)*0.6099 -> 3.691704 | S15: =R15*365 -> 1347.472
B16: Low | C16: 5 showers x 5-7 minutes per person per week + X loads of laundry | P16: Pilot rate (W) | Q16: 50
B17: Medium | C17: 7 showers x 8-10 minutes per person per week + Y loads of laundry | P17: Electricty rate
B18: High | C18: 7 showers x 10-15 minutes per person per week + Z loads of laundry
O20: Gas instantaneous | P20: Assumed efficiency from AS 4552 | Q20: 0.75 | R20: better to take an average of existing products
B21: Medium water use scenario is informed by data | P21: Electricty rate
B22: Low and high also informed by data (if available) but designed/selected to give +/- 30-50% between scenarios. | P22: Pilot rate
B24: Product efficiency variation | S24: =R27/24 -> 0.13819482
R25: AS/NZS 4692 MEPS level based on AU MEPS
B26: HP COP by region? | O26: Heat pump water heater | P26: Scenario | Q26: Tank size | R26: Standing loss (kWh/day) | S26: Standing heatloss per year
P27: Low | Q27: 180 | R27: =Q27^(0.3261)*0.6099 -> 3.3166756 | S27: =R27*365 -> 1210.5866
P28: Medium | Q28: 250 | R28: =Q28^(0.3261)*0.6099 -> 3.691704 | S28: =R28*365 -> 1347.472
P29: High | Q29: 310 | R29: =Q29^(0.3261)*0.6099 -> 3.959968 | S29: =R29*365 -> 1445.3883
P31: Zone | Q31: Assumed average COP
P32: Northland | Q32: 4
P33: Auckland | Q33: 3.8
P34: Bay of Plenty | Q34: 3.6
P35: Waikato | Q35: 3.4
P36: Rotorua | Q36: 3.2
P37: Taupo | Q37: 3
P38: Taranaki | Q38: 2.8
P39: East Coast | Q39: 2.6
P40: Wairarapa | Q40: 2.4
P41: Manawatu | Q41: 2.2
P42: Wellington | Q42: 2
P43: Marlborough | Q43: 2
... P45: Canterbury | Q45: 2
P46: Queenstown | Q46: 2 | Z46: Need to add pilot light rate
P47: Otago | Q47: 2
P48: Centreal Otago | Q48: 2
P49: Southland | Q49: 2 | S49: Need to correct for standing temperature vs tap temperature | X49: Assumed water temperature rise | Y49: Number of people | Z49: Electricity price | AA49: Gas price | AB49: Gas daily charge | AD49: Region
X50: 45 | Y50: 1 | Z50: 0.25 | AA50: 0.1 | AB50: 1.2 | AD50: Northland
O52: Water use units are per week per person | P52: Scenario | Q52: Showers | R52: Washes on warm wash (assumed hot water connection) | S52: Assumed litres washing machine | T52: Assumed litres shower per min | U52: Assumed shower length | V52: Hot water use shower | W52: Washing machine water use | X52: Total per person per week | Y52: Electric storage water heater energy consumption | Z52: Gas cylinder energy consumption | AA52: Gas instantaneous energy consumption | AB52: Heat pump water heater energy consumpiton | AC52: Electric storage water heater cost | AD52: Gas cylinder cost | AE52: Gas instantaneous energy cost | AF52: Heat pump water heater cost
P53: Low | Q53: 3 | R53: 1 | S53: 70 | T53: 10 | U53: 10 | V53: =U53*T53*Q53 -> 300 | W53: =R53*S53 -> 70 | X53: =V53+W53 -> 370 | Y53: =S4+$X53*$X$50*$Q$9*52*$Y$50 -> 1562.184 | Z53: =S13+$X53*$X$50*$Q$9*52*$Y$50*(1/$Q$20) -> 2412.4125 | AA53: =$X53*$X$50*$Q$9*52*$Y$50*(1/$Q$20) -> 1323.712 | AB53: =S27+$X53*$X$50*$Q$9*52*$Y$50*(1/VLOOKUP($AD$50,$P$32:$Q$49,2,FALSE)) -> 1458.7826 | AC53: =Y53*$Z$50 -> 390.54601 | AD53: =AB53*$AA$50+$AB$50*365 -> 583.87826 | AE53: =AA53*$AA$50+$AB$50*365 -> 570.3712 | AF53: =AB53*$Z$50 -> 364.69565
P54: Medium | Q54: 5 | R54: 2 | S54: 70 | T54: 10 | U54: 10 | V54: =U54*T54*Q54 -> 500 | W54: =R54*S54 -> 140 | X54: =V54+W54 -> 640 | Y54: =S5+$X54*$X$50*$Q$9*52*$Y$50 -> 2359.648 | Z54: =S14+$X54*$X$50*$Q$9*52*$Y$50*(1/$Q$20) -> 3500.2507 | AA54: =$X54*$X$50*$Q$9*52*$Y$50*(1/$Q$20) -> 2289.6641 | AB54: =S28+$X54*$X$50*$Q$9*52*$Y$50*(1/VLOOKUP($AD$50,$P$32:$Q$49,2,FALSE)) -> 1776.784 | AC54: =Y54*$Z$50 -> 589.91201 | AD54: =AB54*$AA$50+$AB$50*365 -> 615.6784 | AE54: =AA54*$AA$50+$AB$50*365 -> 666.96641 | AF54: =AB54*$Z$50 -> 444.19599
P55: High | Q55: 9 | R55: 3 | S55: 70 | T55: 10 | U55: 10 | V55: =U55*T55*Q55 -> 900 | W55: =R55*S55 -> 210 | X55: =V55+W55 -> 1110 | Y55: =S6+$X55*$X$50*$Q$9*52*$Y$50 -> 3766.7521 | Z55: =S15+$X55*$X$50*$Q$9*52*$Y$50*(1/$Q$20) -> 5318.6081 | AA55: =$X55*$X$50*$Q$9*52*$Y$50*(1/$Q$20) -> 3971.1361 | AB55: =S29+$X55*$X$50*$Q$9*52*$Y$50*(1/VLOOKUP($AD$50,$P$32:$Q$49,2,FALSE)) -> 2189.9764 | AC55: =Y55*$Z$50 -> 941.68802 | AD55: =AB55*$AA$50+$AB$50*365 -> 656.99764 | AE55: =AA55*$AA$50+$AB$50*365 -> 835.11361 | AF55: =AB55*$Z$50 -> 547.49409
L56: 6.569
B58: Clean version
B60: Constants | F60: Cylinder heat loss | G60: Electric storage water heaters | J60: Gas storage | M60: Heat pump water heater
B61: Energy to heat 1L of water by 1 degree (kWh) | C61: 0.0011466667 | F61: Scenario | G61: Tank size (L) | H61: Standing loss (kWh/day) | I61: Standing heatloss per year (kWh/year) | J61: Tank size (L) | K61: Standing loss (kWh/day) | L61: Standing heatloss per year (kWh/year) | M61: Tank size (L) | N61: Standing loss (kWh/day) | O61: Standing heatloss per year (kWh/year)
B62: Electricity price ($/kWh) | C62: 0.265 | F62: Low | G62: 130 | H62: 1.56 | I62: =H62*365 -> 569.4 | J62: 130 | K62: =(0.42+0.02*(J62^(2/3))+0.006*30)*24*0.277778*55/45 -> 9.0709005 | L62: =K62*365 -> 3310.8787 | M62: 170 | N62: =M62^(0.3261)*0.6099+0.2+0.2 -> 3.6554275 | O62: =N62*365 -> 1334.231
B63: Gas price ($/kWh) | C63: 0.1 | F63: Medium | G63: 180 | H63: 1.76 | I63: =H63*365 -> 642.4 | J63: 180 | K63: =(0.42+0.02*(J63^(2/3))+0.006*30)*24*0.277778*55/45 -> 10.084117 | L63: =K63*365 -> 3680.7026 | M63: 250 | N63: =M63^(0.3261)*0.6099+0.2+0.2 -> 4.091704 | O63: =N63*365 -> 1493.472
B64: Gas daily charge ($/day) | C64: 1.37 | F64: High | G64: 250 | H64: 2.16 | I64: =H64*365 -> 788.4 | J64: 260 | K64: =(0.42+0.02*(J64^(2/3))+0.006*30)*24*0.277778*55/45 -> 11.527416 | L64: =K64*365 -> 4207.5069 | M64: 300 | N64: =M64^(0.3261)*0.6099+0.2+0.2 -> 4.3178506 | O64: =N64*365 -> 1576.0155
B65: Set point of hot water out of system/tank (degree C) | C65: 65 | H65: Based on MEPS level with TPR valve 4692 | K65: 6.9.2 based on AS/NZS 4552.2:2010, 45 degree temperature rise, corrected to 55 degree temp rise | N65: Based on heat exchanger MEPS in AU 4692. 0.2 added for TPR valve, 0.2 added for two fittings
B66: Gas system thermal efficiency | C66: 0.8 | D66: Based on MEPS being 75%, MBIE syaing 95%, and Rinnai saying 90% | F66: Water consumption per week per person | J66: This needs to be adjusted from a storage temp of set point to what it is at the tab (10 degrees)
F67: Scenario | G67: Showers | H67: Washes on warm wash (assumed hot water connection) | I67: Assumed litres washing machine | J67: Assumed litres shower per min | K67: Assumed shower length | L67: Hot water use shower with temperature adjustment | M67: Washing machine water use with temperature adjustment | N67: Total per person per week (temperature adjustment) | O67: Water use per year | P67: Lost hot water for instantaneous | S67: Questions
B68: Electricity consumption (gas instantaneous) (kWh) | C68: 0.05 | F68: Low | G68: 3 | H68: 1 | I68: 70 | J68: 10 | K68: 8 | L68: =K68*J68*G68*$C$69/$C$65 -> 136.61538 | M68: =H68*I68*$C$70/$C$65 -> 38.769231 | N68: =L68+M68 -> 175.38462 | O68: =N68*52 -> 9120 | P68: =$C$73*(G68+H68) -> 8
B69: Shower set point | C69: 37 | D69: What is the Ideal Temperature to Shower in? - Rheem Asia – Rheem Manufacturing Company | F69: Medium | G69: 5 | H69: 2 | I69: 70 | J69: 10 | K69: 10 | L69: =K69*J69*G69*$C$69/$C$65 -> 284.61538 | M69: =H69*I69*$C$70/$C$65 -> 77.538462 | N69: =L69+M69 -> 362.15385 | O69: =N69*52 -> 18832 | P69: =$C$73*(G69+H69) -> 14
B70: Washing machine set point | C70: 36 | D70: Based of the temperature of set point of washing machine standard | F70: High | G70: 9 | H70: 3 | I70: 70 | J70: 10 | K70: 12 | L70: =K70*J70*G70*$C$69/$C$65 -> 614.76923 | M70: =H70*I70*$C$70/$C$65 -> 116.30769 | N70: =L70+M70 -> 731.07692 | O70: =N70*52 -> 38016 | P70: =$C$73*(G70+H70) -> 24
B71: GHG emissions gas (kg/kWh) | C71: 0.21
B72: GHG emissions electricity (kg/kWh) | C72: 0.129
B73: Instantaneous start- up water (L) volume | C73: 2 | D73: From old tool
H74: Hot water options | Building Performance | I74: Say thermal efficiency is 95% | M74: Temperature difference indoor degree C | N74: 5
H75: Rinnai INFINITY A-Series Gas Continuous Flow Water Heaters | rinnai.co.nz | I75: Rinnai say 92% or 80%
B76: Region based metrics | E76: Gas water heater low standing losses, assumed outdoor | F76: Gas water heater medium standing losses, assumed outdoor | G76: Gas water heater high standing losses, assumed outdoor | H76: HWPH low standing losses, assumed outdoor | I76: HWPH medium standing losses, assumed outdoor | J76: HWPH high standing losses, assumed outdoor | K76: ESWH low standing losses, assumed indoor | L76: ESWH medium standing losses, assumed indoor | M76: ESWH high standing losses, assumed indoor
B77: Zone | C77: Assumed average COP Heat pump average over a year | D77: Inlet water temperature average over a year | E77: Low Gas storage | F77: Medium Gas storage | G77: High Gas storage | H77: Low Heat pump | I77: Medium Heat pump | J77: High Heat pump | K77: Low Electric | L77: Medium Electric | M77: High Electric | P77: Calculation
B78: Northland | C78: =VLOOKUP(B78,$C$100:$E$117,3,FALSE) -> 3.0756996 | D78: =VLOOKUP(B78,$C$122:$D$139,2,FALSE) -> 15.520205 | E78: =($C$65-$D78)/55*$K$62 -> 8.1604781 | F78: =($C$65-$D78)/55*$K$63 -> 9.0720003 | G78: =($C$65-$D78)/55*$K$64 -> 10.37044 | H78: =($C$65-$D78)/55*$N$62 -> 3.2885418 | I78: =($C$65-$D78)/55*$N$63 -> 3.6810304 | J78: =($C$65-$D78)/55*$N$64 -> 3.8844793 | K78: =($C$65-$D78-$N$74)/55*$H$62 -> 1.2616087 | L78: =($C$65-$D78-$N$74)/55*$H$63 -> 1.4233534 | M78: =($C$65-$D78-$N$74)/55*$H$64 -> 1.7468428 | P78: Region | Q78: Auckland
B79: Auckland | C79: =VLOOKUP(B79,$C$100:$E$117,3,FALSE) -> 3.0769231 | D79: =VLOOKUP(B79,$C$122:$D$139,2,FALSE) -> 15.274315 | E79: =($C$65-$D79)/55*$K$62 -> 8.2010316 | F79: =($C$65-$D79)/55*$K$63 -> 9.1170837 | G79: =($C$65-$D79)/55*$K$64 -> 10.421976 | H79: =($C$65-$D79)/55*$N$62 -> 3.3048843 | I79: =($C$65-$D79)/55*$N$63 -> 3.6993233 | J79: =($C$65-$D79)/55*$N$64 -> 3.9037833 | K79: =($C$65-$D79-$N$74)/55*$H$62 -> 1.2685831 | L79: =($C$65-$D79-$N$74)/55*$H$63 -> 1.4312219 | M79: =($C$65-$D79-$N$74)/55*$H$64 -> 1.7564996 | P79: Number of people | Q79: 3
B80: Bay of Plenty | C80: =VLOOKUP(B80,$C$100:$E$117,3,FALSE) -> 2.9813398 | D80: =VLOOKUP(B80,$C$122:$D$139,2,FALSE) -> 14.932991 | E80: =($C$65-$D80)/55*$K$62 -> 8.2573247 | F80: =($C$65-$D80)/55*$K$63 -> 9.1796647 | G80: =($C$65-$D80)/55*$K$64 -> 10.493514 | H80: =($C$65-$D80)/55*$N$62 -> 3.3275695 | I80: =($C$65-$D80)/55*$N$63 -> 3.724716 | J80: =($C$65-$D80)/55*$N$64 -> 3.9305794 | K80: =($C$65-$D80-$N$74)/55*$H$62 -> 1.2782643 | L80: =($C$65-$D80-$N$74)/55*$H$63 -> 1.4421443 | M80: =($C$65-$D80-$N$74)/55*$H$64 -> 1.7699044 | P80: =MATCH(_xlfn.CONCAT($P83," ",Q$82),$B$76:$M$76,0) -> #N/A
B81: Waikato | C81: =VLOOKUP(B81,$C$100:$E$117,3,FALSE) -> 2.684924 | D81: =VLOOKUP(B81,$C$122:$D$139,2,FALSE) -> 13.536758 | E81: =($C$65-$D81)/55*$K$62 -> 8.487599 | F81: =($C$65-$D81)/55*$K$63 -> 9.4356606 | G81: =($C$65-$D81)/55*$K$64 -> 10.786149 | H81: =($C$65-$D81)/55*$N$62 -> 3.4203664 | I81: =($C$65-$D81)/55*$N$63 -> 3.8285882 | J81: =($C$65-$D81)/55*$N$64 -> 4.0401926 | K81: =($C$65-$D81-$N$74)/55*$H$62 -> 1.3178665 | L81: =($C$65-$D81-$N$74)/55*$H$63 -> 1.4868237 | M81: =($C$65-$D81-$N$74)/55*$H$64 -> 1.8247382 | P81: =VLOOKUP($Q$78,$B$77:$M$95,MATCH(_xlfn.CONCAT($P83," ",Q$82),$B$76:$M$76,0),FALSE) -> #N/A | Q81: Energy consumption | U81: Running cost per year | Y81: GHG emissions | AC81: Running cost over life
B82: Rotorua | C82: =VLOOKUP(B82,$C$100:$E$117,3,FALSE) -> 2.6523024 | D82: =VLOOKUP(B82,$C$122:$D$139,2,FALSE) -> 12.184132 | E82: =($C$65-$D82)/55*$K$62 -> 8.7106814 | F82: =($C$65-$D82)/55*$K$63 -> 9.6836612 | G82: =($C$65-$D82)/55*$K$64 -> 11.069645 | H82: =($C$65-$D82)/55*$N$62 -> 3.510265 | I82: =($C$65-$D82)/55*$N$63 -> 3.9292163 | J82: =($C$65-$D82)/55*$N$64 -> 4.1463823 | K82: =($C$65-$D82-$N$74)/55*$H$62 -> 1.3562319 | L82: =($C$65-$D82-$N$74)/55*$H$63 -> 1.5301078 | M82: =($C$65-$D82-$N$74)/55*$H$64 -> 1.8778595 | Q82: Electric | R82: Gas storage | S82: Gas instantaneous | T82: Heat pump | U82: Electric | V82: Gas storage | W82: Gas instantaneous | X82: Heat pump | Y82: Electric | Z82: Gas storage | AA82: Gas instantaneous | AB82: Heat pump | AC82: Electric | AD82: Gas storage | AE82: Gas instantaneous | AF82: Heat pump
B83: Taupo | C83: =VLOOKUP(B83,$C$100:$E$117,3,FALSE) -> 2.4167974 | D83: =VLOOKUP(B83,$C$122:$D$139,2,FALSE) -> 11.666553 | E83: =($C$65-$D83)/55*$K$62 -> 8.7960436 | F83: =($C$65-$D83)/55*$K$63 -> 9.7785583 | G83: =($C$65-$D83)/55*$K$64 -> 11.178125 | H83: =($C$65-$D83)/55*$N$62 -> 3.5446645 | I83: =($C$65-$D83)/55*$N$63 -> 3.9677214 | J83: =($C$65-$D83)/55*$N$64 -> 4.1870156 | K83: =($C$65-$D83-$N$74)/55*$H$62 -> 1.3709123 | L83: =($C$65-$D83-$N$74)/55*$H$63 -> 1.5466703 | M83: =($C$65-$D83-$N$74)/55*$H$64 -> 1.8981863 | P83: Low | Q83: =VLOOKUP($Q$78,$B$77:$M$95,MATCH(_xlfn.CONCAT($P83," ",Q$82),$B$77:$M$77,0),FALSE)*365+N68*($C$65-VLOOKUP($Q$78,$B$78:$D$95,3,FALSE))*$C$61*52*$Q$79 -> 2023.0668 | R83: =VLOOKUP($Q$78,$B$77:$M$95,MATCH(_xlfn.CONCAT($P83," ",R$82),$B$77:$M$77,0),FALSE)*365+N68*(($C$65-VLOOKUP($Q$78,$B$78:$D$95,3,FALSE))*$C$61*(1/$C$66)*52*$Q$79) -> 4943.4191 | S83: =(N68+P68)*(($C$65-VLOOKUP($Q$78,$B$78:$D$95,3,FALSE))*$C$61*(1/$C$66)*52*$Q$79)+$C$68*365 -> 2057.2418 | T83: =VLOOKUP($Q$78,$B$77:$M$95,MATCH(_xlfn.CONCAT($P83," ",T$82),$B$77:$M$77,0),FALSE)*365*1/VLOOKUP($Q$78,$B$78:$D$95,2,FALSE)+N68*($C$65-VLOOKUP($Q$78,$B$78:$D$95,3,FALSE))*(1/VLOOKUP($Q$78,$B$78:$D$95,2,FALSE)*$Q$79)*$C$61*52 -> 899.05295 | U83: =Q83*$C$62 -> 536.11271 | V83: =R83*$C$63+$C$64*365 -> 994.39191 | W83: =S83*$C$63+$C$64*365 -> 705.77418 | X83: =T83*$C$62 -> 238.24903 | Y83: =Q83*$C$72 -> 260.97562 | Z83: =R83*$C$71 -> 1038.118 | AA83: =S83*$C$71 -> 432.02078 | AB83: =T83*$C$72 -> 115.97783 | AC83: =U83*12 -> 6433.3525 | AD83: =V83*12 -> 11932.703 | AE83: =W83*12 -> 8469.2902 | AF83: =X83*12 -> 2858.9884
B84: Taranaki | C84: =VLOOKUP(B84,$C$100:$E$117,3,FALSE) -> 2.9308053 | D84: =VLOOKUP(B84,$C$122:$D$139,2,FALSE) -> 13.594292 | E84: =($C$65-$D84)/55*$K$62 -> 8.4781102 | F84: =($C$65-$D84)/55*$K$63 -> 9.4251119 | G84: =($C$65-$D84)/55*$K$64 -> 10.774091 | H84: =($C$65-$D84)/55*$N$62 -> 3.4165425 | I84: =($C$65-$D84)/55*$N$63 -> 3.824308 | J84: =($C$65-$D84)/55*$N$64 -> 4.0356758 | K84: =($C$65-$D84-$N$74)/55*$H$62 -> 1.3162346 | L84: =($C$65-$D84-$N$74)/55*$H$63 -> 1.4849826 | M84: =($C$65-$D84-$N$74)/55*$H$64 -> 1.8224787 | P84: Medium | Q84: =VLOOKUP($Q$78,$B$77:$M$95,MATCH(_xlfn.CONCAT($P84," ",Q$82),$B$77:$M$77,0),FALSE)*365+N69*($C$65-VLOOKUP($Q$78,$B$78:$D$95,3,FALSE))*$C$61*52*$Q$79 -> 3743.7294 | R84: =VLOOKUP($Q$78,$B$77:$M$95,MATCH(_xlfn.CONCAT($P84," ",R$82),$B$77:$M$77,0),FALSE)*365+N69*(($C$65-VLOOKUP($Q$78,$B$78:$D$95,3,FALSE))*$C$61*(1/$C$66)*52*$Q$79) -> 7354.4023 | S84: =(N69+P69)*(($C$65-VLOOKUP($Q$78,$B$78:$D$95,3,FALSE))*$C$61*(1/$C$66)*52*$Q$79)+$C$68*365 -> 4200.578 | T84: =VLOOKUP($Q$78,$B$77:$M$95,MATCH(_xlfn.CONCAT($P84," ",T$82),$B$77:$M$77,0),FALSE)*365*1/VLOOKUP($Q$78,$B$78:$D$95,2,FALSE)+N69*($C$65-VLOOKUP($Q$78,$B$78:$D$95,3,FALSE))*(1/VLOOKUP($Q$78,$B$78:$D$95,2,FALSE)*$Q$79)*$C$61*52 -> 1485.7656 | U84: =Q84*$C$62 -> 992.08829 | V84: =R84*$C$63+$C$64*365 -> 1235.4902 | W84: =S84*$C$63+$C$64*365 -> 920.1078 | X84: =T84*$C$62 -> 393.72788 | Y84: =Q84*$C$72 -> 482.94109 | Z84: =R84*$C$71 -> 1544.4245 | AA84: =S84*$C$71 -> 882.12139 | AB84: =T84*$C$72 -> 191.66376 | AC84: =U84*12 -> 11905.059 | AD84: =V84*12 -> 14825.883 | AE84: =W84*12 -> 11041.294 | AF84: =X84*12 -> 4724.7346
B85: East Coast | C85: =VLOOKUP(B85,$C$100:$E$117,3,FALSE) -> 2.806299 | D85: =VLOOKUP(B85,$C$122:$D$139,2,FALSE) -> 14.02089 | E85: =($C$65-$D85)/55*$K$62 -> 8.4077533 | F85: =($C$65-$D85)/55*$K$63 -> 9.3468961 | G85: =($C$65-$D85)/55*$K$64 -> 10.68468 | H85: =($C$65-$D85)/55*$N$62 -> 3.3881898 | I85: =($C$65-$D85)/55*$N$63 -> 3.7925714 | J85: =($C$65-$D85)/55*$N$64 -> 4.0021851 | K85: =($C$65-$D85-$N$74)/55*$H$62 -> 1.3041347 | L85: =($C$65-$D85-$N$74)/55*$H$63 -> 1.4713315 | M85: =($C$65-$D85-$N$74)/55*$H$64 -> 1.805725 | P85: High | Q85: =VLOOKUP($Q$78,$B$77:$M$95,MATCH(_xlfn.CONCAT($P85," ",Q$82),$B$77:$M$77,0),FALSE)*365+N70*($C$65-VLOOKUP($Q$78,$B$78:$D$95,3,FALSE))*$C$61*52*$Q$79 -> 7144.001 | R85: =VLOOKUP($Q$78,$B$77:$M$95,MATCH(_xlfn.CONCAT($P85," ",R$82),$B$77:$M$77,0),FALSE)*365+N70*(($C$65-VLOOKUP($Q$78,$B$78:$D$95,3,FALSE))*$C$61*(1/$C$66)*52*$Q$79) -> 11932.619 | S85: =(N70+P70)*(($C$65-VLOOKUP($Q$78,$B$78:$D$95,3,FALSE))*$C$61*(1/$C$66)*52*$Q$79)+$C$68*365 -> 8413.6962 | T85: =VLOOKUP($Q$78,$B$77:$M$95,MATCH(_xlfn.CONCAT($P85," ",T$82),$B$77:$M$77,0),FALSE)*365*1/VLOOKUP($Q$78,$B$78:$D$95,2,FALSE)+N70*($C$65-VLOOKUP($Q$78,$B$78:$D$95,3,FALSE))*(1/VLOOKUP($Q$78,$B$78:$D$95,2,FALSE)*$Q$79)*$C$61*52 -> 2576.5218 | U85: =Q85*$C$62 -> 1893.1603 | V85: =R85*$C$63+$C$64*365 -> 1693.3119 | W85: =S85*$C$63+$C$64*365 -> 1341.4196 | X85: =T85*$C$62 -> 682.77829 | Y85: =Q85*$C$72 -> 921.57613 | Z85: =R85*$C$71 -> 2505.8501 | AA85: =S85*$C$71 -> 1766.8762 | AB85: =T85*$C$72 -> 332.37132 | AC85: =U85*12 -> 22717.923 | AD85: =V85*12 -> 20319.743 | AE85: =W85*12 -> 16097.035 | AF85: =X85*12 -> 8193.3395
B86: Wairarapa | C86: =VLOOKUP(B86,$C$100:$E$117,3,FALSE) -> 2.4897221 | D86: =VLOOKUP(B86,$C$122:$D$139,2,FALSE) -> 12.442123 | E86: =($C$65-$D86)/55*$K$62 -> 8.6681322 | F86: =($C$65-$D86)/55*$K$63 -> 9.6363592 | G86: =($C$65-$D86)/55*$K$64 -> 11.015573 | H86: =($C$65-$D86)/55*$N$62 -> 3.4931183 | I86: =($C$65-$D86)/55*$N$63 -> 3.9100232 | J86: =($C$65-$D86)/55*$N$64 -> 4.1261284 | K86: =($C$65-$D86-$N$74)/55*$H$62 -> 1.3489143 | L86: =($C$65-$D86-$N$74)/55*$H$63 -> 1.5218521 | M86: =($C$65-$D86-$N$74)/55*$H$64 -> 1.8677275
B87: Manawatu | C87: =VLOOKUP(B87,$C$100:$E$117,3,FALSE) -> 2.8634024 | D87: =VLOOKUP(B87,$C$122:$D$139,2,FALSE) -> 13.155023 | E87: =($C$65-$D87)/55*$K$62 -> 8.5505569 | F87: =($C$65-$D87)/55*$K$63 -> 9.5056508 | G87: =($C$65-$D87)/55*$K$64 -> 10.866157 | H87: =($C$65-$D87)/55*$N$62 -> 3.4457374 | I87: =($C$65-$D87)/55*$N$63 -> 3.8569873 | J87: =($C$65-$D87)/55*$N$64 -> 4.0701612 | K87: =($C$65-$D87-$N$74)/55*$H$62 -> 1.3286939 | L87: =($C$65-$D87-$N$74)/55*$H$63 -> 1.4990393 | M87: =($C$65-$D87-$N$74)/55*$H$64 -> 1.83973 | P87: Calculation | X87: =(U83-X83)/U83 -> 0.55559899
B88: Wellington | C88: =VLOOKUP(B88,$C$100:$E$117,3,FALSE) -> 3.093896 | D88: =VLOOKUP(B88,$C$122:$D$139,2,FALSE) -> 12.834018 | E88: =($C$65-$D88)/55*$K$62 -> 8.6034987 | F88: =($C$65-$D88)/55*$K$63 -> 9.5645063 | G88: =($C$65-$D88)/55*$K$64 -> 10.933436 | H88: =($C$65-$D88)/55*$N$62 -> 3.4670721 | I88: =($C$65-$D88)/55*$N$63 -> 3.8808683 | J88: =($C$65-$D88)/55*$N$64 -> 4.0953621 | K88: =($C$65-$D88-$N$74)/55*$H$62 -> 1.3377988 | L88: =($C$65-$D88-$N$74)/55*$H$63 -> 1.5093114 | M88: =($C$65-$D88-$N$74)/55*$H$64 -> 1.8523367 | P88: Region | Q88: Manawatu | X88: =(U84-X84)/U84 -> 0.60313222
B89: Marlborough | C89: =VLOOKUP(B89,$C$100:$E$117,3,FALSE) -> 2.7795363 | D89: =VLOOKUP(B89,$C$122:$D$139,2,FALSE) -> 12.905936 | E89: =($C$65-$D89)/55*$K$62 -> 8.5916376 | F89: =($C$65-$D89)/55*$K$63 -> 9.5513203 | G89: =($C$65-$D89)/55*$K$64 -> 10.918363 | H89: =($C$65-$D89)/55*$N$62 -> 3.4622922 | I89: =($C$65-$D89)/55*$N$63 -> 3.875518 | J89: =($C$65-$D89)/55*$N$64 -> 4.0897161 | K89: =($C$65-$D89-$N$74)/55*$H$62 -> 1.3357589 | L89: =($C$65-$D89-$N$74)/55*$H$63 -> 1.50701 | M89: =($C$65-$D89-$N$74)/55*$H$64 -> 1.8495123 | P89: Number of people | Q89: 3 | X89: =(U85-X85)/U85 -> 0.6393447
B90: West Coast | C90: =VLOOKUP(B90,$C$100:$E$117,3,FALSE) -> 2.7539758 | D90: =VLOOKUP(B90,$C$122:$D$139,2,FALSE) -> 11.413699 | E90: =($C$65-$D90)/55*$K$62 -> 8.8377456 | F90: =($C$65-$D90)/55*$K$63 -> 9.8249184 | G90: =($C$65-$D90)/55*$K$64 -> 11.23112 | H90: =($C$65-$D90)/55*$N$62 -> 3.5614698 | I90: =($C$65-$D90)/55*$N$63 -> 3.9865324 | J90: =($C$65-$D90)/55*$N$64 -> 4.2068663 | K90: =($C$65-$D90-$N$74)/55*$H$62 -> 1.3780842 | L90: =($C$65-$D90-$N$74)/55*$H$63 -> 1.5547616 | M90: =($C$65-$D90-$N$74)/55*$H$64 -> 1.9081166
B91: Canterbury | C91: =VLOOKUP(B91,$C$100:$E$117,3,FALSE) -> 2.4538879 | D91: =VLOOKUP(B91,$C$122:$D$139,2,FALSE) -> 11.323516 | E91: =($C$65-$D91)/55*$K$62 -> 8.852619 | F91: =($C$65-$D91)/55*$K$63 -> 9.8414532 | G91: =($C$65-$D91)/55*$K$64 -> 11.250021 | H91: =($C$65-$D91)/55*$N$62 -> 3.5674636 | I91: =($C$65-$D91)/55*$N$63 -> 3.9932415 | J91: =($C$65-$D91)/55*$N$64 -> 4.2139462 | K91: =($C$65-$D91-$N$74)/55*$H$62 -> 1.3806421 | L91: =($C$65-$D91-$N$74)/55*$H$63 -> 1.5576475 | M91: =($C$65-$D91-$N$74)/55*$H$64 -> 1.9116583 | Q91: Energy consumption | U91: Running cost per year | Y91: GHG emissions | AC91: Running cost over life
B92: Queenstown | C92: =VLOOKUP(B92,$C$100:$E$117,3,FALSE) -> 2.2496073 | D92: =VLOOKUP(B92,$C$122:$D$139,2,FALSE) -> 9.4969178 | E92: =($C$65-$D92)/55*$K$62 -> 9.1538716 | F92: =($C$65-$D92)/55*$K$63 -> 10.176356 | G92: =($C$65-$D92)/55*$K$64 -> 11.632857 | H92: =($C$65-$D92)/55*$N$62 -> 3.6888635 | I92: =($C$65-$D92)/55*$N$63 -> 4.1291306 | J92: =($C$65-$D92)/55*$N$64 -> 4.3573458 | K92: =($C$65-$D92-$N$74)/55*$H$62 -> 1.4324511 | L92: =($C$65-$D92-$N$74)/55*$H$63 -> 1.6160986 | M92: =($C$65-$D92-$N$74)/55*$H$64 -> 1.9833938 | Q92: Electric | R92: Gas storage | S92: Gas instantaneous | T92: Heat pump | U92: Electric | V92: Gas storage | W92: Gas instantaneous | X92: Heat pump | Y92: Electric | Z92: Gas storage | AA92: Gas instantaneous | AB92: Heat pump | AC92: Electric | AD92: Gas storage | AE92: Gas instantaneous | AF92: Heat pump
B93: Otago | C93: =VLOOKUP(B93,$C$100:$E$117,3,FALSE) -> 2.8966981 | D93: =VLOOKUP(B93,$C$122:$D$139,2,FALSE) -> 10.788242 | E93: =($C$65-$D93)/55*$K$62 -> 8.9408993 | F93: =($C$65-$D93)/55*$K$63 -> 9.9395944 | G93: =($C$65-$D93)/55*$K$64 -> 11.362209 | H93: =($C$65-$D93)/55*$N$62 -> 3.6030391 | I93: =($C$65-$D93)/55*$N$63 -> 4.033063 | J93: =($C$65-$D93)/55*$N$64 -> 4.2559686 | K93: =($C$65-$D93-$N$74)/55*$H$62 -> 1.3958244 | L93: =($C$65-$D93-$N$74)/55*$H$63 -> 1.5747763 | M93: =($C$65-$D93-$N$74)/55*$H$64 -> 1.93268 | P93: Low | Q93: =VLOOKUP($Q$88,$B$77:$M$95,MATCH(_xlfn.CONCAT($P93," ",Q$92),$B$77:$M$77,0),FALSE)*365+N68*($C$65-VLOOKUP($Q$88,$B$78:$D$95,3,FALSE))*$C$61*52*$Q$89 -> 2111.4954 | R93: =VLOOKUP($Q$88,$B$77:$M$95,MATCH(_xlfn.CONCAT($P93," ",R$92),$B$77:$M$77,0),FALSE)*365+N68*(($C$65-VLOOKUP($Q$88,$B$78:$D$95,3,FALSE))*$C$61*(1/$C$66)*52*$Q$89) -> 5154.106 | S93: =(N68+P68)*(($C$65-VLOOKUP($Q$88,$B$78:$D$95,3,FALSE))*$C$61*(1/$C$66)*52*$Q$89)+$C$68*365 -> 2144.143 | T93: =VLOOKUP($Q$88,$B$77:$M$95,MATCH(_xlfn.CONCAT($P93," ",T$92),$B$77:$M$77,0),FALSE)*365*1/VLOOKUP($Q$88,$B$78:$D$95,2,FALSE)+N68*($C$65-VLOOKUP($Q$88,$B$78:$D$95,3,FALSE))*(1/VLOOKUP($Q$88,$B$78:$D$95,2,FALSE)*$Q$89)*$C$61*52 -> 1007.2689 | U93: =Q93*$C$62 -> 559.54629 | V93: =R93*$C$63+$C$64*365 -> 1015.4606 | W93: =S93*$C$63+$C$64*365 -> 714.4643 | X93: =T93*$C$62 -> 266.92627 | Y93: =Q93*$C$72 -> 272.38291 | Z93: =R93*$C$71 -> 1082.3622 | AA93: =S93*$C$71 -> 450.27003 | AB93: =T93*$C$72 -> 129.93769 | AC93: =U93*12 -> 6714.5554 | AD93: =V93*12 -> 12185.527 | AE93: =W93*12 -> 8573.5716 | AF93: =X93*12 -> 3203.1152
B94: Centreal Otago | C94: =VLOOKUP(B94,$C$100:$E$117,3,FALSE) -> 2.0618099 | D94: =VLOOKUP(B94,$C$122:$D$139,2,FALSE) -> 9.4558219 | E94: =($C$65-$D94)/55*$K$62 -> 9.1606493 | F94: =($C$65-$D94)/55*$K$63 -> 10.18389 | G94: =($C$65-$D94)/55*$K$64 -> 11.64147 | H94: =($C$65-$D94)/55*$N$62 -> 3.6915948 | I94: =($C$65-$D94)/55*$N$63 -> 4.1321879 | J94: =($C$65-$D94)/55*$N$64 -> 4.3605721 | K94: =($C$65-$D94-$N$74)/55*$H$62 -> 1.4336167 | L94: =($C$65-$D94-$N$74)/55*$H$63 -> 1.6174137 | M94: =($C$65-$D94-$N$74)/55*$H$64 -> 1.9850077 | P94: Medium | Q94: =VLOOKUP($Q$88,$B$77:$M$95,MATCH(_xlfn.CONCAT($P94," ",Q$92),$B$77:$M$77,0),FALSE)*365+N69*($C$65-VLOOKUP($Q$88,$B$78:$D$95,3,FALSE))*$C$61*52*$Q$89 -> 3905.7749 | R94: =VLOOKUP($Q$88,$B$77:$M$95,MATCH(_xlfn.CONCAT($P94," ",R$92),$B$77:$M$77,0),FALSE)*365+N69*(($C$65-VLOOKUP($Q$88,$B$78:$D$95,3,FALSE))*$C$61*(1/$C$66)*52*$Q$89) -> 7667.8445 | S94: =(N69+P69)*(($C$65-VLOOKUP($Q$88,$B$78:$D$95,3,FALSE))*$C$61*(1/$C$66)*52*$Q$89)+$C$68*365 -> 4378.8275 | T94: =VLOOKUP($Q$88,$B$77:$M$95,MATCH(_xlfn.CONCAT($P94," ",T$92),$B$77:$M$77,0),FALSE)*365*1/VLOOKUP($Q$88,$B$78:$D$95,2,FALSE)+N69*($C$65-VLOOKUP($Q$88,$B$78:$D$95,3,FALSE))*(1/VLOOKUP($Q$88,$B$78:$D$95,2,FALSE)*$Q$89)*$C$61*52 -> 1664.6022 | U94: =Q94*$C$62 -> 1035.0303 | V94: =R94*$C$63+$C$64*365 -> 1266.8345 | W94: =S94*$C$63+$C$64*365 -> 937.93275 | X94: =T94*$C$62 -> 441.11958 | Y94: =Q94*$C$72 -> 503.84496 | Z94: =R94*$C$71 -> 1610.2473 | AA94: =S94*$C$71 -> 919.55377 | AB94: =T94*$C$72 -> 214.73368 | AC94: =U94*12 -> 12420.364 | AD94: =V94*12 -> 15202.013 | AE94: =W94*12 -> 11255.193 | AF94: =X94*12 -> 5293.435
B95: Southland | C95: =VLOOKUP(B95,$C$100:$E$117,3,FALSE) -> 2.6844569 | D95: =VLOOKUP(B95,$C$122:$D$139,2,FALSE) -> 9.9902968 | E95: =($C$65-$D95)/55*$K$62 -> 9.0725008 | F95: =($C$65-$D95)/55*$K$63 -> 10.085896 | G95: =($C$65-$D95)/55*$K$64 -> 11.52945 | H95: =($C$65-$D95)/55*$N$62 -> 3.6560724 | I95: =($C$65-$D95)/55*$N$63 -> 4.0924258 | J95: =($C$65-$D95)/55*$N$64 -> 4.3186124 | K95: =($C$65-$D95-$N$74)/55*$H$62 -> 1.418457 | L95: =($C$65-$D95-$N$74)/55*$H$63 -> 1.6003105 | M95: =($C$65-$D95-$N$74)/55*$H$64 -> 1.9640174 | P95: High | Q95: =VLOOKUP($Q$88,$B$77:$M$95,MATCH(_xlfn.CONCAT($P95," ",Q$92),$B$77:$M$77,0),FALSE)*365+N70*($C$65-VLOOKUP($Q$88,$B$78:$D$95,3,FALSE))*$C$61*52*$Q$89 -> 7451.5306 | R95: =VLOOKUP($Q$88,$B$77:$M$95,MATCH(_xlfn.CONCAT($P95," ",R$92),$B$77:$M$77,0),FALSE)*365+N70*(($C$65-VLOOKUP($Q$88,$B$78:$D$95,3,FALSE))*$C$61*(1/$C$66)*52*$Q$89) -> 12441.184 | S95: =(N70+P70)*(($C$65-VLOOKUP($Q$88,$B$78:$D$95,3,FALSE))*$C$61*(1/$C$66)*52*$Q$89)+$C$68*365 -> 8771.5073 | T95: =VLOOKUP($Q$88,$B$77:$M$95,MATCH(_xlfn.CONCAT($P95," ",T$92),$B$77:$M$77,0),FALSE)*365*1/VLOOKUP($Q$88,$B$78:$D$95,2,FALSE)+N70*($C$65-VLOOKUP($Q$88,$B$78:$D$95,3,FALSE))*(1/VLOOKUP($Q$88,$B$78:$D$95,2,FALSE)*$Q$89)*$C$61*52 -> 2886.6491 | U95: =Q95*$C$62 -> 1974.6556 | V95: =R95*$C$63+$C$64*365 -> 1744.1684 | W95: =S95*$C$63+$C$64*365 -> 1377.2007 | X95: =T95*$C$62 -> 764.96202 | Y95: =Q95*$C$72 -> 961.24745 | Z95: =R95*$C$71 -> 2612.6486 | AA95: =S95*$C$71 -> 1842.0165 | AB95: =T95*$C$72 -> 372.37774 | AC95: =U95*12 -> 23695.867 | AD95: =V95*12 -> 20930.02 | AE95: =W95*12 -> 16526.409 | AF95: =X95*12 -> 9179.5442
X97: =(U93-X93)/U93 -> 0.52295945
V98: =(V94-X94)*12 -> 9908.5784 | W98: =V98-7000 -> 2908.5784 | X98: =(U94-X94)/U94 -> 0.57381
B99: Zone | D99: Using AC HSPF and calculating it as a ratio of auckland to other regions, based on registration data | F99: Savings over electric % | V99: =(V94-U94)*12 -> 2781.6493 | X99: =(U95-X95)/U95 -> 0.61260991
B100: Auckland | C100: Auckland | D100: 1 | E100: =J103 -> 3.0769231 | F100: =100-100/E100 -> 67.5
B101: fhsp_bay_of_plenty_tauranga | C101: Bay of Plenty | D101: 0.96893544 | E101: =$E$100*D101 -> 2.9813398 | F101: =100-100/E101 -> 66.458034 | I101: EECA quote saving of 60% to 75% | J101: Hot water heat pumps in the home | EECA
B102: fhsp_canterbury_christchurch | C102: Canterbury | D102: 0.79751357 | E102: =$E$100*D102 -> 2.4538879 | F102: =100-100/E102 -> 59.248342 | I102: Average of this | J102: =(60+75)/2 -> 67.5 | V102: =(V94-X94)/26 -> 31.758264 | W102: =7000/V102 -> 220.41507
B103: fhsp_central_otago_lauder | C103: Centreal Otago | D103: 0.67008823 | E103: =$E$100*D103 -> 2.0618099 | F103: =100-100/E103 -> 51.498924 | I103: COP | J103: =1/(100-J102)*100 -> 3.0769231 | W103: =W102/26 -> 8.4775027
B104: fhsp_east_coast_napier | C104: East Coast | D104: 0.91204716 | E104: =$E$100*D104 -> 2.806299 | F104: =100-100/E104 -> 64.365878
B105: fhsp_manawatu_paraparaumu | C105: Manawatu | D105: 0.93060578 | E105: =$E$100*D105 -> 2.8634024 | F105: =100-100/E105 -> 65.076512
B106: fhsp_nelson_marlborough_nelson | C106: Marlborough | D106: 0.90334929 | E106: =$E$100*D106 -> 2.7795363 | F106: =100-100/E106 -> 64.022776
B107: fhsp_northland_kaitaia | C107: Northland | D107: 0.99960237 | E107: =$E$100*D107 -> 3.0756996 | F107: =100-100/E107 -> 67.487072
B108: fhsp_otago_dunedin | C108: Otago | D108: 0.94142689 | E108: =$E$100*D108 -> 2.8966981 | F108: =100-100/E108 -> 65.477935
B109: fhsp_queenstown_lakes_queenstown | C109: Queenstown | D109: 0.73112237 | E109: =$E$100*D109 -> 2.2496073 | F109: =100-100/E109 -> 55.547797
B110: fhsp_rotorua_rotorua | C110: Rotorua | D110: 0.86199828 | E110: =$E$100*D110 -> 2.6523024 | F110: =100-100/E110 -> 62.296908
...

Sheet WH (2)
B2: Water heating calculation
O4: Heat pump water heater COP estimate by climate zone
B5: Variable | C5: Value | D5: comment | F5: Heat pump water heater performance | O5: Zone | P5: Zone | Q5: Using AC HSPF and calculating it as a ratio of auckland to other regions, based on registration data | R5: COP | S5: Savings over electric % | X5: Calculation
B6: Energy to heat 1L of water by 1 degree (kWh) | C6: 0.0011466667 | D6: A fact | F6: EECA quote saving of 60% to 75% | G6: Hot water heat pumps in the home | EECA | O6: Auckland | P6: Auckland | Q6: 1 | R6: =G8 -> 3.0769231 | S6: =100-100/R6 -> 67.5 | X6: Region | Y6: Auckland
B7: Electricity price ($/kWh) | C7: 0.265 | D7: Global to tool | F7: Average of this | G7: =(60+75)/2 -> 67.5 | O7: fhsp_bay_of_plenty_tauranga | P7: Bay of Plenty | Q7: 0.96893544 | R7: =$R$6*Q7 -> 2.9813398 | S7: =100-100/R7 -> 66.458034 | X7: Number of people | Y7: 3
B8: Gas price ($/kWh) | C8: 0.1 | D8: Global to tool | F8: COP | G8: =1/(100-G7)*100 -> 3.0769231 | O8: fhsp_canterbury_christchurch | P8: Canterbury | Q8: 0.79751357 | R8: =$R$6*Q8 -> 2.4538879 | S8: =100-100/R8 -> 59.248342
B9: Gas daily charge ($/day) | C9: 1.37 | D9: Global to tool | O9: fhsp_central_otago_lauder | P9: Centreal Otago | Q9: 0.67008823 | R9: =$R$6*Q9 -> 2.0618099 | S9: =100-100/R9 -> 51.498924 | Y9: Energy consumption per year | AC9: Running cost per year | AG9: GHG emissions | AK9: Running cost over life
B10: Set point of hot water out of system/tank (degree C) | C10: 65 | D10: Global to tool | O10: fhsp_east_coast_napier | P10: East Coast | Q10: 0.91204716 | R10: =$R$6*Q10 -> 2.806299 | S10: =100-100/R10 -> 64.365878 | Y10: Electric | Z10: Gas storage | AA10: Gas instantaneous | AB10: Heat pump | AC10: Electric | AD10: Gas storage | AE10: Gas instantaneous | AF10: Heat pump | AG10: Electric | AH10: Gas storage | AI10: Gas instantaneous | AJ10: Heat pump | AK10: Electric | AL10: Gas storage | AM10: Gas instantaneous | AN10: Heat pump
B11: Gas system thermal efficiency | C11: 0.8 | D11: Based on MEPS being 75%, MBIE saying 95%, and Rinnai saying 90%: - https://rinnai.co.nz/water-heating/gas-hot-water-systems/residential-use/rinnai-infinity-a-series-internal-and-external - https://www.building.govt.nz/getting-started/smarter-homes-guides/water-and-waste/hot-water-options#:~:text=Gas%20is%20only%20used%20when,to%2095%20per%20cent%20efficient. | O11: fhsp_manawatu_paraparaumu | P11: Manawatu | Q11: 0.93060578 | R11: =$R$6*Q11 -> 2.8634024 | S11: =100-100/R11 -> 65.076512 | X11: Low | Y11: =VLOOKUP($Y$6,$B$36:$M$54,MATCH(_xlfn.CONCAT($X11," ",Y$10),$B$36:$M$36,0),FALSE)*365+J29*($C$10-VLOOKUP($Y$6,$B$37:$D$54,3,FALSE))*$C$6*52*$Y$7 -> 2023.0668 | Z11: =VLOOKUP($Y$6,$B$36:$M$54,MATCH(_xlfn.CONCAT($X11," ",Z$10),$B$36:$M$36,0),FALSE)*365+J29*(($C$10-VLOOKUP($Y$6,$B$37:$D$54,3,FALSE))*$C$6*(1/$C$11)*52*$Y$7) -> 4943.4191 | AA11: =(J29+L29)*(($C$10-VLOOKUP($Y$6,$B$37:$D$54,3,FALSE))*$C$6*(1/$C$11)*52*$Y$7)+$C$12*365 -> 2057.2418 | AB11: =VLOOKUP($Y$6,$B$36:$M$54,MATCH(_xlfn.CONCAT($X11," ",AB$10),$B$36:$M$36,0),FALSE)*365*1/VLOOKUP($Y$6,$B$37:$D$54,2,FALSE)+J29*($C$10-VLOOKUP($Y$6,$B$37:$D$54,3,FALSE))*(1/VLOOKUP($Y$6,$B$37:$D$54,2,FALSE)*$Y$7)*$C$6*52 -> 899.05295 | AC11: =Y11*$C$7 -> 536.11271 | AD11: =Z11*$C$8+$C$9*365 -> 994.39191 | AE11: =AA11*$C$8+$C$9*365 -> 705.77418 | AF11: =AB11*$C$7 -> 238.24903 | AG11: =Y11*$C$16 -> 260.97562 | AH11: =Z11*$C$15 -> 1038.118 | AI11: =AA11*$C$15 -> 432.02078 | AJ11: =AB11*$C$16 -> 115.97783 | AK11: =AC11*12 -> 6433.3525 | AL11: =AD11*12 -> 11932.703 | AM11: =AE11*12 -> 8469.2902 | AN11: =AF11*12 -> 2858.9884
B12: Electricity consumption (gas instantaneous) (kWh) | C12: 0.05 | D12: Based on registration data | O12: fhsp_nelson_marlborough_nelson | P12: Marlborough | Q12: 0.90334929 | R12: =$R$6*Q12 -> 2.7795363 | S12: =100-100/R12 -> 64.022776 | X12: Medium | Y12: =VLOOKUP($Y$6,$B$36:$M$54,MATCH(_xlfn.CONCAT($X12," ",Y$10),$B$36:$M$36,0),FALSE)*365+J30*($C$10-VLOOKUP($Y$6,$B$37:$D$54,3,FALSE))*$C$6*52*$Y$7 -> 3743.7294 | Z12: =VLOOKUP($Y$6,$B$36:$M$54,MATCH(_xlfn.CONCAT($X12," ",Z$10),$B$36:$M$36,0),FALSE)*365+J30*(($C$10-VLOOKUP($Y$6,$B$37:$D$54,3,FALSE))*$C$6*(1/$C$11)*52*$Y$7) -> 7354.4023 | AA12: =(J30+L30)*(($C$10-VLOOKUP($Y$6,$B$37:$D$54,3,FALSE))*$C$6*(1/$C$11)*52*$Y$7)+$C$12*365 -> 4200.578 | AB12: =VLOOKUP($Y$6,$B$36:$M$54,MATCH(_xlfn.CONCAT($X12," ",AB$10),$B$36:$M$36,0),FALSE)*365*1/VLOOKUP($Y$6,$B$37:$D$54,2,FALSE)+J30*($C$10-VLOOKUP($Y$6,$B$37:$D$54,3,FALSE))*(1/VLOOKUP($Y$6,$B$37:$D$54,2,FALSE)*$Y$7)*$C$6*52 -> 1485.7656 | AC12: =Y12*$C$7 -> 992.08829 | AD12: =Z12*$C$8+$C$9*365 -> 1235.4902 | AE12: =AA12*$C$8+$C$9*365 -> 920.1078 | AF12: =AB12*$C$7 -> 393.72788 | AG12: =Y12*$C$16 -> 482.94109 | AH12: =Z12*$C$15 -> 1544.4245 | AI12: =AA12*$C$15 -> 882.12139 | AJ12: =AB12*$C$16 -> 191.66376 | AK12: =AC12*12 -> 11905.059 | AL12: =AD12*12 -> 14825.883 | AM12: =AE12*12 -> 11041.294 | AN12: =AF12*12 -> 4724.7346
B13: Shower set point | C13: 37 | D13: What is the Ideal Temperature to Shower in? - Rheem Asia – Rheem Manufacturing Company | O13: fhsp_northland_kaitaia | P13: Northland | Q13: 0.99960237 | R13: =$R$6*Q13 -> 3.0756996 | S13: =100-100/R13 -> 67.487072 | X13: High | Y13: =VLOOKUP($Y$6,$B$36:$M$54,MATCH(_xlfn.CONCAT($X13," ",Y$10),$B$36:$M$36,0),FALSE)*365+J31*($C$10-VLOOKUP($Y$6,$B$37:$D$54,3,FALSE))*$C$6*52*$Y$7 -> 7144.001 | Z13: =VLOOKUP($Y$6,$B$36:$M$54,MATCH(_xlfn.CONCAT($X13," ",Z$10),$B$36:$M$36,0),FALSE)*365+J31*(($C$10-VLOOKUP($Y$6,$B$37:$D$54,3,FALSE))*$C$6*(1/$C$11)*52*$Y$7) -> 11932.619 | AA13: =(J31+L31)*(($C$10-VLOOKUP($Y$6,$B$37:$D$54,3,FALSE))*$C$6*(1/$C$11)*52*$Y$7)+$C$12*365 -> 8413.6962 | AB13: =VLOOKUP($Y$6,$B$36:$M$54,MATCH(_xlfn.CONCAT($X13," ",AB$10),$B$36:$M$36,0),FALSE)*365*1/VLOOKUP($Y$6,$B$37:$D$54,2,FALSE)+J31*($C$10-VLOOKUP($Y$6,$B$37:$D$54,3,FALSE))*(1/VLOOKUP($Y$6,$B$37:$D$54,2,FALSE)*$Y$7)*$C$6*52 -> 2576.5218 | AC13: =Y13*$C$7 -> 1893.1603 | AD13: =Z13*$C$8+$C$9*365 -> 1693.3119 | AE13: =AA13*$C$8+$C$9*365 -> 1341.4196 | AF13: =AB13*$C$7 -> 682.77829 | AG13: =Y13*$C$16 -> 921.57613 | AH13: =Z13*$C$15 -> 2505.8501 | AI13: =AA13*$C$15 -> 1766.8762 | AJ13: =AB13*$C$16 -> 332.37132 | AK13: =AC13*12 -> 22717.923 | AL13: =AD13*12 -> 20319.743 | AM13: =AE13*12 -> 16097.035 | AN13: =AF13*12 -> 8193.3395
B14: Washing machine set point | C14: 36 | D14: Based of the temperature of set point of washing machine standard | O14: fhsp_otago_dunedin | P14: Otago | Q14: 0.94142689 | R14: =$R$6*Q14 -> 2.8966981 | S14: =100-100/R14 -> 65.477935
B15: GHG emissions gas (kg/kWh) | C15: 0.21 | D15: Global to tool | O15: fhsp_queenstown_lakes_queenstown | P15: Queenstown | Q15: 0.73112237 | R15: =$R$6*Q15 -> 2.2496073 | S15: =100-100/R15 -> 55.547797 | X15: Calculation
B16: GHG emissions electricity (kg/kWh) | C16: 0.129 | D16: Global to tool | O16: fhsp_rotorua_rotorua | P16: Rotorua | Q16: 0.86199828 | R16: =$R$6*Q16 -> 2.6523024 | S16: =100-100/R16 -> 62.296908 | X16: Region | Y16: Centreal Otago
B17: Instantaneous start- up water (L) volume | C17: 2 | D17: From old hot water tool | O17: fhsp_southland_invercargill | P17: Southland | Q17: 0.8724485 | R17: =$R$6*Q17 -> 2.6844569 | S17: =100-100/R17 -> 62.748518 | X17: Number of people | Y17: 3
B18: Temperature difference indoor degree C | C18: 5 | D18: Guess | O18: fhsp_taranaki_new_plymouth | P18: Taranaki | Q18: 0.95251173 | R18: =$R$6*Q18 -> 2.9308053 | S18: =100-100/R18 -> 65.879685
O19: fhsp_taupo_king_country_turangi | P19: Taupo | Q19: 0.78545915 | R19: =$R$6*Q19 -> 2.4167974 | S19: =100-100/R19 -> 58.622928 | Y19: Energy consumption per year | AC19: Running cost per year | AG19: GHG emissions | AK19: Running cost over life
B20: Cylinder heat loss (20 degree ambient, 55 temperature rise) | C20: Electric storage water heaters | F20: Gas storage | I20: Heat pump water heater | O20: fhsp_waikato_hamilton | P20: Waikato | Q20: 0.8726003 | R20: =$R$6*Q20 -> 2.684924 | S20: =100-100/R20 -> 62.754998 | Y20: Electric | Z20: Gas storage | AA20: Gas instantaneous | AB20: Heat pump | AC20: Electric | AD20: Gas storage | AE20: Gas instantaneous | AF20: Heat pump | AG20: Electric | AH20: Gas storage | AI20: Gas instantaneous | AJ20: Heat pump | AK20: Electric | AL20: Gas storage | AM20: Gas instantaneous | AN20: Heat pump
B21: Scenario | C21: Tank size (L) | D21: Standing loss (kWh/day) | E21: Standing heatloss per year (kWh/year) | F21: Tank size (L) | G21: Standing loss (kWh/day) | H21: Standing heatloss per year (kWh/year) | I21: Tank size (L) | J21: Standing loss (kWh/day) | K21: Standing heatloss per year (kWh/year) | O21: fhsp_wairarapa_masterton | P21: Wairarapa | Q21: 0.80915968 | R21: =$R$6*Q21 -> 2.4897221 | S21: =100-100/R21 -> 59.834875 | T21: 3.3 | X21: Low | Y21: =VLOOKUP($Y$16,$B$36:$M$54,MATCH(_xlfn.CONCAT($X21," ",Y$20),$B$36:$M$36,0),FALSE)*365+J29*($C$10-VLOOKUP($Y$16,$B$37:$D$54,3,FALSE))*$C$6*52*$Y$17 -> 2265.8465 | Z21: =VLOOKUP($Y$16,$B$36:$M$54,MATCH(_xlfn.CONCAT($X21," ",Z$20),$B$36:$M$36,0),FALSE)*365+J29*(($C$10-VLOOKUP($Y$16,$B$37:$D$54,3,FALSE))*$C$6*(1/$C$11)*52*$Y$17) -> 5521.8576 | AA21: =(J29+L29)*(($C$10-VLOOKUP($Y$16,$B$37:$D$54,3,FALSE))*$C$6*(1/$C$11)*52*$Y$17)+$C$12*365 -> 2295.828 | AB21: =VLOOKUP($Y$16,$B$36:$M$54,MATCH(_xlfn.CONCAT($X21," ",AB$20),$B$36:$M$36,0),FALSE)*365*1/VLOOKUP($Y$16,$B$37:$D$54,2,FALSE)+J29*($C$10-VLOOKUP($Y$16,$B$37:$D$54,3,FALSE))*(1/VLOOKUP($Y$16,$B$37:$D$54,2,FALSE)*$Y$17)*$C$6*52 -> 1498.6874 | AC21: =Y21*$C$7 -> 600.44933 | AD21: =Z21*$C$8+$C$9*365 -> 1052.2358 | AE21: =AA21*$C$8+$C$9*365 -> 729.6328 | AF21: =AB21*$C$7 -> 397.15216 | AG21: =Y21*$C$16 -> 292.2942 | AH21: =Z21*$C$15 -> 1159.5901 | AI21: =AA21*$C$15 -> 482.12388 | AJ21: =AB21*$C$16 -> 193.33067 | AK21: =AC21*12 -> 7205.392 | AL21: =AD21*12 -> 12626.829 | AM21: =AE21*12 -> 8755.5936 | AN21: =AF21*12 -> 4765.8259
B22: Low | C22: 130 | D22: 1.56 | E22: =D22*365 -> 569.4 | F22: 130 | G22: =(0.42+0.02*(F22^(2/3))+0.006*30)*24*0.277778*55/45 -> 9.0709005 | H22: =G22*365 -> 3310.8787 | I22: 170 | J22: =I22^(0.3261)*0.6099+0.2+0.2 -> 3.6554275 | K22: =J22*365 -> 1334.231 | O22: fhsp_wellington_wellington | P22: Wellington | Q22: 1.0055162 | R22: =$R$6*Q22 -> 3.093896 | S22: =100-100/R22 -> 67.678293 | X22: Medium | Y22: =VLOOKUP($Y$16,$B$36:$M$54,MATCH(_xlfn.CONCAT($X22," ",Y$20),$B$36:$M$36,0),FALSE)*365+J30*($C$10-VLOOKUP($Y$16,$B$37:$D$54,3,FALSE))*$C$6*52*$Y$17 -> 4188.6235 | Z22: =VLOOKUP($Y$16,$B$36:$M$54,MATCH(_xlfn.CONCAT($X22," ",Z$20),$B$36:$M$36,0),FALSE)*365+J30*(($C$10-VLOOKUP($Y$16,$B$37:$D$54,3,FALSE))*$C$6*(1/$C$11)*52*$Y$17) -> 8214.9543 | AA22: =(J30+L30)*(($C$10-VLOOKUP($Y$16,$B$37:$D$54,3,FALSE))*$C$6*(1/$C$11)*52*$Y$17)+$C$12*365 -> 4689.9599 | AB22: =VLOOKUP($Y$16,$B$36:$M$54,MATCH(_xlfn.CONCAT($X22," ",AB$20),$B$36:$M$36,0),FALSE)*365*1/VLOOKUP($Y$16,$B$37:$D$54,2,FALSE)+J30*($C$10-VLOOKUP($Y$16,$B$37:$D$54,3,FALSE))*(1/VLOOKUP($Y$16,$B$37:$D$54,2,FALSE)*$Y$17)*$C$6*52 -> 2476.7152 | AC22: =Y22*$C$7 -> 1109.9852 | AD22: =Z22*$C$8+$C$9*365 -> 1321.5454 | AE22: =AA22*$C$8+$C$9*365 -> 969.04599 | AF22: =AB22*$C$7 -> 656.32954 | AG22: =Y22*$C$16 -> 540.33243 | AH22: =Z22*$C$15 -> 1725.1404 | AI22: =AA22*$C$15 -> 984.89157 | AJ22: =AB22*$C$16 -> 319.49627 | AK22: =AC22*12 -> 13319.823 | AL22: =AD22*12 -> 15858.545 | AM22: =AE22*12 -> 11628.552 | AN22: =AF22*12 -> 7875.9545
B23: Medium | C23: 180 | D23: 1.76 | E23: =D23*365 -> 642.4 | F23: 180 | G23: =(0.42+0.02*(F23^(2/3))+0.006*30)*24*0.277778*55/45 -> 10.084117 | H23: =G23*365 -> 3680.7026 | I23: 250 | J23: =I23^(0.3261)*0.6099+0.2+0.2 -> 4.091704 | K23: =J23*365 -> 1493.472 | O23: fhsp_west_coast_hokitika | P23: West Coast | Q23: 0.89504215 | R23: =$R$6*Q23 -> 2.7539758 | S23: =100-100/R23 -> 63.688861 | X23: High | Y23: =VLOOKUP($Y$16,$B$36:$M$54,MATCH(_xlfn.CONCAT($X23," ",Y$20),$B$36:$M$36,0),FALSE)*365+J31*($C$10-VLOOKUP($Y$16,$B$37:$D$54,3,FALSE))*$C$6*52*$Y$17 -> 7988.3201 | Z23: =VLOOKUP($Y$16,$B$36:$M$54,MATCH(_xlfn.CONCAT($X23," ",Z$20),$B$36:$M$36,0),FALSE)*365+J31*(($C$10-VLOOKUP($Y$16,$B$37:$D$54,3,FALSE))*$C$6*(1/$C$11)*52*$Y$17) -> 13328.877 | AA23: =(J31+L31)*(($C$10-VLOOKUP($Y$16,$B$37:$D$54,3,FALSE))*$C$6*(1/$C$11)*52*$Y$17)+$C$12*365 -> 9396.0627 | AB23: =VLOOKUP($Y$16,$B$36:$M$54,MATCH(_xlfn.CONCAT($X23," ",AB$20),$B$36:$M$36,0),FALSE)*365*1/VLOOKUP($Y$16,$B$37:$D$54,2,FALSE)+J31*($C$10-VLOOKUP($Y$16,$B$37:$D$54,3,FALSE))*(1/VLOOKUP($Y$16,$B$37:$D$54,2,FALSE)*$Y$17)*$C$6*52 -> 4294.9648 | AC23: =Y23*$C$7 -> 2116.9048 | AD23: =Z23*$C$8+$C$9*365 -> 1832.9377 | AE23: =AA23*$C$8+$C$9*365 -> 1439.6563 | AF23: =AB23*$C$7 -> 1138.1657 | AG23: =Y23*$C$16 -> 1030.4933 | AH23: =Z23*$C$15 -> 2799.0642 | AI23: =AA23*$C$15 -> 1973.1732 | AJ23: =AB23*$C$16 -> 554.05046 | AK23: =AC23*12 -> 25402.858 | AL23: =AD23*12 -> 21995.252 | AM23: =AE23*12 -> 17275.875 | AN23: =AF23*12 -> 13657.988
B24: High | C24: 250 | D24: 2.16 | E24: =D24*365 -> 788.4 | F24: 260 | G24: =(0.42+0.02*(F24^(2/3))+0.006*30)*24*0.277778*55/45 -> 11.527416 | H24: =G24*365 -> 4207.5069 | I24: 300 | J24: =I24^(0.3261)*0.6099+0.2+0.2 -> 4.3178506 | K24: =J24*365 -> 1576.0155
B25: Comment source | C25: Typically size from sales data | D25: Based on MEPS level with TPR valve 4692 | F25: Based on size from sales data and whats on the market | G25: 6.9.2 based on AS/NZS 4552.2:2010, 45 degree temperature rise, corrected to 55 degree temp rise. Assumed 30 MJ nominal gas consumption | I25: Based on market scan | J25: Based on heat exchanger MEPS in AU 4692. 0.2 added for TPR valve, 0.2 added for two fittings
B27: Water consumption per week per person
B28: Scenario | C28: Showers | D28: Washes on warm wash (assumed hot water connection) | E28: Assumed litres washing machine | F28: Assumed litres shower per min | G28: Assumed shower length | H28: Hot water use shower with temperature adjustment | I28: Washing machine water use with temperature adjustment | J28: Total per person per week (temperature adjustment) | K28: Water use per year | L28: Lost hot water for instantaneous
B29: Low | C29: 3 | D29: 1 | E29: 70 | F29: 10 | G29: 8 | H29: =G29*F29*C29*$C$13/$C$10 -> 136.61538 | I29: =D29*E29*$C$14/$C$10 -> 38.769231 | J29: =H29+I29 -> 175.38462 | K29: =J29*52 -> 9120 | L29: =$C$17*(C29+D29) -> 8
B30: Medium | C30: 5 | D30: 2 | E30: 70 | F30: 10 | G30: 10 | H30: =G30*F30*C30*$C$13/$C$10 -> 284.61538 | I30: =D30*E30*$C$14/$C$10 -> 77.538462 | J30: =H30+I30 -> 362.15385 | K30: =J30*52 -> 18832 | L30: =$C$17*(C30+D30) -> 14
B31: High | C31: 9 | D31: 3 | E31: 70 | F31: 10 | G31: 12 | H31: =G31*F31*C31*$C$13/$C$10 -> 614.76923 | I31: =D31*E31*$C$14/$C$10 -> 116.30769 | J31: =H31+I31 -> 731.07692 | K31: =J31*52 -> 38016 | L31: =$C$17*(C31+D31) -> 24
B32: Comment | C32: created to have variation | D32: created to have variation | E32: Based on typical front load water consumption, could be refined | F32: Typical flow rate | G32: Picked to show variation
B35: Region based metrics. Including how heat loss changes based on climate | E35: Gas water heater low standing losses, assumed outdoor | F35: Gas water heater medium standing losses, assumed outdoor | G35: Gas water heater high standing losses, assumed outdoor | H35: HWPH low standing losses, assumed outdoor | I35: HWPH medium standing losses, assumed outdoor | J35: HWPH high standing losses, assumed outdoor | K35: ESWH low standing losses, assumed indoor | L35: ESWH medium standing losses, assumed indoor | M35: ESWH high standing losses, assumed indoor
B36: Zone | C36: Assumed average COP Heat pump average over a year | D36: Inlet water temperature average over a year | E36: Low Gas storage | F36: Medium Gas storage | G36: High Gas storage | H36: Low Heat pump | I36: Medium Heat pump | J36: High Heat pump | K36: Low Electric | L36: Medium Electric | M36: High Electric
B37: Northland | C37: =VLOOKUP(B37,$P$6:$R$23,3,FALSE) -> 3.0756996 | D37: =VLOOKUP(B37,$Q$87:$R$104,2,FALSE) -> 15.520205 | E37: =($C$10-$D37)/55*$G$22 -> 8.1604781 | F37: =($C$10-$D37)/55*$G$23 -> 9.0720003 | G37: =($C$10-$D37)/55*$G$24 -> 10.37044 | H37: =($C$10-$D37)/55*$J$22 -> 3.2885418 | I37: =($C$10-$D37)/55*$J$23 -> 3.6810304 | J37: =($C$10-$D37)/55*$J$24 -> 3.8844793 | K37: =($C$10-$D37-$C$18)/55*$D$22 -> 1.2616087 | L37: =($C$10-$D37-$C$18)/55*$D$23 -> 1.4233534 | M37: =($C$10-$D37-$C$18)/55*$D$24 -> 1.7468428
B38: Auckland | C38: =VLOOKUP(B38,$P$6:$R$23,3,FALSE) -> 3.0769231 | D38: =VLOOKUP(B38,$Q$87:$R$104,2,FALSE) -> 15.274315 | E38: =($C$10-$D38)/55*$G$22 -> 8.2010316 | F38: =($C$10-$D38)/55*$G$23 -> 9.1170837 | G38: =($C$10-$D38)/55*$G$24 -> 10.421976 | H38: =($C$10-$D38)/55*$J$22 -> 3.3048843 | I38: =($C$10-$D38)/55*$J$23 -> 3.6993233 | J38: =($C$10-$D38)/55*$J$24 -> 3.9037833 | K38: =($C$10-$D38-$C$18)/55*$D$22 -> 1.2685831 | L38: =($C$10-$D38-$C$18)/55*$D$23 -> 1.4312219 | M38: =($C$10-$D38-$C$18)/55*$D$24 -> 1.7564996
B39: Bay of Plenty | C39: =VLOOKUP(B39,$P$6:$R$23,3,FALSE) -> 2.9813398 | D39: =VLOOKUP(B39,$Q$87:$R$104,2,FALSE) -> 14.932991 | E39: =($C$10-$D39)/55*$G$22 -> 8.2573247 | F39: =($C$10-$D39)/55*$G$23 -> 9.1796647 | G39: =($C$10-$D39)/55*$G$24 -> 10.493514 | H39: =($C$10-$D39)/55*$J$22 -> 3.3275695 | I39: =($C$10-$D39)/55*$J$23 -> 3.724716 | J39: =($C$10-$D39)/55*$J$24 -> 3.9305794 | K39: =($C$10-$D39-$C$18)/55*$D$22 -> 1.2782643 | L39: =($C$10-$D39-$C$18)/55*$D$23 -> 1.4421443 | M39: =($C$10-$D39-$C$18)/55*$D$24 -> 1.7699044
B40: Waikato | C40: =VLOOKUP(B40,$P$6:$R$23,3,FALSE) -> 2.684924 | D40: =VLOOKUP(B40,$Q$87:$R$104,2,FALSE) -> 13.536758 | E40: =($C$10-$D40)/55*$G$22 -> 8.487599 | F40: =($C$10-$D40)/55*$G$23 -> 9.4356606 | G40: =($C$10-$D40)/55*$G$24 -> 10.786149 | H40: =($C$10-$D40)/55*$J$22 -> 3.4203664 | I40: =($C$10-$D40)/55*$J$23 -> 3.8285882 | J40: =($C$10-$D40)/55*$J$24 -> 4.0401926 | K40: =($C$10-$D40-$C$18)/55*$D$22 -> 1.3178665 | L40: =($C$10-$D40-$C$18)/55*$D$23 -> 1.4868237 | M40: =($C$10-$D40-$C$18)/55*$D$24 -> 1.8247382
B41: Rotorua | C41: =VLOOKUP(B41,$P$6:$R$23,3,FALSE) -> 2.6523024 | D41: =VLOOKUP(B41,$Q$87:$R$104,2,FALSE) -> 12.184132 | E41: =($C$10-$D41)/55*$G$22 -> 8.7106814 | F41: =($C$10-$D41)/55*$G$23 -> 9.6836612 | G41: =($C$10-$D41)/55*$G$24 -> 11.069645 | H41: =($C$10-$D41)/55*$J$22 -> 3.510265 | I41: =($C$10-$D41)/55*$J$23 -> 3.9292163 | J41: =($C$10-$D41)/55*$J$24 -> 4.1463823 | K41: =($C$10-$D41-$C$18)/55*$D$22 -> 1.3562319 | L41: =($C$10-$D41-$C$18)/55*$D$23 -> 1.5301078 | M41: =($C$10-$D41-$C$18)/55*$D$24 -> 1.8778595
B42: Taupo | C42: =VLOOKUP(B42,$P$6:$R$23,3,FALSE) -> 2.4167974 | D42: =VLOOKUP(B42,$Q$87:$R$104,2,FALSE) -> 11.666553 | E42: =($C$10-$D42)/55*$G$22 -> 8.7960436 | F42: =($C$10-$D42)/55*$G$23 -> 9.7785583 | G42: =($C$10-$D42)/55*$G$24 -> 11.178125 | H42: =($C$10-$D42)/55*$J$22 -> 3.5446645 | I42: =($C$10-$D42)/55*$J$23 -> 3.9677214 | J42: =($C$10-$D42)/55*$J$24 -> 4.1870156 | K42: =($C$10-$D42-$C$18)/55*$D$22 -> 1.3709123 | L42: =($C$10-$D42-$C$18)/55*$D$23 -> 1.5466703 | M42: =($C$10-$D42-$C$18)/55*$D$24 -> 1.8981863
B43: Taranaki | C43: =VLOOKUP(B43,$P$6:$R$23,3,FALSE) -> 2.9308053 | D43: =VLOOKUP(B43,$Q$87:$R$104,2,FALSE) -> 13.594292 | E43: =($C$10-$D43)/55*$G$22 -> 8.4781102 | F43: =($C$10-$D43)/55*$G$23 -> 9.4251119 | G43: =($C$10-$D43)/55*$G$24 -> 10.774091 | H43: =($C$10-$D43)/55*$J$22 -> 3.4165425 | I43: =($C$10-$D43)/55*$J$23 -> 3.824308 | J43: =($C$10-$D43)/55*$J$24 -> 4.0356758 | K43: =($C$10-$D43-$C$18)/55*$D$22 -> 1.3162346 | L43: =($C$10-$D43-$C$18)/55*$D$23 -> 1.4849826 | M43: =($C$10-$D43-$C$18)/55*$D$24 -> 1.8224787
B44: East Coast | C44: =VLOOKUP(B44,$P$6:$R$23,3,FALSE) -> 2.806299 | D44: =VLOOKUP(B44,$Q$87:$R$104,2,FALSE) -> 14.02089 | E44: =($C$10-$D44)/55*$G$22 -> 8.4077533 | F44: =($C$10-$D44)/55*$G$23 -> 9.3468961 | G44: =($C$10-$D44)/55*$G$24 -> 10.68468 | H44: =($C$10-$D44)/55*$J$22 -> 3.3881898 | I44: =($C$10-$D44)/55*$J$23 -> 3.7925714 | J44: =($C$10-$D44)/55*$J$24 -> 4.0021851 | K44: =($C$10-$D44-$C$18)/55*$D$22 -> 1.3041347 | L44: =($C$10-$D44-$C$18)/55*$D$23 -> 1.4713315 | M44: =($C$10-$D44-$C$18)/55*$D$24 -> 1.805725
B45: Wairarapa | C45: =VLOOKUP(B45,$P$6:$R$23,3,FALSE) -> 2.4897221 | D45: =VLOOKUP(B45,$Q$87:$R$104,2,FALSE) -> 12.442123 | E45: =($C$10-$D45)/55*$G$22 -> 8.6681322 | F45: =($C$10-$D45)/55*$G$23 -> 9.6363592 | G45: =($C$10-$D45)/55*$G$24 -> 11.015573 | H45: =($C$10-$D45)/55*$J$22 -> 3.4931183 | I45: =($C$10-$D45)/55*$J$23 -> 3.9100232 | J45: =($C$10-$D45)/55*$J$24 -> 4.1261284 | K45: =($C$10-$D45-$C$18)/55*$D$22 -> 1.3489143 | L45: =($C$10-$D45-$C$18)/55*$D$23 -> 1.5218521 | M45: =($C$10-$D45-$C$18)/55*$D$24 -> 1.8677275
B46: Manawatu | C46: =VLOOKUP(B46,$P$6:$R$23,3,FALSE) -> 2.8634024 | D46: =VLOOKUP(B46,$Q$87:$R$104,2,FALSE) -> 13.155023 | E46: =($C$10-$D46)/55*$G$22 -> 8.5505569 | F46: =($C$10-$D46)/55*$G$23 -> 9.5056508 | G46: =($C$10-$D46)/55*$G$24 -> 10.866157 | H46: =($C$10-$D46)/55*$J$22 -> 3.4457374 | I46: =($C$10-$D46)/55*$J$23 -> 3.8569873 | J46: =($C$10-$D46)/55*$J$24 -> 4.0701612 | K46: =($C$10-$D46-$C$18)/55*$D$22 -> 1.3286939 | L46: =($C$10-$D46-$C$18)/55*$D$23 -> 1.4990393 | M46: =($C$10-$D46-$C$18)/55*$D$24 -> 1.83973
B47: Wellington | C47: =VLOOKUP(B47,$P$6:$R$23,3,FALSE) -> 3.093896 | D47: =VLOOKUP(B47,$Q$87:$R$104,2,FALSE) -> 12.834018 | E47: =($C$10-$D47)/55*$G$22 -> 8.6034987 | F47: =($C$10-$D47)/55*$G$23 -> 9.5645063 | G47: =($C$10-$D47)/55*$G$24 -> 10.933436 | H47: =($C$10-$D47)/55*$J$22 -> 3.4670721 | I47: =($C$10-$D47)/55*$J$23 -> 3.8808683 | J47: =($C$10-$D47)/55*$J$24 -> 4.0953621 | K47: =($C$10-$D47-$C$18)/55*$D$22 -> 1.3377988 | L47: =($C$10-$D47-$C$18)/55*$D$23 -> 1.5093114 | M47: =($C$10-$D47-$C$18)/55*$D$24 -> 1.8523367
B48: Marlborough | C48: =VLOOKUP(B48,$P$6:$R$23,3,FALSE) -> 2.7795363 | D48: =VLOOKUP(B48,$Q$87:$R$104,2,FALSE) -> 12.905936 | E48: =($C$10-$D48)/55*$G$22 -> 8.5916376 | F48: =($C$10-$D48)/55*$G$23 -> 9.5513203 | G48: =($C$10-$D48)/55*$G$24 -> 10.918363 | H48: =($C$10-$D48)/55*$J$22 -> 3.4622922 | I48: =($C$10-$D48)/55*$J$23 -> 3.875518 | J48: =($C$10-$D48)/55*$J$24 -> 4.0897161 | K48: =($C$10-$D48-$C$18)/55*$D$22 -> 1.3357589 | L48: =($C$10-$D48-$C$18)/55*$D$23 -> 1.50701 | M48: =($C$10-$D48-$C$18)/55*$D$24 -> 1.8495123
... B54: Southland | C54: =VLOOKUP(B54,$P$6:$R$23,3,FALSE) -> 2.6844569 | D54: =VLOOKUP(B54,$Q$87:$R$104,2,FALSE) -> 9.9902968 | E54: =($C$10-$D54)/55*$G$22 -> 9.0725008 | F54: =($C$10-$D54)/55*$G$23 -> 10.085896 | G54: =($C$10-$D54)/55*$G$24 -> 11.52945 | H54: =($C$10-$D54)/55*$J$22 -> 3.6560724 | I54: =($C$10-$D54)/55*$J$23 -> 4.0924258 | J54: =($C$10-$D54)/55*$J$24 -> 4.3186124 | K54: =($C$10-$D54-$C$18)/55*$D$22 -> 1.418457 | L54: =($C$10-$D54-$C$18)/55*$D$23 -> 1.6003105 | M54: =($C$10-$D54-$C$18)/55*$D$24 -> 1.9640174
D55: =AVERAGE( D37:D54 ) -> 12.474207 | E55: =($C$10-$D55)/55*$G$22 -> 8.6628407 | F55: =($C$10-$D55)/55*$G$23 -> 9.6304767 | G55: =($C$10-$D55)/55*$G$24 -> 11.008849 | H55: =($C$10-$D55)/55*$J$22 -> 3.4909859 | I55: =($C$10-$D55)/55*$J$23 -> 3.9076363 | J55: =($C$10-$D55)/55*$J$24 -> 4.1236096 | K55: =($C$10-$D55-$C$18)/55*$D$22 -> 1.3480043 | L55: =($C$10-$D55-$C$18)/55*$D$23 -> 1.5208254 | M55: =($C$10-$D55-$C$18)/55*$D$24 -> 1.8664675
P85: 2017 climate data NIWA | V85: From old tool
P86: Zone | R86: average air temperature | S86: Water temperature ratio to Auckland | T86: energy savings | U86: COP based on average outdoor temperature | V86: COP based on AC climate zone | W86: Difference | X86: % change
P87: Northland | Q87: Northland | R87: 15.520205 | S87: =R87/$R$88 -> 1.0160983 | T87: =VLOOKUP(Q87,$P$6:$Q$23,2,FALSE) -> 0.99960237 | U87: =S87*$G$8 -> 3.1264563 | V87: =VLOOKUP(Q87,$P$6:$R$23,3,FALSE) -> 3.0756996 | W87: =U87-V87 -> 0.050756683 | X87: =W87/U87 -> 0.016234573 | Z87: Climate 1 | AA87: 15.833333
P88: Auckland | Q88: Auckland | R88: 15.274315 | S88: =R88/$R$88 -> 1 | T88: =VLOOKUP(Q88,$P$6:$Q$23,2,FALSE) -> 1 | U88: =S88*$G$8 -> 3.0769231 | V88: =VLOOKUP(Q88,$P$6:$R$23,3,FALSE) -> 3.0769231 | W88: =U88-V88 -> 0 | X88: =W88/U88 -> 0 | Z88: Climate 2 | AA88: 13.5
P89: Hamilton | Q89: Waikato | R89: 13.536758 | S89: =R89/$R$88 -> 0.88624321 | T89: =VLOOKUP(Q89,$P$6:$Q$23,2,FALSE) -> 0.8726003 | U89: =S89*$G$8 -> 2.7269022 | V89: =VLOOKUP(Q89,$P$6:$R$23,3,FALSE) -> 2.684924 | W89: =U89-V89 -> 0.041978167 | X89: =W89/U89 -> 0.015394086 | Z89: Climate 3 | AA89: 10.916667
P90: Bay of Plenty | Q90: Bay of Plenty | R90: 14.932991 | S90: =R90/$R$88 -> 0.97765371 | T90: =VLOOKUP(Q90,$P$6:$Q$23,2,FALSE) -> 0.96893544 | U90: =S90*$G$8 -> 3.0081653 | V90: =VLOOKUP(Q90,$P$6:$R$23,3,FALSE) -> 2.9813398 | W90: =U90-V90 -> 0.026825467 | X90: =W90/U90 -> 0.0089175508
P91: Rototura | Q91: Rotorua | R91: 12.184132 | S91: =R91/$R$88 -> 0.79768765 | T91: =VLOOKUP(Q91,$P$6:$Q$23,2,FALSE) -> 0.86199828 | U91: =S91*$G$8 -> 2.4544235 | V91: =VLOOKUP(Q91,$P$6:$R$23,3,FALSE) -> 2.6523024 | W91: =U91-V91 -> -0.19787887 | X91: =W91/U91 -> -0.080621321 | Z91: Northland | AA91: Climate 1 | AB91: =VLOOKUP(AA91,$Z$87:$AA$89,2,FALSE) -> 15.833333
P92: Taupo | Q92: Taupo | R92: 11.666553 | S92: =R92/$R$88 -> 0.76380201 | T92: =VLOOKUP(Q92,$P$6:$Q$23,2,FALSE) -> 0.78545915 | U92: =S92*$G$8 -> 2.35016 | V92: =VLOOKUP(Q92,$P$6:$R$23,3,FALSE) -> 2.4167974 | W92: =U92-V92 -> -0.066637376 | X92: =W92/U92 -> -0.028354399 | Z92: Auckland | AA92: Climate 1 | AB92: =VLOOKUP(AA92,$Z$87:$AA$89,2,FALSE) -> 15.833333
P93: New Plymouth | Q93: Taranaki | R93: 13.594292 | S93: =R93/$R$88 -> 0.89000994 | T93: =VLOOKUP(Q93,$P$6:$Q$23,2,FALSE) -> 0.95251173 | U93: =S93*$G$8 -> 2.7384921 | V93: =VLOOKUP(Q93,$P$6:$R$23,3,FALSE) -> 2.9308053 | W93: =U93-V93 -> -0.19231321 | X93: =W93/U93 -> -0.07022595 | Z93: Coromandel | AA93: Climate 1 | AB93: =VLOOKUP(AA93,$Z$87:$AA$89,2,FALSE) -> 15.833333
P94: East Coast | Q94: East Coast | R94: 14.02089 | S94: =R94/$R$88 -> 0.91793906 | T94: =VLOOKUP(Q94,$P$6:$Q$23,2,FALSE) -> 0.91204716 | U94: =S94*$G$8 -> 2.8244279 | V94: =VLOOKUP(Q94,$P$6:$R$23,3,FALSE) -> 2.806299 | W94: =U94-V94 -> 0.018128909 | X94: =W94/U94 -> 0.006418613 | Z94: Bay of Plenty | AA94: Climate 2 | AB94: =VLOOKUP(AA94,$Z$87:$AA$89,2,FALSE) -> 13.5
P95: Manawatu | Q95: Manawatu | R95: 13.155023 | S95: =R95/$R$88 -> 0.86125124 | T95: =VLOOKUP(Q95,$P$6:$Q$23,2,FALSE) -> 0.93060578 | U95: =S95*$G$8 -> 2.6500038 | V95: =VLOOKUP(Q95,$P$6:$R$23,3,FALSE) -> 2.8634024 | W95: =U95-V95 -> -0.21339857 | X95: =W95/U95 -> -0.080527644 | Z95: Waikato | AA95: Climate 2 | AB95: =VLOOKUP(AA95,$Z$87:$AA$89,2,FALSE) -> 13.5
P96: Wairarapa | Q96: Wairarapa | R96: 12.442123 | S96: =R96/$R$88 -> 0.81457815 | T96: =VLOOKUP(Q96,$P$6:$Q$23,2,FALSE) -> 0.80915968 | U96: =S96*$G$8 -> 2.5063943 | V96: =VLOOKUP(Q96,$P$6:$R$23,3,FALSE) -> 2.4897221 | W96: =U96-V96 -> 0.016672217 | X96: =W96/U96 -> 0.0066518733 | Z96: Rotorua | AA96: Climate 2 | AB96: =VLOOKUP(AA96,$Z$87:$AA$89,2,FALSE) -> 13.5
P97: Wellington | Q97: Wellington | R97: 12.834018 | S97: =R97/$R$88 -> 0.84023527 | T97: =VLOOKUP(Q97,$P$6:$Q$23,2,FALSE) -> 1.0055162 | U97: =S97*$G$8 -> 2.5853393 | V97: =VLOOKUP(Q97,$P$6:$R$23,3,FALSE) -> 3.093896 | W97: =U97-V97 -> -0.50855667 | X97: =W97/U97 -> -0.1967079 | Z97: East Coast | AA97: Climate 2 | AB97: =VLOOKUP(AA97,$Z$87:$AA$89,2,FALSE) -> 13.5
P98: Nelson-Walborough | Q98: Marlborough | R98: 12.905936 | S98: =R98/$R$88 -> 0.84494369 | T98: =VLOOKUP(Q98,$P$6:$Q$23,2,FALSE) -> 0.90334929 | U98: =S98*$G$8 -> 2.5998267 | V98: =VLOOKUP(Q98,$P$6:$R$23,3,FALSE) -> 2.7795363 | W98: =U98-V98 -> -0.17970954 | X98: =W98/U98 -> -0.06912366 | Z98: Taupo | AA98: Climate 3 | AB98: =VLOOKUP(AA98,$Z$87:$AA$89,2,FALSE) -> 10.916667
P99: West Coast | Q99: West Coast | R99: 11.413699 | S99: =R99/$R$88 -> 0.74724782 | T99: =VLOOKUP(Q99,$P$6:$Q$23,2,FALSE) -> 0.89504215 | U99: =S99*$G$8 -> 2.2992241 | V99: =VLOOKUP(Q99,$P$6:$R$23,3,FALSE) -> 2.7539758 | W99: =U99-V99 -> -0.45475177 | X99: =W99/U99 -> -0.19778489 | Z99: Ruapehu | AA99: Climate 3 | AB99: =VLOOKUP(AA99,$Z$87:$AA$89,2,FALSE) -> 10.916667
P100: Christchurch | Q100: Canterbury | R100: 11.323516 | S100: =R100/$R$88 -> 0.74134362 | T100: =VLOOKUP(Q100,$P$6:$Q$23,2,FALSE) -> 0.79751357 | U100: =S100*$G$8 -> 2.2810573 | V100: =VLOOKUP(Q100,$P$6:$R$23,3,FALSE) -> 2.4538879 | W100: =U100-V100 -> -0.17283063 | X100: =W100/U100 -> -0.075767773 | Z100: Taranaki | AA100: Climate 2 | AB100: =VLOOKUP(AA100,$Z$87:$AA$89,2,FALSE) -> 13.5
P101: Queenstown-Lakes | Q101: Queenstown | R101: 9.4969178 | S101: =R101/$R$88 -> 0.62175736 | T101: =VLOOKUP(Q101,$P$6:$Q$23,2,FALSE) -> 0.73112237 | U101: =S101*$G$8 -> 1.9130996 | V101: =VLOOKUP(Q101,$P$6:$R$23,3,FALSE) -> 2.2496073 | W101: =U101-V101 -> -0.33650773 | X101: =W101/U101 -> -0.17589661 | Z101: Hawke’s Bay | AA101: Climate 2 | AB101: =VLOOKUP(AA101,$Z$87:$AA$89,2,FALSE) -> 13.5
P102: Central otago | Q102: Centreal Otago | R102: 9.4558219 | S102: =R102/$R$88 -> 0.61906684 | T102: =VLOOKUP(Q102,$P$6:$Q$23,2,FALSE) -> 0.67008823 | U102: =S102*$G$8 -> 1.904821 | V102: =VLOOKUP(Q102,$P$6:$R$23,3,FALSE) -> 2.0618099 | W102: =U102-V102 -> -0.15698889 | X102: =W102/U102 -> -0.082416611 | Z102: Wanganui | AA102: Climate 2 | AB102: =VLOOKUP(AA102,$Z$87:$AA$89,2,FALSE) -> 13.5
... P104: Invercargill | Q104: Southland | R104: 9.9902968 | S104: =R104/$R$88 -> 0.65405858 | T104: =VLOOKUP(Q104,$P$6:$Q$23,2,FALSE) -> 0.8724485 | U104: =S104*$G$8 -> 2.0124879 | V104: =VLOOKUP(Q104,$P$6:$R$23,3,FALSE) -> 2.6844569 | W104: =U104-V104 -> -0.671969 | X104: =W104/U104 -> -0.33389964 | Z104: Wairarapa | AA104: Climate 2 | AB104: =VLOOKUP(AA104,$Z$87:$AA$89,2,FALSE) -> 13.5
Z105: Wellington | AA105: Climate 2 | AB105: =VLOOKUP(AA105,$Z$87:$AA$89,2,FALSE) -> 13.5
Z106: Nelson | AA106: Climate 3 | AB106: =VLOOKUP(AA106,$Z$87:$AA$89,2,FALSE) -> 10.916667
Z107: Marlborough | AA107: Climate 3 | AB107: =VLOOKUP(AA107,$Z$87:$AA$89,2,FALSE) -> 10.916667
Z108: West Coast | AA108: Climate 3 | AB108: =VLOOKUP(AA108,$Z$87:$AA$89,2,FALSE) -> 10.916667
Z109: Christchurch | AA109: Climate 3 | AB109: =VLOOKUP(AA109,$Z$87:$AA$89,2,FALSE) -> 10.916667
Z110: Canterbury | AA110: Climate 3 | AB110: =VLOOKUP(AA110,$Z$87:$AA$89,2,FALSE) -> 10.916667
Z111: Mt Cook | AA111: Climate 3 | AB111: =VLOOKUP(AA111,$Z$87:$AA$89,2,FALSE) -> 10.916667
Z112: Wanaka | AA112: Climate 3 | AB112: =VLOOKUP(AA112,$Z$87:$AA$89,2,FALSE) -> 10.916667
Z113: Queenstown | AA113: Climate 3 | AB113: =VLOOKUP(AA113,$Z$87:$AA$89,2,FALSE) -> 10.916667
Z114: Otago | AA114: Climate 3 | AB114: =VLOOKUP(AA114,$Z$87:$AA$89,2,FALSE) -> 10.916667
Z115: Dunedin | AA115: Climate 3 | AB115: =VLOOKUP(AA115,$Z$87:$AA$89,2,FALSE) -> 10.916667
Z116: Fiordland | AA116: Climate 3 | AB116: =VLOOKUP(AA116,$Z$87:$AA$89,2,FALSE) -> 10.916667
... Z118: Stewart Island | AA118: Climate 3 | AB118: =VLOOKUP(AA118,$Z$87:$AA$89,2,FALSE) -> 10.916667

Sheet WH - Final
B2: Water heating calculation
B4: Need to factor Rewiring Aotearoa numbers by:
B6: Number of people
B7: Usage (low/medium/high)
B10: Data from Machines tab of Rewiring spreadsheet and EEUD
B12: Note 365.25 days per year in calculation
B14: Options for homes | C14: If Ngas | D14: If LPG | E14: If diesel boiler | F14: If resistive (& ripple control) | G14: If resistive + solar | H14: If heat pump on grid | I14: If heat pump + solar
B15: kWh/day | C15: 6.878 | D15: 6.878 | E15: 9.01 | F15: 7.26 | G15: 7.26 | H15: 2.074 | I15: 2.07
B16: kWh/year | C16: 2512 | D16: 2512 | E16: 3292 | F16: 2652 | G16: 2652 | H16: 758 | I16: 758
B18: Efficiency | C18: 0.95 | D18: 0.95 | F18: 0.9 | H18: 3.15
B20: ESD | C20: =C16 * C18 -> 2386.4 | D20: =D16 * D18 -> 2386.4 | F20: =F16 * F18 -> 2386.8 | H20: =H16 * H18 -> 2387.7
C21: =C20 / 365.25 -> 6.5336071 | D21: =D20 / 365.25 -> 6.5336071 | F21: =F20 / 365.25 -> 6.5347023 | H21: =H20 / 365.25 -> 6.5371663
B23: Values above are determined from RBS and:
B25: Number of homes | C25: 1920300 | D25: Misc tab, cell B2
B27: National ESD | C27: =C20 * C25 / 1000000 -> 4582.6039 | D27: GWh
C28: =C27 * 3.6 -> 16497.374 | D28: TJ | E28: EEUD has 19.316 TJ of fuel use for residential water heating in 2022. Fuel use > ESD makes sense as very few HWHPs.
B30: EEUD fuel consumption | C30: 19316 | D30: TJ
B31: Aggregate efficiency | C31: 0.8
B32: National ESD | C32: =C31 * C30 -> 15452.8
B34: AS/NZS 4234:2021 Heated water systems - Calculation of energy consumption
B39: Key data point is 70% energy saving for HWHP relative to electric in VEU programme (and for HP5-AU climate which is Canberra weather file).
B40: See Matt S's email of Wednesday, September 25, 2024 11:53 AM.
B42: As per analysis in "Climate comparison" tab, Wairarapa is good match to Canberra.
B44: Approximate method for scaling HWHP COP to other climates in NZ is to use the air-air HSPF data.
B48: Average household occupancy | D48: ='WH - Evidence'!I229 -> 2.6
B50: Cold water temperature | C50: 12.5 | D50: degC | E50: Average across climate zones - see WH (2) tab.
B52: Use type | C52: Mean daily volume (L) | D52: Proportion hot | E52: MDV hot (L) | F52: Temperature | G52: Q . Delta T | H52: % Q . Delta T | J52: MDV hot per person (L)
B53: Dishwasher | C53: 6.1 | D53: 0 | E53: =D53 * C53 -> 0 | F53: =$C$50 -> 12.5 | G53: =E53 * ( F53 - $C$50 ) -> 0 | H53: =G53 / $G$60 -> 0 | J53: =E53 / $D$48 -> 0 | L53: Dishwashers are most often internally heated so no draw from HW system.
B54: Washing Machine | C54: 54.1 | D54: 0.5 | E54: =D54 * C54 -> 27.05 | F54: 35 | G54: =E54 * ( F54 - $C$50 ) -> 608.625 | H54: =G54 / $G$60 -> 0.151635 | J54: =E54 / $D$48 -> 10.403846 | L54: Normal/warm wash is 35 deg. Assume 50% of water use is cold (for e.g. rinse) and 50% is 35 degC.
B55: Toilet | C55: 80.7 | D55: 0 | E55: =D55 * C55 -> 0 | F55: =$C$50 -> 12.5 | G55: =E55 * ( F55 - $C$50 ) -> 0 | H55: =G55 / $G$60 -> 0 | J55: =E55 / $D$48 -> 0 | L55: All cold
B56: Shower | C56: 102.1 | D56: 1 | E56: =D56 * C56 -> 102.1 | F56: 37 | G56: =E56 * ( F56 - $C$50 ) -> 2501.45 | H56: =G56 / $G$60 -> 0.62322018 | J56: =E56 / $D$48 -> 39.269231 | L56: All 37 degC.
B57: Tap | C57: 46.3 | D57: 0.5 | E57: =D57 * C57 -> 23.15 | F57: 40 | G57: =E57 * ( F57 - $C$50 ) -> 636.625 | H57: =G57 / $G$60 -> 0.15861102 | J57: =E57 / $D$48 -> 8.9038462 | L57: Assume 50/50 cold/40 degC.
B58: High Flow/Outdoor* | C58: 21.8 | D58: 0.5 | E58: =D58 * C58 -> 10.9 | F58: 37 | G58: =E58 * ( F58 - $C$50 ) -> 267.05 | H58: =G58 / $G$60 -> 0.06653379 | J58: =E58 / $D$48 -> 4.1923077 | L58: Assume winter use is laundry tubs/baths i.e. 0% outdoor. Assume this is constant through the year. Assume 50% is at 37 degC.
B59: Undefined | C59: 8.3 | D59: 0 | E59: =D59 * C59 -> 0 | F59: =$C$50 -> 12.5 | G59: =E59 * ( F59 - $C$50 ) -> 0 | H59: =G59 / $G$60 -> 0 | J59: =E59 / $D$48 -> 0 | L59: Ignore.
C60: =SUM( C53:C59 ) -> 319.4 | E60: =SUM( E53:E59 ) -> 163.2 | G60: =SUM( G53:G59 ) -> 4013.75
B62: * High Flow/Outdoor mean daily volume is from winter season.
B66: Top-down and bottom-up reconciliation
B68: Specific heat capacity | C68: 4184 | D68: J / ( kg K )
C69: =C68 / 1000000 / 3.6 -> 0.0011622222 | D69: kWh / ( kg K )
B71: Weekly per person | C71: 403 | D71: L | E71: From water use data
B72: Annual per person | C72: =365.25 * C71 / 7 -> 21027.964 | D72: L
B74: People per house | C74: 2.7 | E74: As per top-down
B75: Annual per house | C75: =C74 * C72 -> 56775.504 | D75: L
B77: Delta T | C77: 25 | D77: degC
B79: Annual kWh per house | C79: =C69 * C75 * C77 -> 1649.6438 | D79: kWh
B81: From Rewiring estimate | C81: =C20 -> 2386.4 | D81: kWh
B83: Bottom-up - top-down | C83: =C79 - C81 -> -736.7562 | D83: kWh
B85: Updated top-down | C85: =M110 -> 2085.5775 | D85: kWh | E85: Assumes lower efficiences reflective of older stock of appliances. Hence lower estimate of ESD.
B87: New BU - TD | C87: =C79 - C85 -> -435.9337 | D87: kWh
C88: =C87 / C85 -> -0.20902302 | E88: Normalised by updated top-down
B90: Annual kWh per house | C90: =C69 * 365.25 * E60 * C77 -> 1731.9668 | D90: kWh | E90: From 163 L number in table above
B92: Alternate BU - TD | C92: =C90 - C85 -> -353.6107 | D92: kWh
C93: =C92 / C85 -> -0.1695505 | E93: Normalised by updated top-down
B96: Re-analysis of top-down with lower efficiencies
C98: # | D98: # / home | E98: % | F98: kWh/day | G98: kWh/day | H98: kWh/day | I98: kWh/day | K98: kWh/day
B99: Water heaters | C99: How many in country | D99: How many per home | E99: COP | F99: Electricity | G99: Gas | H99: LPG | I99: Wood | J99: Total | K99: Base energy needs
B100: Electric Water - Med/Large | C100: 792094 | D100: 0.41 | E100: 0.8 | F100: 3.49 | J100: =SUM( F100:I100 ) -> 3.49 | K100: =J100 * E100 -> 2.792
B101: Electric Water - Small | C101: 458067 | D101: 0.24 | E101: 0.8 | F101: 1.26 | J101: =SUM( F101:I101 ) -> 1.26 | K101: =J101 * E101 -> 1.008
B102: Gas instant (LPG) | C102: 142039 | D102: 0.07 | E102: 0.85 | H102: 0.52 | J102: =SUM( F102:I102 ) -> 0.52 | K102: =J102 * E102 -> 0.442
B103: Gas instant (mains) | C103: 299344 | D103: 0.16 | E103: 0.85 | G103: 1.1 | J103: =SUM( F103:I103 ) -> 1.1 | K103: =J103 * E103 -> 0.935
B104: Gas storage (LPG) | C104: 1439 | D104: 0 | E104: 0.6 | H104: 0.01 | J104: =SUM( F104:I104 ) -> 0.01 | K104: =J104 * E104 -> 0.006
B105: Gas storage (mains) | C105: 16355 | D105: 0.01 | E105: 0.6 | G105: 0.07 | J105: =SUM( F105:I105 ) -> 0.07 | K105: =J105 * E105 -> 0.042 | M105: Estimate of number in country too low?
B106: Heat pump | C106: 10859 | D106: 0.01 | E106: 3 | F106: 0.01 | J106: =SUM( F106:I106 ) -> 0.01 | K106: =J106 * E106 -> 0.03
B107: Solar electric | C107: 49990 | D107: 0.03 | E107: 3 | F107: 0.06 | J107: =SUM( F107:I107 ) -> 0.06 | K107: =J107 * E107 -> 0.18
B108: Solar gas | C108: 0 | D108: 0 | E108: N/A
B109: Wood | C109: 183082 | D109: 0.1 | E109: 0.5 | I109: 0.55 | J109: =SUM( F109:I109 ) -> 0.55 | K109: =J109 * E109 -> 0.275
B110: Total | C110: =SUM( C100:C109 ) -> 1953269 | F110: 4.82 | G110: 1.17 | H110: 0.53 | I110: 0.55 | J110: 7.07 | K110: =SUM( K100:K109 ) -> 5.71 | M110: =K110 * 365.25 -> 2085.5775
G112: Rewiring ESD estimate from above: | K112: 6.53 | M112: =K112 * 365.25 -> 2385.0825
B115: Interim conclusions from bottom-up vs top-down
B117: There is a roughly 17% difference which cannot be easily explained.
B119: Potential reasons are:
B121: Water use in BRANZ study is lower than national average. Given that household size in study is 2.6, this is possible. Potentially also an effect of being monitored?
B122: EEUD/RBS allocations indicate higher than true use of energy for heating water. Unknown.
B123: Assumed efficiencies from which energy service demand are derived are too high. Possible.
B125: Test:
B127: As below, conclude that efficiencies would have to be implausibly low to fully explain difference in energy service demand.
B128: No evidence to choose between adjusting water use and adjusting allocation of energy use for heating water.
B129: Conclude that primary reference should be water use data, with showering numbers intentionally rounded up to be slightly closer to energy service demand.
B132: Second re-analysis of top-down with lower efficiencies
C134: # | D134: # / home | E134: % | F134: kWh/day | G134: kWh/day | H134: kWh/day | I134: kWh/day | K134: kWh/day
B135: Water heaters | C135: How many in country | D135: How many per home | E135: COP | F135: Electricity | G135: Gas | H135: LPG | I135: Wood | J135: Total | K135: Base energy needs
B136: Electric Water - Med/Large | C136: 792094 | D136: 0.41 | E136: 0.75 | F136: 3.49 | J136: =SUM( F136:I136 ) -> 3.49 | K136: =J136 * E136 -> 2.6175 | M136: Reduce by 5 percentage points
B137: Electric Water - Small | C137: 458067 | D137: 0.24 | E137: 0.75 | F137: 1.26 | J137: =SUM( F137:I137 ) -> 1.26 | K137: =J137 * E137 -> 0.945 | M137: Reduce by 5 percentage points
B138: Gas instant (LPG) | C138: 142039 | D138: 0.07 | E138: 0.8 | H138: 0.52 | J138: =SUM( F138:I138 ) -> 0.52 | K138: =J138 * E138 -> 0.416 | M138: Reduce by 5 percentage points
B139: Gas instant (mains) | C139: 299344 | D139: 0.16 | E139: 0.8 | G139: 1.1 | J139: =SUM( F139:I139 ) -> 1.1 | K139: =J139 * E139 -> 0.88 | M139: Reduce by 5 percentage points
B140: Gas storage (LPG) | C140: 1439 | D140: 0 | E140: 0.55 | H140: 0.01 | J140: =SUM( F140:I140 ) -> 0.01 | K140: =J140 * E140 -> 0.0055 | M140: Reduce by 5 percentage points
B141: Gas storage (mains) | C141: 16355 | D141: 0.01 | E141: 0.55 | G141: 0.07 | J141: =SUM( F141:I141 ) -> 0.07 | K141: =J141 * E141 -> 0.0385 | M141: Reduce by 5 percentage points
B142: Heat pump | C142: 10859 | D142: 0.01 | E142: 2 | F142: 0.01 | J142: =SUM( F142:I142 ) -> 0.01 | K142: =J142 * E142 -> 0.02 | M142: Reduce by 100 percentage points
B143: Solar electric | C143: 49990 | D143: 0.03 | E143: 3 | F143: 0.06 | J143: =SUM( F143:I143 ) -> 0.06 | K143: =J143 * E143 -> 0.18 | M143: Same
B144: Solar gas | C144: 0 | D144: 0 | E144: N/A
B145: Wood | C145: 183082 | D145: 0.1 | E145: 0.5 | I145: 0.55 | J145: =SUM( F145:I145 ) -> 0.55 | K145: =J145 * E145 -> 0.275 | M145: Same
B146: Total | C146: =SUM( C136:C145 ) -> 1953269 | F146: 4.82 | G146: 1.17 | H146: 0.53 | I146: 0.55 | J146: 7.07 | K146: =SUM( K136:K145 ) -> 5.3775 | M146: =K146 * 365.25 -> 1964.1319 | O146: About 5% lower - as expected.
G148: Previous revised estimate: | K148: =K110 -> 5.71 | M148: =K148 * 365.25 -> 2085.5775
G150: Rewiring ESD estimate from above: | K150: 6.53 | M150: =K150 * 365.25 -> 2385.0825

Sheet WH - Final (2)
B3: Constants
B5: Specific heat capacity | C5: 4184 | D5: J / ( kg K )
C6: =C5 / 1000000 / 3.6 -> 0.0011622222 | D6: kWh / ( kg K )
B8: Density | C8: 1 | D8: kg / L
B11: Per-person demand
B13: Showering
B15: Scenario | C15: Per week | D15: Per shower | E15: Flow | F15: Volume | G15: Volume | H15: Ratio | J15: Temperature
C16: [] | D16: [min] | E16: [L/min] | F16: [L/use] | G16: [L/day] | J16: [degC]
B17: Low | C17: 5 | D17: 5 | E17: 5 | F17: =D17 * E17 -> 25 | G17: =C17 * D17 * E17 / 7 -> 17.857143 | H17: =G17 / $G$18 -> 0.42517007 | J17: 37
B18: Medium | C18: 6 | D18: 7 | E18: 7 | F18: =D18 * E18 -> 49 | G18: =C18 * D18 * E18 / 7 -> 42 | H18: =G18 / $G$18 -> 1 | J18: 37
B19: High | C19: 7 | D19: 9 | E19: 9 | F19: =D19 * E19 -> 81 | G19: =C19 * D19 * E19 / 7 -> 81 | H19: =G19 / $G$18 -> 1.9285714 | J19: 37
B21: Other - assumed to not vary under low/medium/high scenarios
C23: Volume | D23: Temperature
C24: [L/day] | D24: [degC]
B25: Washing Machine | C25: 10.403846 | D25: 35
B26: Tap | C26: 8.9038462 | D26: 40
B27: High Flow/Outdoor* | C27: 4.1923077 | D27: 37
B29: * High Flow/Outdoor mean daily volume is from winter season.
B32: Climate
B34: Zone | C34: Climate zone code | D34: Average Tc | F34: NZBC | J34: NIWA to NZBC map in different order - used for XLOOKUP at left and below in HWHP COP table | T34: Mappings based on:
D35: [degC]
B36: Northland | C36: NL | D36: 15.520205 | F36: =_xlfn.XLOOKUP( B36, $J$36:$J$53, $K$36:$K$53 ) -> 1 | J36: Northland | K36: 1 | T36: https://www.building.govt.nz/assets/Uploads/building-code-compliance/h1-energy-efficiency/asvm/h1-energy-efficiency-as1-5th-edition-amendment-1.pdf
B37: Auckland | C37: AK | D37: 15.274315 | F37: =_xlfn.XLOOKUP( B37, $J$36:$J$53, $K$36:$K$53 ) -> 1 | J37: Auckland | K37: 1
B38: Hamilton | C38: HN | D38: 13.536758 | F38: =_xlfn.XLOOKUP( B38, $J$36:$J$53, $K$36:$K$53 ) -> 2 | J38: Hamilton | K38: 2 | T38: See table on p. 23 and map on p. 24.
B39: Bay of Plenty | C39: BP | D39: 14.932991 | F39: =_xlfn.XLOOKUP( B39, $J$36:$J$53, $K$36:$K$53 ) -> 1 | J39: Taupo | K39: 4
B40: Rotorua | C40: RR | D40: 12.184132 | F40: =_xlfn.XLOOKUP( B40, $J$36:$J$53, $K$36:$K$53 ) -> 4 | J40: Bay of Plenty | K40: 1
B41: Taupo | C41: TP | D41: 11.666553 | F41: =_xlfn.XLOOKUP( B41, $J$36:$J$53, $K$36:$K$53 ) -> 4 | J41: Rotorua | K41: 4
B42: New Plymouth | C42: NP | D42: 13.594292 | F42: =_xlfn.XLOOKUP( B42, $J$36:$J$53, $K$36:$K$53 ) -> 2 | J42: New Plymouth | K42: 2
B43: East Coast | C43: EC | D43: 14.02089 | F43: =_xlfn.XLOOKUP( B43, $J$36:$J$53, $K$36:$K$53 ) -> 2 | J43: East Coast | K43: 2
B44: Manawatu | C44: MW | D44: 13.155023 | F44: =_xlfn.XLOOKUP( B44, $J$36:$J$53, $K$36:$K$53 ) -> 3 | J44: Manawatu | K44: 3
B45: Wairarapa | C45: WI | D45: 12.442123 | F45: =_xlfn.XLOOKUP( B45, $J$36:$J$53, $K$36:$K$53 ) -> 4 | J45: Wairarapa | K45: 4
B46: Wellington | C46: WN | D46: 12.834018 | F46: =_xlfn.XLOOKUP( B46, $J$36:$J$53, $K$36:$K$53 ) -> 3 | J46: Wellington | K46: 3
B47: Nelson-Marlborough | C47: NM | D47: 12.905936 | F47: =_xlfn.XLOOKUP( B47, $J$36:$J$53, $K$36:$K$53 ) -> 3 | J47: Nelson-Marlborough | K47: 3
B48: West Coast | C48: WC | D48: 11.413699 | F48: =_xlfn.XLOOKUP( B48, $J$36:$J$53, $K$36:$K$53 ) -> 4 | J48: West Coast | K48: 4
B49: Christchurch | C49: CC | D49: 11.323516 | F49: =_xlfn.XLOOKUP( B49, $J$36:$J$53, $K$36:$K$53 ) -> 5 | J49: Christchurch | K49: 5
B50: Queenstown-Lakes | C50: QL | D50: 9.4969178 | F50: =_xlfn.XLOOKUP( B50, $J$36:$J$53, $K$36:$K$53 ) -> 6 | J50: Queenstown-Lakes | K50: 6
... B53: Invercargill | C53: IN | D53: 9.9902968 | F53: =_xlfn.XLOOKUP( B53, $J$36:$J$53, $K$36:$K$53 ) -> 6 | J53: Invercargill | K53: 6
B56: Efficiencies
B58: Burner efficiency (fuel to heat)
B60: Gas instantaneous | C60: 0.834 | E60: First draft: 0.9 | G60: Updated 25/11/24 to 0.834 | J60: 20241031 - Gas water heater product data for Gareth.xlsx
B61: Gas storage | C61: 0.885 | E61: First draft: 0.9 | G61: Updated 25/11/24 to 0.885 | J61: 20241031 - Gas water heater product data for Gareth.xlsx
B63: Storage and ambient temperatures
B65: Water storage temperature | C65: 65 | E65: Standard assumption
B66: Average indoor temperature | C66: 18 | E66: Assumption - aligns with NZ Building Code
B67: Average outdoor temperature = 12.5. Wellington = 12.8. Quick fix for checks is to switch in Wellington here. | C67: 12.8 | E67: From climate data - national unweighted average across 18 climate zones | M67: See "WH" tab
B69: Storage - indoor Delta T | C69: =C65 - C66 -> 47
B70: Storage - outdoor Delta T | C70: =C65 - C67 -> 52.2
B72: Cylinder heat loss - storage and ambient temperatures as above
B73: Note: Electric and gas assumed indoors, HP assumed outdoors
C75: Electric storage water heaters | G75: Gas storage | K75: Heat pump water heater
B76: Scenario | C76: Tank size (L) | D76: Standing loss (kWh/day) | E76: Standing heatloss per year (kWh/year) | G76: Tank size (L) | H76: Standing loss (kWh/day) | I76: Standing heatloss per year (kWh/year) | K76: Tank size (L) | L76: Standing loss (kWh/day) | M76: Standing heatloss per year (kWh/year)
B77: Low | C77: 130 | D77: =1.56*( $C$69 / 55 ) -> 1.3330909 | E77: =D77*365.25 -> 486.91145 | G77: 130 | H77: =(0.42+0.02*(G77^(2/3))+0.006*30)*24*0.277778*$C$69/45 -> 7.7514968 | I77: =H77*365.25 -> 2831.2342 | K77: 170 | L77: =K77^(0.3261)*0.6099*$C$70/55 + 0.2 + 0.2 -> 3.4896966 | M77: =L77*365.25 -> 1274.6117
B78: Medium | C78: 180 | D78: =1.76*( $C$69 / 55 ) -> 1.504 | E78: =D78*365.25 -> 549.336 | G78: 180 | H78: =(0.42+0.02*(G78^(2/3))+0.006*30)*24*0.277778*$C$69/45 -> 8.617336 | I78: =H78*365.25 -> 3147.482 | K78: 250 | L78: =K78^(0.3261)*0.6099*$C$70/55 + 0.2 + 0.2 -> 3.9037627 | M78: =L78*365.25 -> 1425.8493
B79: High | C79: 250 | D79: =2.16*( $C$69 / 55 ) -> 1.8458182 | E79: =D79*365.25 -> 674.18509 | G79: 260 | H79: =(0.42+0.02*(G79^(2/3))+0.006*30)*24*0.277778*$C$69/45 -> 9.8507011 | I79: =H79*365.25 -> 3597.9686 | K79: 300 | L79: =K79^(0.3261)*0.6099*$C$70/55 + 0.2 + 0.2 -> 4.1183964 | M79: =L79*365.25 -> 1504.2443
B81: Tank size | C81: Typical size from sales data | G81: Typical size from sales data and market availability | K81: Based on market scan
C82: Based on MEPS level with TPR valve 4692 | G82: 6.9.2 based on AS/NZS 4552.2:2010, 45 degree temperature rise, corrected to 55 degree temp rise. Assumed 30 MJ nominal gas consumption | K82: Based on heat exchanger MEPS in AU 4692. 0.2 added for TPR valve, 0.2 added for two fittings
B84: Heat pump COP
B86: Key datapoint is % savings for HP vs resistance from Victoria Energy Upgrade programme as per graph below.
B88: Conclusion is to assume 70% saving (bottom end of 'middle' of distribution).
B107: This is inclusive of standing losses, and assumes 'average' hot water use.
B109: Total energy use | C109: =E180 -> 2698.6476 | D109: kWh | E109: Equal to fuel (electricity) use. Used for comparison. Based on 3 people, medium water use.
B111: Electricity (HP) | C111: =0.3 * C109 -> 809.59429 | D111: kWh | E111: If HP in comparable situation.
B113: Assumed COP | C113: =C109 / C111 -> 3.3333333 | E113: This assumes that the standing losses are equivalent. Because standing losses for HPs are higher, the refrigeration cycle COP will be higher than this. Initial assumption is to adopt this as the COP to act as a conservative assumption.
B115: Benchmark COP | C115: =$D$135 -> 3.9915987 | E115: This is the COP for a single-split air-air HP in Wairarapa. Similar climate to Canberra, which is HP5-AU, which is basis for 70% saving.
B117: Space heating data used to scale HWHP COP. All data is linked from "SH - Final" tab.
B119: ='SH - Final'!B209 -> Region (as per registration) | C119: ='SH - Final'!C209 -> Region | D119: ='SH - Final'!D209 -> COP | F119: COP - water heating | H119: NZBC zone
B120: ='SH - Final'!B210 -> fhsp_auckland_auckland | C120: ='SH - Final'!C210 -> Auckland | D120: ='SH - Final'!D210 -> 4.9386232 | F120: =$C$113 * ( D120 / $C$115 ) -> 4.1241815 | H120: =_xlfn.XLOOKUP( C120, $J$36:$J$53, $K$36:$K$53 ) -> 1
B121: ='SH - Final'!B211 -> fhsp_bay_of_plenty_tauranga | C121: ='SH - Final'!C211 -> Bay of Plenty | D121: ='SH - Final'!D211 -> 4.7837394 | F121: =$C$113 * ( D121 / $C$115 ) -> 3.9948399 | H121: =_xlfn.XLOOKUP( C121, $J$36:$J$53, $K$36:$K$53 ) -> 1
B122: ='SH - Final'!B212 -> fhsp_canterbury_christchurch | C122: ='SH - Final'!C212 -> Christchurch | D122: ='SH - Final'!D212 -> 3.9340181 | F122: =$C$113 * ( D122 / $C$115 ) -> 3.2852485 | H122: =_xlfn.XLOOKUP( C122, $J$36:$J$53, $K$36:$K$53 ) -> 5
B123: ='SH - Final'!B213 -> fhsp_central_otago_lauder | C123: ='SH - Final'!C213 -> Central Otago | D123: ='SH - Final'!D213 -> 3.3033806 | F123: =$C$113 * ( D123 / $C$115 ) -> 2.7586112 | H123: =_xlfn.XLOOKUP( C123, $J$36:$J$53, $K$36:$K$53 ) -> 6
B124: ='SH - Final'!B214 -> fhsp_east_coast_napier | C124: ='SH - Final'!C214 -> East Coast | D124: ='SH - Final'!D214 -> 4.5019613 | F124: =$C$113 * ( D124 / $C$115 ) -> 3.7595306 | H124: =_xlfn.XLOOKUP( C124, $J$36:$J$53, $K$36:$K$53 ) -> 2
B125: ='SH - Final'!B215 -> fhsp_manawatu_paraparaumu | C125: ='SH - Final'!C215 -> Manawatu | D125: ='SH - Final'!D215 -> 4.5936697 | F125: =$C$113 * ( D125 / $C$115 ) -> 3.8361151 | H125: =_xlfn.XLOOKUP( C125, $J$36:$J$53, $K$36:$K$53 ) -> 3
B126: ='SH - Final'!B216 -> fhsp_nelson_marlborough_nelson | C126: ='SH - Final'!C216 -> Nelson-Marlborough | D126: ='SH - Final'!D216 -> 4.4584903 | F126: =$C$113 * ( D126 / $C$115 ) -> 3.7232286 | H126: =_xlfn.XLOOKUP( C126, $J$36:$J$53, $K$36:$K$53 ) -> 3
B127: ='SH - Final'!B217 -> fhsp_northland_kaitaia | C127: ='SH - Final'!C217 -> Northland | D127: ='SH - Final'!D217 -> 4.9374026 | F127: =$C$113 * ( D127 / $C$115 ) -> 4.1231621 | H127: =_xlfn.XLOOKUP( C127, $J$36:$J$53, $K$36:$K$53 ) -> 1
B128: ='SH - Final'!B218 -> fhsp_otago_dunedin | C128: ='SH - Final'!C218 -> Dunedin | D128: ='SH - Final'!D218 -> 4.6468026 | F128: =$C$113 * ( D128 / $C$115 ) -> 3.8804858 | H128: =_xlfn.XLOOKUP( C128, $J$36:$J$53, $K$36:$K$53 ) -> 5
B129: ='SH - Final'!B219 -> fhsp_queenstown_lakes_queenstown | C129: ='SH - Final'!C219 -> Queenstown-Lakes | D129: ='SH - Final'!D219 -> 3.6053948 | F129: =$C$113 * ( D129 / $C$115 ) -> 3.0108194 | H129: =_xlfn.XLOOKUP( C129, $J$36:$J$53, $K$36:$K$53 ) -> 6
B130: ='SH - Final'!B220 -> fhsp_rotorua_rotorua | C130: ='SH - Final'!C220 -> Rotorua | D130: ='SH - Final'!D220 -> 4.253671 | F130: =$C$113 * ( D130 / $C$115 ) -> 3.5521865 | H130: =_xlfn.XLOOKUP( C130, $J$36:$J$53, $K$36:$K$53 ) -> 4
B131: ='SH - Final'!B221 -> fhsp_southland_invercargill | C131: ='SH - Final'!C221 -> Invercargill | D131: ='SH - Final'!D221 -> 4.3049381 | F131: =$C$113 * ( D131 / $C$115 ) -> 3.594999 | H131: =_xlfn.XLOOKUP( C131, $J$36:$J$53, $K$36:$K$53 ) -> 6
... B137: ='SH - Final'!B227 -> fhsp_west_coast_hokitika | C137: ='SH - Final'!C227 -> West Coast | D137: ='SH - Final'!D227 -> 4.417089 | F137: =$C$113 * ( D137 / $C$115 ) -> 3.6886549 | H137: =_xlfn.XLOOKUP( C137, $J$36:$J$53, $K$36:$K$53 ) -> 4
E139: Minimum | F139: =MIN( F120:F137 ) -> 2.7586112
E140: Maximum | F140: =MAX( F120:F137 ) -> 4.146509
B143: Calculation
B145: Climate zone | C145: Christchurch
B146: Inlet temperature | C146: =_xlfn.XLOOKUP( C145, B36:B53, D36:D53 ) -> 11.323516
B148: Use | C148: Delta T
B149: Shower | C149: =J17 - C146 -> 25.676484
B150: Washing Machine | C150: =D25 - C146 -> 23.676484
B151: Tap | C151: =D26 - C146 -> 28.676484
B152: High Flow/Outdoor* | C152: =D27 - C146 -> 25.676484
B155: EDB | C155: ID | D155: Daily | E155: Day | F155: Night
B156: Wellington Electricity | C156: 172954 | D156: 1.787445 | E156: 0.29325 | F156: 0.146625 | H156: Manual copy and paste
B158: Natural gas | D158: ='Gas prices'!C3 -> 1.6 | E158: ='Gas prices'!D3 -> 0.11
B159: LPG | D159: ='Gas prices'!C4 -> 0.37782341 | E159: ='Gas prices'!D4 -> 0.244
B162: Energy service demand
B164: Number of people | C164: Other | D164: Showering energy use | G164: Total delivered energy use
D165: Low | E165: Medium | F165: High | G165: Low | H165: Medium | I165: High
B166: 1 | C166: =B166 * 365.25 * $C$6 * ( $C$25*$C$150 + $C$26*$C$151 + $C$27*$C$152 ) -> 258.64938 | D166: =$B166 * 365.25 * $C$6 * $G$17 * $C$149 -> 194.63768 | E166: =$B166 * 365.25 * $C$6 * $G$18 * $C$149 -> 457.78783 | F166: =$B166 * 365.25 * $C$6 * $G$19 * $C$149 -> 882.87653 | G166: =$C166 + D166 -> 453.28707 | H166: =$C166 + E166 -> 716.43721 | I166: =$C166 + F166 -> 1141.5259
B167: 2 | C167: =B167 * 365.25 * $C$6 * ( $C$25*$C$150 + $C$26*$C$151 + $C$27*$C$152 ) -> 517.29877 | D167: =$B167 * 365.25 * $C$6 * $G$17 * $C$149 -> 389.27537 | E167: =$B167 * 365.25 * $C$6 * $G$18 * $C$149 -> 915.57566 | F167: =$B167 * 365.25 * $C$6 * $G$19 * $C$149 -> 1765.7531 | G167: =$C167 + D167 -> 906.57413 | H167: =$C167 + E167 -> 1432.8744 | I167: =$C167 + F167 -> 2283.0518
B168: 3 | C168: =B168 * 365.25 * $C$6 * ( $C$25*$C$150 + $C$26*$C$151 + $C$27*$C$152 ) -> 775.94815 | D168: =$B168 * 365.25 * $C$6 * $G$17 * $C$149 -> 583.91305 | E168: =$B168 * 365.25 * $C$6 * $G$18 * $C$149 -> 1373.3635 | F168: =$B168 * 365.25 * $C$6 * $G$19 * $C$149 -> 2648.6296 | G168: =$C168 + D168 -> 1359.8612 | H168: =$C168 + E168 -> 2149.3116 | I168: =$C168 + F168 -> 3424.5777
B169: 4 | C169: =B169 * 365.25 * $C$6 * ( $C$25*$C$150 + $C$26*$C$151 + $C$27*$C$152 ) -> 1034.5975 | D169: =$B169 * 365.25 * $C$6 * $G$17 * $C$149 -> 778.55073 | E169: =$B169 * 365.25 * $C$6 * $G$18 * $C$149 -> 1831.1513 | F169: =$B169 * 365.25 * $C$6 * $G$19 * $C$149 -> 3531.5061 | G169: =$C169 + D169 -> 1813.1483 | H169: =$C169 + E169 -> 2865.7489 | I169: =$C169 + F169 -> 4566.1037
...

Sheet WH - 2026
B2: June 2026 update to heat pump water heater model in HESC
B4: This tab added 16th June 2026
B6: Initial results from the HPWH project suggest lower COPs than have been modelled in the HESC. Potentially by up to 30%.
B7: EECA is also about to launch a 'hot water heating calculator' with Master Plumbers, so desire is to update HESC with best available data (and avoid a potential 'large' reduction in COPs later on).
B8: Proposal is to reduce COPs/savings by 15% as mid-point of 0% (do nothing/as-is) and 30%.
B10: Key points to update:
B12: 1. Lower COPs across the board.
B13: 2. Particularly low (delivered) COPs for low hot water usage households.
B14: 3. Less climate variation than modelled (noting the model used climate variation for air-air space heating as a proxy).
B16: Higher standing losses are likely to be part of the discrepancy. These are currently modelled using AS/NZS 4692 (Parts 1 and 2).
B18: Suggested modelling approach:
B20: 1. Decrease reference COP.
... B30: Reference COP
B32: Existing reference COP | C32: =1 / 0.3 -> 3.3333333 | E32: Applies to Canberra/Wairarapa. "WH - Final (2)" tab cell C113.
B33: New reference COP | C33: 3.5 | E33: Assumption. Direct replacement for previous value.
B35: Standing losses
B37: Air speed | C37: =AVERAGE( 0.25, 0.5 ) -> 0.375 | E37: AS/NZS 4692.1
B39: Average wind speed in NZ: | C39: 3.5 | E39: See NIWA data below. Most regional centres/climate zones appear to be teal coloured (some blue/lower, some green/higher) so assume 3.5 as mid-point of teal.
B41: Assume increase in convective heat loss only occurs for expansion relief valve and 2 x water fittings.
B43: Assumed increase in fittings h-value: | C43: 1 | E43: Based on ChatGPT conversation (which suggested 3 based on ratio of 3.5 m/s average wind speed to 0.375 m/s test standard air speed).
E44: https://chatgpt.com/s/t_6a30d1aa353c81c7b9dac58a0bf6df7f
B46: Heat pump water heater
B47: Tank size (L) | C47: Standing loss (kWh/day) | D47: Standing heatloss per year (kWh/year) | F47: Existing loss from fittings | G47: New loss from fittings | H47: Total loss | I47: Standing loss | J47: Percentage change
B48: 170 | C48: 3.4896966 | D48: 1274.6117 | F48: 0.4 | G48: =$C$43 * F48 -> 0.4 | H48: =C48 + ( G48 - F48 ) -> 3.4896966 | I48: =H48 * 365.25 -> 1274.6117 | J48: =( I48 - D48 ) / D48 -> 0
B49: 250 | C49: 3.9037627 | D49: 1425.8493 | F49: 0.4 | G49: =$C$43 * F49 -> 0.4 | H49: =C49 + ( G49 - F49 ) -> 3.9037627 | I49: =H49 * 365.25 -> 1425.8493 | J49: =( I49 - D49 ) / D49 -> 0
B50: 300 | C50: 4.1183964 | D50: 1504.2443 | F50: 0.4 | G50: =$C$43 * F50 -> 0.4 | H50: =C50 + ( G50 - F50 ) -> 4.1183964 | I50: =H50 * 365.25 -> 1504.2443 | J50: =( I50 - D50 ) / D50 -> 0
B52: Data in green box from "WH - Final (2)" tab cells K75:M79
B54: De-rate climate variation
B56: De-rating coefficient | C56: 0.5 | E56: Assumption. Previous assumption was implicitly 1.0.
B58: Assumed water heating COP | C58: =C33 -> 3.5 | D58: As above
B59: Benchmark space heating COP | C59: =_xlfn.XLOOKUP( D59, C63:C80, D63:D80 ) -> 3.9915987 | D59: Wairarapa
B62: Region (as per registration) | C62: Region | D62: COP - SH | E62: COP - WH ( v1) | G62: Ratio | H62: De-rated ratio | J62: COP - WH - (v2) | L62: Check NEW = OLD | M62: %
B63: fhsp_wellington_wellington | C63: Wellington | D63: 4.96536 | E63: 4.146509 | G63: =D63 / $C$59 -> 1.2439527 | H63: =1 + $C$56 * ( G63 - 1 ) -> 1.1219764 | J63: =$C$58 * H63 -> 3.9269172 | L63: =J63 = E63 -> FALSE | M63: =( J63 - E63 ) / E63 -> -0.05295823
B64: fhsp_auckland_auckland | C64: Auckland | D64: 4.9386232 | E64: 4.1241815 | G64: =D64 / $C$59 -> 1.2372544 | H64: =1 + $C$56 * ( G64 - 1 ) -> 1.1186272 | J64: =$C$58 * H64 -> 3.9151953 | L64: =J64 = E64 -> FALSE | M64: =( J64 - E64 ) / E64 -> -0.050673376
B65: fhsp_northland_kaitaia | C65: Northland | D65: 4.9374026 | E65: 4.1231621 | G65: =D65 / $C$59 -> 1.2369486 | H65: =1 + $C$56 * ( G65 - 1 ) -> 1.1184743 | J65: =$C$58 * H65 -> 3.9146601 | L65: =J65 = E65 -> FALSE | M65: =( J65 - E65 ) / E65 -> -0.050568472
B66: fhsp_bay_of_plenty_tauranga | C66: Bay of Plenty | D66: 4.7837394 | E66: 3.9948399 | G66: =D66 / $C$59 -> 1.198452 | H66: =1 + $C$56 * ( G66 - 1 ) -> 1.099226 | J66: =$C$58 * H66 -> 3.847291 | L66: =J66 = E66 -> FALSE | M66: =( J66 - E66 ) / E66 -> -0.036934887
B67: fhsp_taranaki_new_plymouth | C67: New Plymouth | D67: 4.7023523 | E67: 3.9268746 | G67: =D67 / $C$59 -> 1.1780624 | H67: =1 + $C$56 * ( G67 - 1 ) -> 1.0890312 | J67: =$C$58 * H67 -> 3.8116092 | L67: =J67 = E67 -> FALSE | M67: =( J67 - E67 ) / E67 -> -0.029352969
B68: fhsp_otago_dunedin | C68: Dunedin | D68: 4.6468026 | E68: 3.8804858 | G68: =D68 / $C$59 -> 1.1641457 | H68: =1 + $C$56 * ( G68 - 1 ) -> 1.0820729 | J68: =$C$58 * H68 -> 3.787255 | L68: =J68 = E68 -> FALSE | M68: =( J68 - E68 ) / E68 -> -0.024025532
B69: fhsp_manawatu_paraparaumu | C69: Manawatu | D69: 4.5936697 | E69: 3.8361151 | G69: =D69 / $C$59 -> 1.1508345 | H69: =1 + $C$56 * ( G69 - 1 ) -> 1.0754173 | J69: =$C$58 * H69 -> 3.7639605 | L69: =J69 = E69 -> FALSE | M69: =( J69 - E69 ) / E69 -> -0.018809314
B70: fhsp_east_coast_napier | C70: East Coast | D70: 4.5019613 | E70: 3.7595306 | G70: =D70 / $C$59 -> 1.1278592 | H70: =1 + $C$56 * ( G70 - 1 ) -> 1.0639296 | J70: =$C$58 * H70 -> 3.7237536 | L70: =J70 = E70 -> FALSE | M70: =( J70 - E70 ) / E70 -> -0.0095163613
B71: fhsp_nelson_marlborough_nelson | C71: Nelson-Marlborough | D71: 4.4584903 | E71: 3.7232286 | G71: =D71 / $C$59 -> 1.1169686 | H71: =1 + $C$56 * ( G71 - 1 ) -> 1.0584843 | J71: =$C$58 * H71 -> 3.704695 | L71: =J71 = E71 -> FALSE | M71: =( J71 - E71 ) / E71 -> -0.0049778241
B72: fhsp_west_coast_hokitika | C72: West Coast | D72: 4.417089 | E72: 3.6886549 | G72: =D72 / $C$59 -> 1.1065965 | H72: =1 + $C$56 * ( G72 - 1 ) -> 1.0532982 | J72: =$C$58 * H72 -> 3.6865438 | L72: =J72 = E72 -> FALSE | M72: =( J72 - E72 ) / E72 -> -0.00057231532
B73: fhsp_waikato_hamilton | C73: Hamilton | D73: 4.3060723 | E73: 3.5959462 | G73: =D73 / $C$59 -> 1.0787839 | H73: =1 + $C$56 * ( G73 - 1 ) -> 1.0393919 | J73: =$C$58 * H73 -> 3.6378718 | L73: =J73 = E73 -> FALSE | M73: =( J73 - E73 ) / E73 -> 0.011659117
B74: fhsp_southland_invercargill | C74: Invercargill | D74: 4.3049381 | E74: 3.594999 | G74: =D74 / $C$59 -> 1.0784997 | H74: =1 + $C$56 * ( G74 - 1 ) -> 1.0392499 | J74: =$C$58 * H74 -> 3.6373745 | L74: =J74 = E74 -> FALSE | M74: =( J74 - E74 ) / E74 -> 0.011787334
... B80: fhsp_central_otago_lauder | C80: Central Otago | D80: 3.3033806 | E80: 2.7586112 | G80: =D80 / $C$59 -> 0.82758335 | H80: =1 + $C$56 * ( G80 - 1 ) -> 0.91379168 | J80: =$C$58 * H80 -> 3.1982709 | L80: =J80 = E80 -> FALSE | M80: =( J80 - E80 ) / E80 -> 0.15937719
D81: =AVERAGE( D63:D80 ) -> 4.3621663 | E81: =AVERAGE( E63:E80 ) -> 3.6427896 | J81: =AVERAGE( J63:J80 ) -> 3.6624646
B83: Data in green box from "WH - Final (2)" tab cells B119:F137
B86: Example calculations for delivered efficiency
B88: Old model - all values copied from "WH - Final (2)" tab (including cells without green fill)
B90: Wellington | Q90: Christchurch
B92: Energy service demand | Q92: Energy service demand
B94: Number of people | C94: Other | D94: Showering energy use | G94: Total delivered energy use | Q94: Number of people | R94: Other | S94: Showering energy use | V94: Total delivered energy use
D95: Low | E95: Medium | F95: High | G95: Low | H95: Medium | I95: High | S95: Low | T95: Medium | U95: High | V95: Low | W95: Medium | X95: High
B96: 1 | C96: 243.58093 | D96: 183.18749 | E96: 430.85698 | F96: 830.93846 | G96: 426.76842 | H96: 674.43791 | I96: 1074.5194 | Q96: 1 | R96: 258.64938 | S96: 194.63768 | T96: 457.78783 | U96: 882.87653 | V96: 453.28707 | W96: 716.43721 | X96: 1141.5259
B97: 2 | C97: 487.16186 | D97: 366.37498 | E97: 861.71396 | F97: 1661.8769 | G97: 853.53685 | H97: 1348.8758 | I97: 2149.0388 | Q97: 2 | R97: 517.29877 | S97: 389.27537 | T97: 915.57566 | U97: 1765.7531 | V97: 906.57413 | W97: 1432.8744 | X97: 2283.0518
B98: 3 | C98: 730.74279 | D98: 549.56247 | E98: 1292.5709 | F98: 2492.8154 | G98: 1280.3053 | H98: 2023.3137 | I98: 3223.5582 | Q98: 3 | R98: 775.94815 | S98: 583.91305 | T98: 1373.3635 | U98: 2648.6296 | V98: 1359.8612 | W98: 2149.3116 | X98: 3424.5777
B99: 4 | C99: 974.32373 | D99: 732.74997 | E99: 1723.4279 | F99: 3323.7538 | G99: 1707.0737 | H99: 2697.7516 | I99: 4298.0776 | Q99: 4 | R99: 1034.5975 | S99: 778.55073 | T99: 1831.1513 | U99: 3531.5061 | V99: 1813.1483 | W99: 2865.7489 | X99: 4566.1037
B100: 5 | C100: 1217.9047 | D100: 915.93746 | E100: 2154.2849 | F100: 4154.6923 | G100: 2133.8421 | H100: 3372.1896 | I100: 5372.597 | Q100: 5 | R100: 1293.2469 | S100: 973.18842 | T100: 2288.9392 | U100: 4414.3827 | V100: 2266.4353 | W100: 3582.1861 | X100: 5707.6296
B101: 6 | C101: 1461.4856 | D101: 1099.1249 | E101: 2585.1419 | F101: 4985.6308 | G101: 2560.6105 | H101: 4046.6275 | I101: 6447.1164 | Q101: 6 | R101: 1551.8963 | S101: 1167.8261 | T101: 2746.727 | U101: 5297.2592 | V101: 2719.7224 | W101: 4298.6233 | X101: 6849.1555
B103: Heat pump hot water cylinder | Q103: Heat pump hot water cylinder
B105: HP COP | C105: 4.146509 | Q105: HP COP | R105: 3.2852485
B107: Number of people | C107: Standing loss | D107: Total energy (heat) use | G107: Total fuel use | J107: COP | M107: Variable cost | Q107: Number of people | R107: Standing loss | S107: Total energy (heat) use | V107: Total fuel use | Y107: COP | AB107: Variable cost
D108: Low | E108: Medium | F108: High | G108: Low | H108: Medium | I108: High | J108: Low | K108: Medium | L108: High | M108: Low | N108: Medium | O108: High | S108: Low | T108: Medium | U108: High | V108: Low | W108: Medium | X108: High | Y108: Low | Z108: Medium | AA108: High | AB108: Low | AC108: Medium | AD108: High
B109: 1 | C109: 1274.6117 | D109: 1701.3801 | E109: 1949.0496 | F109: 2349.1311 | G109: 410.31627 | H109: 470.04591 | I109: 566.53225 | J109: 1.0400963 | K109: 1.4348341 | L109: 1.8966606 | M109: 60.162623 | N109: 68.920482 | O109: 83.067792 | Q109: 1 | R109: 1274.6117 | S109: 1727.8988 | T109: 1991.0489 | U109: 2416.1376 | V109: 525.9568 | W109: 606.05733 | X109: 735.45049 | Y109: 0.86183327 | Z109: 1.1821278 | AA109: 1.5521451 | AB109: 77.118415 | AC109: 88.863156 | AD109: 107.83543
B110: 2 | C110: 1274.6117 | D110: 2128.1485 | E110: 2623.4875 | F110: 3423.6505 | G110: 513.23862 | H110: 632.69789 | I110: 825.67058 | J110: 1.663041 | K110: 2.131943 | L110: 2.6027799 | M110: 75.253612 | N110: 92.769329 | O110: 121.06395 | Q110: 2 | R110: 1274.6117 | S110: 2181.1858 | T110: 2707.4861 | U110: 3557.6635 | V110: 663.93329 | W110: 824.13435 | X110: 1082.9207 | Y110: 1.3654597 | Z110: 1.7386418 | AA110: 2.1082355 | AB110: 97.349219 | AC110: 120.8387 | AD110: 158.78325
B111: 3 | C111: 1425.8493 | D111: 2706.1546 | E111: 3449.1631 | F111: 4649.4075 | G111: 652.63444 | H111: 831.82336 | I111: 1121.2824 | J111: 1.9617495 | K111: 2.4323839 | L111: 2.8748852 | M111: 95.692525 | N111: 121.9661 | O111: 164.40803 | Q111: 3 | R111: 1425.8493 | S111: 2785.7105 | T111: 3575.161 | U111: 4850.4271 | V111: 847.94516 | W111: 1088.2467 | X111: 1476.4262 | Y111: 1.6037136 | Z111: 1.9750223 | AA111: 2.3195048 | AB111: 124.32996 | AC111: 159.56418 | AD111: 216.481
B112: 4 | C112: 1425.8493 | D112: 3132.923 | E112: 4123.601 | F112: 5723.9269 | G112: 755.55678 | H112: 994.47534 | I112: 1380.4207 | J112: 2.2593586 | K112: 2.7127386 | L112: 3.1135998 | M112: 110.78351 | N112: 145.81495 | O112: 202.40419 | Q112: 4 | R112: 1425.8493 | S112: 3238.9976 | T112: 4291.5982 | U112: 5991.953 | V112: 985.92165 | W112: 1306.3238 | X112: 1823.8964 | Y112: 1.8390389 | Z112: 2.1937508 | AA112: 2.5034884 | AB112: 144.56076 | AC112: 191.53972 | AD112: 267.42882
B113: 5 | C113: 1504.2443 | D113: 3638.0864 | E113: 4876.4338 | F113: 6876.8413 | G113: 877.38539 | H113: 1176.0336 | I113: 1658.4653 | J113: 2.4320466 | K113: 2.8674262 | L113: 3.2394992 | M113: 128.64663 | N113: 172.43592 | O113: 243.17247 | Q113: 5 | R113: 1504.2443 | S113: 3770.6796 | T113: 5086.4304 | U113: 7211.8739 | V113: 1147.7609 | W113: 1548.2635 | X113: 2195.2294 | Y113: 1.9746581 | Z113: 2.3136798 | AA113: 2.6000152 | AB113: 168.29044 | AC113: 227.01414 | AD113: 321.8755
B114: 6 | C114: 1504.2443 | D114: 4064.8548 | E114: 5550.8718 | F114: 7951.3606 | G114: 980.30773 | H114: 1338.6856 | I114: 1917.6036 | J114: 2.6120477 | K114: 3.0228364 | L114: 3.3620694 | M114: 143.73762 | N114: 196.28477 | O114: 281.16863 | Q114: 6 | R114: 1504.2443 | S114: 4223.9667 | T114: 5802.8676 | U114: 8353.3998 | V114: 1285.7374 | W114: 1766.3405 | X114: 2542.6995 | Y114: 2.1153017 | Z114: 2.4336322 | AA114: 2.6936551 | AB114: 188.52124 | AC114: 258.98968 | AD114: 372.82332
B116: New model
B118: HP COP | C118: =_xlfn.XLOOKUP( B90, C63:C80, J63:J80 ) -> 3.9269172 | Q118: HP COP | R118: =_xlfn.XLOOKUP( Q90, C63:C80, J63:J80 ) -> 3.4747554
B120: Number of people | C120: Standing loss | D120: Total energy (heat) use | G120: Total fuel use | J120: COP | M120: Variable cost | Q120: Number of people | R120: Standing loss | S120: Total energy (heat) use | V120: Total fuel use | Y120: COP | AB120: Variable cost
D121: Low | E121: Medium | F121: High | G121: Low | H121: Medium | I121: High | J121: Low | K121: Medium | L121: High | M121: Low | N121: Medium | O121: High | S121: Low | T121: Medium | U121: High | V121: Low | W121: Medium | X121: High | Y121: Low | Z121: Medium | AA121: High | AB121: Low | AC121: Medium | AD121: High
B122: 1 | C122: =I48 -> 1274.6117 | D122: =$C122 + G96 -> 1701.3801 | E122: =$C122 + H96 -> 1949.0496 | F122: =$C122 + I96 -> 2349.1311 | G122: =D122 / $C$118 -> 433.26101 | H122: =E122 / $C$118 -> 496.33071 | I122: =F122 / $C$118 -> 598.21253 | J122: =G96 / G122 -> 0.98501461 | K122: =H96 / H122 -> 1.3588478 | L122: =I96 / I122 -> 1.7962168 | Q122: =B122 -> 1 | R122: =C122 -> 1274.6117 | S122: =$C122 + V96 -> 1727.8988 | T122: =$C122 + W96 -> 1991.0489 | U122: =$C122 + X96 -> 2416.1376 | V122: =S122 / $R$118 -> 497.27205 | W122: =T122 / $R$118 -> 573.00404 | X122: =U122 / $R$118 -> 695.34033 | Y122: =V96 / V122 -> 0.91154745 | Z122: =W96 / W122 -> 1.2503179 | AA122: =X96 / X122 -> 1.6416794
B123: 2 | C123: =C122 -> 1274.6117 | D123: =$C123 + G97 -> 2128.1485 | E123: =$C123 + H97 -> 2623.4875 | F123: =$C123 + I97 -> 3423.6505 | G123: =D123 / $C$118 -> 541.93873 | H123: =E123 / $C$118 -> 668.07813 | I123: =F123 / $C$118 -> 871.84177 | J123: =G97 / G123 -> 1.5749693 | K123: =H97 / H123 -> 2.019039 | L123: =I97 / I123 -> 2.4649413 | Q123: =B123 -> 2 | R123: =C123 -> 1274.6117 | S123: =$C123 + V97 -> 2181.1858 | T123: =$C123 + W97 -> 2707.4861 | U123: =$C123 + X97 -> 3557.6635 | V123: =S123 / $R$118 -> 627.72355 | W123: =T123 / $R$118 -> 779.18753 | X123: =U123 / $R$118 -> 1023.8601 | Y123: =V97 / V123 -> 1.4442251 | Z123: =W97 / W123 -> 1.838934 | AA123: =X97 / X123 -> 2.2298474
B124: 3 | C124: =I49 -> 1425.8493 | D124: =$C124 + G98 -> 2706.1546 | E124: =$C124 + H98 -> 3449.1631 | F124: =$C124 + I98 -> 4649.4075 | G124: =D124 / $C$118 -> 689.12952 | H124: =E124 / $C$118 -> 878.33862 | I124: =F124 / $C$118 -> 1183.9841 | J124: =G98 / G124 -> 1.8578587 | K124: =H98 / H124 -> 2.3035691 | L124: =I98 / I124 -> 2.7226364 | Q124: =B124 -> 3 | R124: =C124 -> 1425.8493 | S124: =$C124 + V98 -> 2785.7105 | T124: =$C124 + W98 -> 3575.161 | U124: =$C124 + X98 -> 4850.4271 | V124: =S124 / $R$118 -> 801.69974 | W124: =T124 / $R$118 -> 1028.8957 | X124: =U124 / $R$118 -> 1395.9046 | Y124: =V98 / V124 -> 1.6962226 | Z124: =W98 / W124 -> 2.08895 | AA124: =X98 / X124 -> 2.4533036
B125: 4 | C125: =C124 -> 1425.8493 | D125: =$C125 + G99 -> 3132.923 | E125: =$C125 + H99 -> 4123.601 | F125: =$C125 + I99 -> 5723.9269 | G125: =D125 / $C$118 -> 797.80724 | H125: =E125 / $C$118 -> 1050.086 | I125: =F125 / $C$118 -> 1457.6133 | J125: =G99 / G125 -> 2.1397069 | K125: =H99 / H125 -> 2.5690768 | L125: =I99 / I125 -> 2.948709 | Q125: =B125 -> 4 | R125: =C125 -> 1425.8493 | S125: =$C125 + V99 -> 3238.9976 | T125: =$C125 + W99 -> 4291.5982 | U125: =$C125 + X99 -> 5991.953 | V125: =S125 / $R$118 -> 932.15124 | W125: =T125 / $R$118 -> 1235.0792 | X125: =U125 / $R$118 -> 1724.4244 | Y125: =V99 / V125 -> 1.9451224 | Z125: =W99 / W125 -> 2.3202956 | AA125: =X99 / X125 -> 2.6479002
B126: 5 | C126: =I50 -> 1504.2443 | D126: =$C126 + G100 -> 3638.0864 | E126: =$C126 + H100 -> 4876.4338 | F126: =$C126 + I100 -> 6876.8413 | G126: =D126 / $C$118 -> 926.44846 | H126: =E126 / $C$118 -> 1241.797 | I126: =F126 / $C$118 -> 1751.2061 | J126: =G100 / G126 -> 2.3032497 | K126: =H100 / H126 -> 2.7155724 | L126: =I100 / I126 -> 3.067941 | Q126: =B126 -> 5 | R126: =C126 -> 1504.2443 | S126: =$C126 + V100 -> 3770.6796 | T126: =$C126 + W100 -> 5086.4304 | U126: =$C126 + X100 -> 7211.8739 | V126: =S126 / $R$118 -> 1085.164 | W126: =T126 / $R$118 -> 1463.824 | X126: =U126 / $R$118 -> 2075.5054 | Y126: =V100 / V126 -> 2.0885647 | Z126: =W100 / W126 -> 2.4471426 | AA126: =X100 / X126 -> 2.749995
B127: 6 | C127: =C126 -> 1504.2443 | D127: =$C127 + G101 -> 4064.8548 | E127: =$C127 + H101 -> 5550.8718 | F127: =$C127 + I101 -> 7951.3606 | G127: =D127 / $C$118 -> 1035.1262 | H127: =E127 / $C$118 -> 1413.5444 | I127: =F127 / $C$118 -> 2024.8353 | J127: =G101 / G127 -> 2.4737183 | K127: =H101 / H127 -> 2.8627523 | L127: =I101 / I127 -> 3.1840201 | Q127: =B127 -> 6 | R127: =C127 -> 1504.2443 | S127: =$C127 + V101 -> 4223.9667 | T127: =$C127 + W101 -> 5802.8676 | U127: =$C127 + X101 -> 8353.3998 | V127: =S127 / $R$118 -> 1215.6155 | W127: =T127 / $R$118 -> 1670.0075 | X127: =U127 / $R$118 -> 2404.0252 | Y127: =V101 / V127 -> 2.2373212 | Z127: =W101 / W127 -> 2.5740144 | AA127: =X101 / X127 -> 2.8490364
J130: =( J122 - J109 ) / J109 -> -0.05295823 | K130: =( K122 - K109 ) / K109 -> -0.05295823 | L130: =( L122 - L109 ) / L109 -> -0.05295823 | Y130: =( Y122 - Y109 ) / Y109 -> 0.057684215 | Z130: =( Z122 - Z109 ) / Z109 -> 0.057684215 | AA130: =( AA122 - AA109 ) / AA109 -> 0.057684215
J131: =( J123 - J110 ) / J110 -> -0.05295823 | K131: =( K123 - K110 ) / K110 -> -0.05295823 | L131: =( L123 - L110 ) / L110 -> -0.05295823 | Y131: =( Y123 - Y110 ) / Y110 -> 0.057684215 | Z131: =( Z123 - Z110 ) / Z110 -> 0.057684215 | AA131: =( AA123 - AA110 ) / AA110 -> 0.057684215
J132: =( J124 - J111 ) / J111 -> -0.05295823 | K132: =( K124 - K111 ) / K111 -> -0.05295823 | L132: =( L124 - L111 ) / L111 -> -0.05295823 | Y132: =( Y124 - Y111 ) / Y111 -> 0.057684215 | Z132: =( Z124 - Z111 ) / Z111 -> 0.057684215 | AA132: =( AA124 - AA111 ) / AA111 -> 0.057684215
J133: =( J125 - J112 ) / J112 -> -0.05295823 | K133: =( K125 - K112 ) / K112 -> -0.05295823 | L133: =( L125 - L112 ) / L112 -> -0.05295823 | Y133: =( Y125 - Y112 ) / Y112 -> 0.057684215 | Z133: =( Z125 - Z112 ) / Z112 -> 0.057684215 | AA133: =( AA125 - AA112 ) / AA112 -> 0.057684215
J134: =( J126 - J113 ) / J113 -> -0.05295823 | K134: =( K126 - K113 ) / K113 -> -0.05295823 | L134: =( L126 - L113 ) / L113 -> -0.05295823 | Y134: =( Y126 - Y113 ) / Y113 -> 0.057684215 | Z134: =( Z126 - Z113 ) / Z113 -> 0.057684215 | AA134: =( AA126 - AA113 ) / AA113 -> 0.057684215
J135: =( J127 - J114 ) / J114 -> -0.05295823 | K135: =( K127 - K114 ) / K114 -> -0.05295823 | L135: =( L127 - L114 ) / L114 -> -0.05295823 | Y135: =( Y127 - Y114 ) / Y114 -> 0.057684215 | Z135: =( Z127 - Z114 ) / Z114 -> 0.057684215 | AA135: =( AA127 - AA114 ) / AA114 -> 0.057684215
B142: References
B144: AS/NZS 4692
B146: Part 1
B158: Part 2
B183: Coefficient | C183: 0.6099
B184: Exponent | C184: 0.3261
B185: Fixed | C185: 0.4
B187: Tank size (L) | C187: Linear loss | D187: Fixed loss | E187: Total loss
B188: 170 | C188: =$C$183 * B188 ^ $C$184 -> 3.2554275 | D188: =$C$185 -> 0.4 | E188: =D188 + C188 -> 3.6554275
B189: 180 | C189: =$C$183 * B189 ^ $C$184 -> 3.3166756 | D189: =$C$185 -> 0.4 | E189: =D189 + C189 -> 3.7166756
B190: 190 | C190: =$C$183 * B190 ^ $C$184 -> 3.3756715 | D190: =$C$185 -> 0.4 | E190: =D190 + C190 -> 3.7756715
B191: 200 | C191: =$C$183 * B191 ^ $C$184 -> 3.4326104 | D191: =$C$185 -> 0.4 | E191: =D191 + C191 -> 3.8326104
B192: 210 | C192: =$C$183 * B192 ^ $C$184 -> 3.4876616 | D192: =$C$185 -> 0.4 | E192: =D192 + C192 -> 3.8876616
B193: 220 | C193: =$C$183 * B193 ^ $C$184 -> 3.5409734 | D193: =$C$185 -> 0.4 | E193: =D193 + C193 -> 3.9409734
B194: 230 | C194: =$C$183 * B194 ^ $C$184 -> 3.5926762 | D194: =$C$185 -> 0.4 | E194: =D194 + C194 -> 3.9926762
...

Sheet Climate comparison
B2: 2017 Residential Climate Files | Energy Rating
C4: Numebr of hours
B5: Temperature | C5: Northland | E5: Auckland | G5: Hamilton | I5: Bay of Plenty | K5: Rototura | M5: Taupo | O5: New Plymouth | Q5: East Coast | S5: Manawatu | U5: Wairarapa | W5: Wellington | Y5: Nelson-Walborough | AA5: West Coast | AC5: Christchurch | AE5: Queenstown-Lakes | AG5: Central otago | AI5: Dunedin | AK5: Invercargill | AM5: Canberra | AO5: Sydney
B6: -9 | AG6: 1 | AM6: 0 | AN6: =$B6*AM6 -> 0 | AO6: 0 | AP6: =$B6*AO6 -> 0
B7: -8 | D7: =$B7*C7 -> 0 | F7: =$B7*E7 -> 0 | H7: =$B7*G7 -> 0 | J7: =$B7*I7 -> 0 | L7: =$B7*K7 -> 0 | N7: =$B7*M7 -> 0 | P7: =$B7*O7 -> 0 | R7: =$B7*Q7 -> 0 | T7: =$B7*S7 -> 0 | V7: =$B7*U7 -> 0 | X7: =$B7*W7 -> 0 | Z7: =$B7*Y7 -> 0 | AB7: =$B7*AA7 -> 0 | AD7: =$B7*AC7 -> 0 | AF7: =$B7*AE7 -> 0 | AG7: 1 | AH7: =$B7*AG7 -> -8 | AJ7: =$B7*AI7 -> 0 | AL7: =$B7*AK7 -> 0 | AM7: 0 | AN7: =$B7*AM7 -> 0 | AO7: 0 | AP7: =$B7*AO7 -> 0
B8: -7 | D8: =$B8*C8 -> 0 | F8: =$B8*E8 -> 0 | H8: =$B8*G8 -> 0 | J8: =$B8*I8 -> 0 | L8: =$B8*K8 -> 0 | N8: =$B8*M8 -> 0 | P8: =$B8*O8 -> 0 | R8: =$B8*Q8 -> 0 | T8: =$B8*S8 -> 0 | V8: =$B8*U8 -> 0 | X8: =$B8*W8 -> 0 | Z8: =$B8*Y8 -> 0 | AB8: =$B8*AA8 -> 0 | AD8: =$B8*AC8 -> 0 | AF8: =$B8*AE8 -> 0 | AG8: 8 | AH8: =$B8*AG8 -> -56 | AJ8: =$B8*AI8 -> 0 | AL8: =$B8*AK8 -> 0 | AM8: 0 | AN8: =$B8*AM8 -> 0 | AO8: 0 | AP8: =$B8*AO8 -> 0
B9: -6 | D9: =$B9*C9 -> 0 | F9: =$B9*E9 -> 0 | H9: =$B9*G9 -> 0 | J9: =$B9*I9 -> 0 | L9: =$B9*K9 -> 0 | N9: =$B9*M9 -> 0 | P9: =$B9*O9 -> 0 | R9: =$B9*Q9 -> 0 | T9: =$B9*S9 -> 0 | V9: =$B9*U9 -> 0 | X9: =$B9*W9 -> 0 | Z9: =$B9*Y9 -> 0 | AB9: =$B9*AA9 -> 0 | AC9: 1 | AD9: =$B9*AC9 -> -6 | AE9: 3 | AF9: =$B9*AE9 -> -18 | AG9: 29 | AH9: =$B9*AG9 -> -174 | AJ9: =$B9*AI9 -> 0 | AL9: =$B9*AK9 -> 0 | AM9: 3 | AN9: =$B9*AM9 -> -18 | AO9: 0 | AP9: =$B9*AO9 -> 0
B10: -5 | D10: =$B10*C10 -> 0 | F10: =$B10*E10 -> 0 | H10: =$B10*G10 -> 0 | J10: =$B10*I10 -> 0 | L10: =$B10*K10 -> 0 | M10: 3 | N10: =$B10*M10 -> -15 | P10: =$B10*O10 -> 0 | R10: =$B10*Q10 -> 0 | T10: =$B10*S10 -> 0 | V10: =$B10*U10 -> 0 | X10: =$B10*W10 -> 0 | Z10: =$B10*Y10 -> 0 | AB10: =$B10*AA10 -> 0 | AC10: 5 | AD10: =$B10*AC10 -> -25 | AE10: 18 | AF10: =$B10*AE10 -> -90 | AG10: 63 | AH10: =$B10*AG10 -> -315 | AJ10: =$B10*AI10 -> 0 | AK10: 2 | AL10: =$B10*AK10 -> -10 | AM10: 14 | AN10: =$B10*AM10 -> -70 | AO10: 0 | AP10: =$B10*AO10 -> 0
B11: -4 | D11: =$B11*C11 -> 0 | F11: =$B11*E11 -> 0 | H11: =$B11*G11 -> 0 | J11: =$B11*I11 -> 0 | K11: 1 | L11: =$B11*K11 -> -4 | M11: 15 | N11: =$B11*M11 -> -60 | P11: =$B11*O11 -> 0 | R11: =$B11*Q11 -> 0 | T11: =$B11*S11 -> 0 | V11: =$B11*U11 -> 0 | X11: =$B11*W11 -> 0 | Z11: =$B11*Y11 -> 0 | AB11: =$B11*AA11 -> 0 | AC11: 15 | AD11: =$B11*AC11 -> -60 | AE11: 37 | AF11: =$B11*AE11 -> -148 | AG11: 74 | AH11: =$B11*AG11 -> -296 | AJ11: =$B11*AI11 -> 0 | AK11: 3 | AL11: =$B11*AK11 -> -12 | AM11: 23 | AN11: =$B11*AM11 -> -92 | AO11: 0 | AP11: =$B11*AO11 -> 0
B12: -3 | D12: =$B12*C12 -> 0 | F12: =$B12*E12 -> 0 | G12: 2 | H12: =$B12*G12 -> -6 | J12: =$B12*I12 -> 0 | K12: 9 | L12: =$B12*K12 -> -27 | M12: 29 | N12: =$B12*M12 -> -87 | P12: =$B12*O12 -> 0 | R12: =$B12*Q12 -> 0 | S12: 1 | T12: =$B12*S12 -> -3 | U12: 15 | V12: =$B12*U12 -> -45 | X12: =$B12*W12 -> 0 | Z12: =$B12*Y12 -> 0 | AB12: =$B12*AA12 -> 0 | AC12: 37 | AD12: =$B12*AC12 -> -111 | AE12: 55 | AF12: =$B12*AE12 -> -165 | AG12: 101 | AH12: =$B12*AG12 -> -303 | AJ12: =$B12*AI12 -> 0 | AK12: 20 | AL12: =$B12*AK12 -> -60 | AM12: 46 | AN12: =$B12*AM12 -> -138 | AO12: 0 | AP12: =$B12*AO12 -> 0
B13: -2 | D13: =$B13*C13 -> 0 | F13: =$B13*E13 -> 0 | G13: 16 | H13: =$B13*G13 -> -32 | J13: =$B13*I13 -> 0 | K13: 23 | L13: =$B13*K13 -> -46 | M13: 67 | N13: =$B13*M13 -> -134 | P13: =$B13*O13 -> 0 | Q13: 2 | R13: =$B13*Q13 -> -4 | S13: 7 | T13: =$B13*S13 -> -14 | U13: 37 | V13: =$B13*U13 -> -74 | X13: =$B13*W13 -> 0 | Y13: 1 | Z13: =$B13*Y13 -> -2 | AA13: 3 | AB13: =$B13*AA13 -> -6 | AC13: 60 | AD13: =$B13*AC13 -> -120 | AE13: 110 | AF13: =$B13*AE13 -> -220 | AG13: 134 | AH13: =$B13*AG13 -> -268 | AJ13: =$B13*AI13 -> 0 | AK13: 23 | AL13: =$B13*AK13 -> -46 | AM13: 57 | AN13: =$B13*AM13 -> -114 | AO13: 0 | AP13: =$B13*AO13 -> 0
B14: -1 | D14: =$B14*C14 -> 0 | F14: =$B14*E14 -> 0 | G14: 25 | H14: =$B14*G14 -> -25 | J14: =$B14*I14 -> 0 | K14: 34 | L14: =$B14*K14 -> -34 | M14: 91 | N14: =$B14*M14 -> -91 | O14: 1 | P14: =$B14*O14 -> -1 | Q14: 6 | R14: =$B14*Q14 -> -6 | S14: 8 | T14: =$B14*S14 -> -8 | U14: 72 | V14: =$B14*U14 -> -72 | X14: =$B14*W14 -> 0 | Y14: 11 | Z14: =$B14*Y14 -> -11 | AA14: 13 | AB14: =$B14*AA14 -> -13 | AC14: 63 | AD14: =$B14*AC14 -> -63 | AE14: 182 | AF14: =$B14*AE14 -> -182 | AG14: 211 | AH14: =$B14*AG14 -> -211 | AI14: 11 | AJ14: =$B14*AI14 -> -11 | AK14: 38 | AL14: =$B14*AK14 -> -38 | AM14: 73 | AN14: =$B14*AM14 -> -73 | AO14: 0 | AP14: =$B14*AO14 -> 0
B15: 0 | D15: =$B15*C15 -> 0 | F15: =$B15*E15 -> 0 | G15: 44 | H15: =$B15*G15 -> 0 | I15: 1 | J15: =$B15*I15 -> 0 | K15: 44 | L15: =$B15*K15 -> 0 | M15: 110 | N15: =$B15*M15 -> 0 | O15: 3 | P15: =$B15*O15 -> 0 | Q15: 25 | R15: =$B15*Q15 -> 0 | S15: 6 | T15: =$B15*S15 -> 0 | U15: 106 | V15: =$B15*U15 -> 0 | X15: =$B15*W15 -> 0 | Y15: 32 | Z15: =$B15*Y15 -> 0 | AA15: 48 | AB15: =$B15*AA15 -> 0 | AC15: 110 | AD15: =$B15*AC15 -> 0 | AE15: 226 | AF15: =$B15*AE15 -> 0 | AG15: 229 | AH15: =$B15*AG15 -> 0 | AI15: 23 | AJ15: =$B15*AI15 -> 0 | AK15: 48 | AL15: =$B15*AK15 -> 0 | AM15: 81 | AN15: =$B15*AM15 -> 0 | AO15: 0 | AP15: =$B15*AO15 -> 0
B16: 1 | D16: =$B16*C16 -> 0 | F16: =$B16*E16 -> 0 | G16: 53 | H16: =$B16*G16 -> 53 | I16: 4 | J16: =$B16*I16 -> 4 | K16: 87 | L16: =$B16*K16 -> 87 | M16: 128 | N16: =$B16*M16 -> 128 | O16: 16 | P16: =$B16*O16 -> 16 | Q16: 34 | R16: =$B16*Q16 -> 34 | S16: 19 | T16: =$B16*S16 -> 19 | U16: 129 | V16: =$B16*U16 -> 129 | X16: =$B16*W16 -> 0 | Y16: 70 | Z16: =$B16*Y16 -> 70 | AA16: 75 | AB16: =$B16*AA16 -> 75 | AC16: 117 | AD16: =$B16*AC16 -> 117 | AE16: 252 | AF16: =$B16*AE16 -> 252 | AG16: 283 | AH16: =$B16*AG16 -> 283 | AI16: 55 | AJ16: =$B16*AI16 -> 55 | AK16: 88 | AL16: =$B16*AK16 -> 88 | AM16: 123 | AN16: =$B16*AM16 -> 123 | AO16: 0 | AP16: =$B16*AO16 -> 0
B17: 2 | D17: =$B17*C17 -> 0 | E17: 2 | F17: =$B17*E17 -> 4 | G17: 69 | H17: =$B17*G17 -> 138 | I17: 11 | J17: =$B17*I17 -> 22 | K17: 91 | L17: =$B17*K17 -> 182 | M17: 126 | N17: =$B17*M17 -> 252 | O17: 36 | P17: =$B17*O17 -> 72 | Q17: 56 | R17: =$B17*Q17 -> 112 | S17: 48 | T17: =$B17*S17 -> 96 | U17: 132 | V17: =$B17*U17 -> 264 | W17: 5 | X17: =$B17*W17 -> 10 | Y17: 86 | Z17: =$B17*Y17 -> 172 | AA17: 106 | AB17: =$B17*AA17 -> 212 | AC17: 175 | AD17: =$B17*AC17 -> 350 | AE17: 303 | AF17: =$B17*AE17 -> 606 | AG17: 356 | AH17: =$B17*AG17 -> 712 | AI17: 74 | AJ17: =$B17*AI17 -> 148 | AK17: 143 | AL17: =$B17*AK17 -> 286 | AM17: 128 | AN17: =$B17*AM17 -> 256 | AO17: 0 | AP17: =$B17*AO17 -> 0
B18: 3 | C18: 3 | D18: =$B18*C18 -> 9 | E18: 5 | F18: =$B18*E18 -> 15 | G18: 115 | H18: =$B18*G18 -> 345 | I18: 47 | J18: =$B18*I18 -> 141 | K18: 139 | L18: =$B18*K18 -> 417 | M18: 142 | N18: =$B18*M18 -> 426 | O18: 54 | P18: =$B18*O18 -> 162 | Q18: 92 | R18: =$B18*Q18 -> 276 | S18: 68 | T18: =$B18*S18 -> 204 | U18: 199 | V18: =$B18*U18 -> 597 | W18: 11 | X18: =$B18*W18 -> 33 | Y18: 99 | Z18: =$B18*Y18 -> 297 | AA18: 197 | AB18: =$B18*AA18 -> 591 | AC18: 181 | AD18: =$B18*AC18 -> 543 | AE18: 336 | AF18: =$B18*AE18 -> 1008 | AG18: 360 | AH18: =$B18*AG18 -> 1080 | AI18: 127 | AJ18: =$B18*AI18 -> 381 | AK18: 216 | AL18: =$B18*AK18 -> 648 | AM18: 170 | AN18: =$B18*AM18 -> 510 | AO18: 0 | AP18: =$B18*AO18 -> 0
B19: 4 | C19: 9 | D19: =$B19*C19 -> 36 | E19: 17 | F19: =$B19*E19 -> 68 | G19: 129 | H19: =$B19*G19 -> 516 | I19: 76 | J19: =$B19*I19 -> 304 | K19: 177 | L19: =$B19*K19 -> 708 | M19: 191 | N19: =$B19*M19 -> 764 | O19: 73 | P19: =$B19*O19 -> 292 | Q19: 144 | R19: =$B19*Q19 -> 576 | S19: 117 | T19: =$B19*S19 -> 468 | U19: 214 | V19: =$B19*U19 -> 856 | W19: 54 | X19: =$B19*W19 -> 216 | Y19: 177 | Z19: =$B19*Y19 -> 708 | AA19: 222 | AB19: =$B19*AA19 -> 888 | AC19: 277 | AD19: =$B19*AC19 -> 1108 | AE19: 400 | AF19: =$B19*AE19 -> 1600 | AG19: 417 | AH19: =$B19*AG19 -> 1668 | AI19: 186 | AJ19: =$B19*AI19 -> 744 | AK19: 324 | AL19: =$B19*AK19 -> 1296 | AM19: 184 | AN19: =$B19*AM19 -> 736 | AO19: 0 | AP19: =$B19*AO19 -> 0
B20: 5 | C20: 22 | D20: =$B20*C20 -> 110 | E20: 34 | F20: =$B20*E20 -> 170 | G20: 176 | H20: =$B20*G20 -> 880 | I20: 113 | J20: =$B20*I20 -> 565 | K20: 201 | L20: =$B20*K20 -> 1005 | M20: 252 | N20: =$B20*M20 -> 1260 | O20: 108 | P20: =$B20*O20 -> 540 | Q20: 154 | R20: =$B20*Q20 -> 770 | S20: 149 | T20: =$B20*S20 -> 745 | U20: 273 | V20: =$B20*U20 -> 1365 | W20: 102 | X20: =$B20*W20 -> 510 | Y20: 201 | Z20: =$B20*Y20 -> 1005 | AA20: 286 | AB20: =$B20*AA20 -> 1430 | AC20: 331 | AD20: =$B20*AC20 -> 1655 | AE20: 449 | AF20: =$B20*AE20 -> 2245 | AG20: 394 | AH20: =$B20*AG20 -> 1970 | AI20: 246 | AJ20: =$B20*AI20 -> 1230 | AK20: 414 | AL20: =$B20*AK20 -> 2070 | AM20: 236 | AN20: =$B20*AM20 -> 1180 | AO20: 1 | AP20: =$B20*AO20 -> 5
B21: 6 | C21: 37 | D21: =$B21*C21 -> 222 | E21: 80 | F21: =$B21*E21 -> 480 | G21: 199 | H21: =$B21*G21 -> 1194 | I21: 138 | J21: =$B21*I21 -> 828 | K21: 261 | L21: =$B21*K21 -> 1566 | M21: 314 | N21: =$B21*M21 -> 1884 | O21: 178 | P21: =$B21*O21 -> 1068 | Q21: 172 | R21: =$B21*Q21 -> 1032 | S21: 221 | T21: =$B21*S21 -> 1326 | U21: 350 | V21: =$B21*U21 -> 2100 | W21: 178 | X21: =$B21*W21 -> 1068 | Y21: 247 | Z21: =$B21*Y21 -> 1482 | AA21: 379 | AB21: =$B21*AA21 -> 2274 | AC21: 368 | AD21: =$B21*AC21 -> 2208 | AE21: 418 | AF21: =$B21*AE21 -> 2508 | AG21: 444 | AH21: =$B21*AG21 -> 2664 | AI21: 386 | AJ21: =$B21*AI21 -> 2316 | AK21: 534 | AL21: =$B21*AK21 -> 3204 | AM21: 279 | AN21: =$B21*AM21 -> 1674 | AO21: 10 | AP21: =$B21*AO21 -> 60
B22: 7 | C22: 57 | D22: =$B22*C22 -> 399 | E22: 112 | F22: =$B22*E22 -> 784 | G22: 311 | H22: =$B22*G22 -> 2177 | I22: 201 | J22: =$B22*I22 -> 1407 | K22: 346 | L22: =$B22*K22 -> 2422 | M22: 351 | N22: =$B22*M22 -> 2457 | O22: 268 | P22: =$B22*O22 -> 1876 | Q22: 277 | R22: =$B22*Q22 -> 1939 | S22: 268 | T22: =$B22*S22 -> 1876 | U22: 363 | V22: =$B22*U22 -> 2541 | W22: 362 | X22: =$B22*W22 -> 2534 | Y22: 301 | Z22: =$B22*Y22 -> 2107 | AA22: 399 | AB22: =$B22*AA22 -> 2793 | AC22: 450 | AD22: =$B22*AC22 -> 3150 | AE22: 567 | AF22: =$B22*AE22 -> 3969 | AG22: 448 | AH22: =$B22*AG22 -> 3136 | AI22: 646 | AJ22: =$B22*AI22 -> 4522 | AK22: 595 | AL22: =$B22*AK22 -> 4165 | AM22: 442 | AN22: =$B22*AM22 -> 3094 | AO22: 37 | AP22: =$B22*AO22 -> 259
B23: 8 | C23: 128 | D23: =$B23*C23 -> 1024 | E23: 170 | F23: =$B23*E23 -> 1360 | G23: 361 | H23: =$B23*G23 -> 2888 | I23: 278 | J23: =$B23*I23 -> 2224 | K23: 445 | L23: =$B23*K23 -> 3560 | M23: 543 | N23: =$B23*M23 -> 4344 | O23: 274 | P23: =$B23*O23 -> 2192 | Q23: 345 | R23: =$B23*Q23 -> 2760 | S23: 368 | T23: =$B23*S23 -> 2944 | U23: 444 | V23: =$B23*U23 -> 3552 | W23: 447 | X23: =$B23*W23 -> 3576 | Y23: 402 | Z23: =$B23*Y23 -> 3216 | AA23: 471 | AB23: =$B23*AA23 -> 3768 | AC23: 560 | AD23: =$B23*AC23 -> 4480 | AE23: 496 | AF23: =$B23*AE23 -> 3968 | AG23: 458 | AH23: =$B23*AG23 -> 3664 | AI23: 878 | AJ23: =$B23*AI23 -> 7024 | AK23: 763 | AL23: =$B23*AK23 -> 6104 | AM23: 416 | AN23: =$B23*AM23 -> 3328 | AO23: 109 | AP23: =$B23*AO23 -> 872
B24: 9 | C24: 178 | D24: =$B24*C24 -> 1602 | E24: 235 | F24: =$B24*E24 -> 2115 | G24: 431 | H24: =$B24*G24 -> 3879 | I24: 327 | J24: =$B24*I24 -> 2943 | K24: 655 | L24: =$B24*K24 -> 5895 | M24: 598 | N24: =$B24*M24 -> 5382 | O24: 338 | P24: =$B24*O24 -> 3042 | Q24: 431 | R24: =$B24*Q24 -> 3879 | S24: 409 | T24: =$B24*S24 -> 3681 | U24: 459 | V24: =$B24*U24 -> 4131 | W24: 731 | X24: =$B24*W24 -> 6579 | Y24: 506 | Z24: =$B24*Y24 -> 4554 | AA24: 598 | AB24: =$B24*AA24 -> 5382 | AC24: 615 | AD24: =$B24*AC24 -> 5535 | AE24: 579 | AF24: =$B24*AE24 -> 5211 | AG24: 452 | AH24: =$B24*AG24 -> 4068 | AI24: 859 | AJ24: =$B24*AI24 -> 7731 | AK24: 803 | AL24: =$B24*AK24 -> 7227 | AM24: 469 | AN24: =$B24*AM24 -> 4221 | AO24: 187 | AP24: =$B24*AO24 -> 1683
B25: 10 | C25: 283 | D25: =$B25*C25 -> 2830 | E25: 302 | F25: =$B25*E25 -> 3020 | G25: 546 | H25: =$B25*G25 -> 5460 | I25: 396 | J25: =$B25*I25 -> 3960 | K25: 664 | L25: =$B25*K25 -> 6640 | M25: 551 | N25: =$B25*M25 -> 5510 | O25: 428 | P25: =$B25*O25 -> 4280 | Q25: 456 | R25: =$B25*Q25 -> 4560 | S25: 492 | T25: =$B25*S25 -> 4920 | U25: 495 | V25: =$B25*U25 -> 4950 | W25: 775 | X25: =$B25*W25 -> 7750 | Y25: 581 | Z25: =$B25*Y25 -> 5810 | AA25: 662 | AB25: =$B25*AA25 -> 6620 | AC25: 548 | AD25: =$B25*AC25 -> 5480 | AE25: 572 | AF25: =$B25*AE25 -> 5720 | AG25: 493 | AH25: =$B25*AG25 -> 4930 | AI25: 843 | AJ25: =$B25*AI25 -> 8430 | AK25: 841 | AL25: =$B25*AK25 -> 8410 | AM25: 489 | AN25: =$B25*AM25 -> 4890 | AO25: 243 | AP25: =$B25*AO25 -> 2430
B26: 11 | C26: 465 | D26: =$B26*C26 -> 5115 | E26: 495 | F26: =$B26*E26 -> 5445 | G26: 534 | H26: =$B26*G26 -> 5874 | I26: 473 | J26: =$B26*I26 -> 5203 | K26: 734 | L26: =$B26*K26 -> 8074 | M26: 667 | N26: =$B26*M26 -> 7337 | O26: 611 | P26: =$B26*O26 -> 6721 | Q26: 523 | R26: =$B26*Q26 -> 5753 | S26: 652 | T26: =$B26*S26 -> 7172 | U26: 489 | V26: =$B26*U26 -> 5379 | W26: 795 | X26: =$B26*W26 -> 8745 | Y26: 618 | Z26: =$B26*Y26 -> 6798 | AA26: 717 | AB26: =$B26*AA26 -> 7887 | AC26: 626 | AD26: =$B26*AC26 -> 6886 | AE26: 547 | AF26: =$B26*AE26 -> 6017 | AG26: 439 | AH26: =$B26*AG26 -> 4829 | AI26: 787 | AJ26: =$B26*AI26 -> 8657 | AK26: 796 | AL26: =$B26*AK26 -> 8756 | AM26: 504 | AN26: =$B26*AM26 -> 5544 | AO26: 298 | AP26: =$B26*AO26 -> 3278
B27: 12 | C27: 608 | D27: =$B27*C27 -> 7296 | E27: 706 | F27: =$B27*E27 -> 8472 | G27: 557 | H27: =$B27*G27 -> 6684 | I27: 516 | J27: =$B27*I27 -> 6192 | K27: 666 | L27: =$B27*K27 -> 7992 | M27: 666 | N27: =$B27*M27 -> 7992 | O27: 721 | P27: =$B27*O27 -> 8652 | Q27: 630 | R27: =$B27*Q27 -> 7560 | S27: 786 | T27: =$B27*S27 -> 9432 | U27: 533 | V27: =$B27*U27 -> 6396 | W27: 797 | X27: =$B27*W27 -> 9564 | Y27: 695 | Z27: =$B27*Y27 -> 8340 | AA27: 855 | AB27: =$B27*AA27 -> 10260 | AC27: 584 | AD27: =$B27*AC27 -> 7008 | AE27: 495 | AF27: =$B27*AE27 -> 5940 | AG27: 477 | AH27: =$B27*AG27 -> 5724 | AI27: 781 | AJ27: =$B27*AI27 -> 9372 | AK27: 711 | AL27: =$B27*AK27 -> 8532 | AM27: 482 | AN27: =$B27*AM27 -> 5784 | AO27: 327 | AP27: =$B27*AO27 -> 3924
B28: 13 | C28: 776 | D28: =$B28*C28 -> 10088 | E28: 831 | F28: =$B28*E28 -> 10803 | G28: 635 | H28: =$B28*G28 -> 8255 | I28: 532 | J28: =$B28*I28 -> 6916 | K28: 630 | L28: =$B28*K28 -> 8190 | M28: 623 | N28: =$B28*M28 -> 8099 | O28: 851 | P28: =$B28*O28 -> 11063 | Q28: 634 | R28: =$B28*Q28 -> 8242 | S28: 887 | T28: =$B28*S28 -> 11531 | U28: 565 | V28: =$B28*U28 -> 7345 | W28: 824 | X28: =$B28*W28 -> 10712 | Y28: 738 | Z28: =$B28*Y28 -> 9594 | AA28: 768 | AB28: =$B28*AA28 -> 9984 | AC28: 518 | AD28: =$B28*AC28 -> 6734 | AE28: 424 | AF28: =$B28*AE28 -> 5512 | AG28: 439 | AH28: =$B28*AG28 -> 5707 | AI28: 717 | AJ28: =$B28*AI28 -> 9321 | AK28: 575 | AL28: =$B28*AK28 -> 7475 | AM28: 439 | AN28: =$B28*AM28 -> 5707 | AO28: 400 | AP28: =$B28*AO28 -> 5200
B29: 14 | C29: 920 | D29: =$B29*C29 -> 12880 | E29: 911 | F29: =$B29*E29 -> 12754 | G29: 668 | H29: =$B29*G29 -> 9352 | I29: 695 | J29: =$B29*I29 -> 9730 | K29: 697 | L29: =$B29*K29 -> 9758 | M29: 568 | N29: =$B29*M29 -> 7952 | O29: 1053 | P29: =$B29*O29 -> 14742 | Q29: 710 | R29: =$B29*Q29 -> 9940 | S29: 839 | T29: =$B29*S29 -> 11746 | U29: 535 | V29: =$B29*U29 -> 7490 | W29: 726 | X29: =$B29*W29 -> 10164 | Y29: 658 | Z29: =$B29*Y29 -> 9212 | AA29: 758 | AB29: =$B29*AA29 -> 10612 | AC29: 544 | AD29: =$B29*AC29 -> 7616 | AE29: 427 | AF29: =$B29*AE29 -> 5978 | AG29: 375 | AH29: =$B29*AG29 -> 5250 | AI29: 619 | AJ29: =$B29*AI29 -> 8666 | AK29: 483 | AL29: =$B29*AK29 -> 6762 | AM29: 433 | AN29: =$B29*AM29 -> 6062 | AO29: 489 | AP29: =$B29*AO29 -> 6846
... B40: 25 | C40: 31 | D40: =$B40*C40 -> 775 | E40: 47 | F40: =$B40*E40 -> 1175 | G40: 40 | H40: =$B40*G40 -> 1000 | I40: 63 | J40: =$B40*I40 -> 1575 | K40: 21 | L40: =$B40*K40 -> 525 | M40: 36 | N40: =$B40*M40 -> 900 | O40: 9 | P40: =$B40*O40 -> 225 | Q40: 71 | R40: =$B40*Q40 -> 1775 | S40: 1 | T40: =$B40*S40 -> 25 | U40: 63 | V40: =$B40*U40 -> 1575 | W40: 1 | X40: =$B40*W40 -> 25 | Y40: 11 | Z40: =$B40*Y40 -> 275 | AA40: 7 | AB40: =$B40*AA40 -> 175 | AC40: 29 | AD40: =$B40*AC40 -> 725 | AE40: 27 | AF40: =$B40*AE40 -> 675 | AG40: 63 | AH40: =$B40*AG40 -> 1575 | AI40: 6 | AJ40: =$B40*AI40 -> 150 | AK40: 14 | AL40: =$B40*AK40 -> 350 | AM40: 124 | AN40: =$B40*AM40 -> 3100 | AO40: 285 | AP40: =$B40*AO40 -> 7125
B41: 26 | C41: 4 | D41: =$B41*C41 -> 104 | E41: 12 | F41: =$B41*E41 -> 312 | G41: 21 | H41: =$B41*G41 -> 546 | I41: 36 | J41: =$B41*I41 -> 936 | K41: 5 | L41: =$B41*K41 -> 130 | M41: 18 | N41: =$B41*M41 -> 468 | O41: 7 | P41: =$B41*O41 -> 182 | Q41: 40 | R41: =$B41*Q41 -> 1040 | S41: 1 | T41: =$B41*S41 -> 26 | U41: 47 | V41: =$B41*U41 -> 1222 | X41: =$B41*W41 -> 0 | Y41: 7 | Z41: =$B41*Y41 -> 182 | AA41: 2 | AB41: =$B41*AA41 -> 52 | AC41: 43 | AD41: =$B41*AC41 -> 1118 | AE41: 13 | AF41: =$B41*AE41 -> 338 | AG41: 35 | AH41: =$B41*AG41 -> 910 | AI41: 1 | AJ41: =$B41*AI41 -> 26 | AK41: 2 | AL41: =$B41*AK41 -> 52 | AM41: 100 | AN41: =$B41*AM41 -> 2600 | AO41: 198 | AP41: =$B41*AO41 -> 5148
B42: 27 | C42: 1 | D42: =$B42*C42 -> 27 | E42: 4 | F42: =$B42*E42 -> 108 | G42: 13 | H42: =$B42*G42 -> 351 | I42: 7 | J42: =$B42*I42 -> 189 | K42: 1 | L42: =$B42*K42 -> 27 | M42: 9 | N42: =$B42*M42 -> 243 | O42: 3 | P42: =$B42*O42 -> 81 | Q42: 22 | R42: =$B42*Q42 -> 594 | T42: =$B42*S42 -> 0 | U42: 21 | V42: =$B42*U42 -> 567 | X42: =$B42*W42 -> 0 | Y42: 5 | Z42: =$B42*Y42 -> 135 | AB42: =$B42*AA42 -> 0 | AC42: 35 | AD42: =$B42*AC42 -> 945 | AE42: 7 | AF42: =$B42*AE42 -> 189 | AG42: 29 | AH42: =$B42*AG42 -> 783 | AI42: 2 | AJ42: =$B42*AI42 -> 54 | AL42: =$B42*AK42 -> 0 | AM42: 89 | AN42: =$B42*AM42 -> 2403 | AO42: 105 | AP42: =$B42*AO42 -> 2835
B43: 28 | D43: =$B43*C43 -> 0 | F43: =$B43*E43 -> 0 | G43: 5 | H43: =$B43*G43 -> 140 | I43: 1 | J43: =$B43*I43 -> 28 | L43: =$B43*K43 -> 0 | M43: 9 | N43: =$B43*M43 -> 252 | O43: 1 | P43: =$B43*O43 -> 28 | Q43: 10 | R43: =$B43*Q43 -> 280 | T43: =$B43*S43 -> 0 | U43: 10 | V43: =$B43*U43 -> 280 | X43: =$B43*W43 -> 0 | Y43: 1 | Z43: =$B43*Y43 -> 28 | AB43: =$B43*AA43 -> 0 | AC43: 38 | AD43: =$B43*AC43 -> 1064 | AE43: 2 | AF43: =$B43*AE43 -> 56 | AG43: 12 | AH43: =$B43*AG43 -> 336 | AI43: 2 | AJ43: =$B43*AI43 -> 56 | AL43: =$B43*AK43 -> 0 | AM43: 65 | AN43: =$B43*AM43 -> 1820 | AO43: 59 | AP43: =$B43*AO43 -> 1652
B44: 29 | D44: =$B44*C44 -> 0 | F44: =$B44*E44 -> 0 | G44: 4 | H44: =$B44*G44 -> 116 | J44: =$B44*I44 -> 0 | L44: =$B44*K44 -> 0 | N44: =$B44*M44 -> 0 | P44: =$B44*O44 -> 0 | Q44: 7 | R44: =$B44*Q44 -> 203 | T44: =$B44*S44 -> 0 | U44: 7 | V44: =$B44*U44 -> 203 | X44: =$B44*W44 -> 0 | Z44: =$B44*Y44 -> 0 | AB44: =$B44*AA44 -> 0 | AC44: 13 | AD44: =$B44*AC44 -> 377 | AE44: 2 | AF44: =$B44*AE44 -> 58 | AG44: 7 | AH44: =$B44*AG44 -> 203 | AJ44: =$B44*AI44 -> 0 | AL44: =$B44*AK44 -> 0 | AM44: 85 | AN44: =$B44*AM44 -> 2465 | AO44: 40 | AP44: =$B44*AO44 -> 1160
B45: 30 | D45: =$B45*C45 -> 0 | F45: =$B45*E45 -> 0 | H45: =$B45*G45 -> 0 | J45: =$B45*I45 -> 0 | L45: =$B45*K45 -> 0 | N45: =$B45*M45 -> 0 | P45: =$B45*O45 -> 0 | Q45: 6 | R45: =$B45*Q45 -> 180 | T45: =$B45*S45 -> 0 | U45: 3 | V45: =$B45*U45 -> 90 | X45: =$B45*W45 -> 0 | Z45: =$B45*Y45 -> 0 | AB45: =$B45*AA45 -> 0 | AC45: 7 | AD45: =$B45*AC45 -> 210 | AF45: =$B45*AE45 -> 0 | AG45: 3 | AH45: =$B45*AG45 -> 90 | AJ45: =$B45*AI45 -> 0 | AL45: =$B45*AK45 -> 0 | AM45: 53 | AN45: =$B45*AM45 -> 1590 | AO45: 22 | AP45: =$B45*AO45 -> 660
B46: 31 | D46: =$B46*C46 -> 0 | F46: =$B46*E46 -> 0 | H46: =$B46*G46 -> 0 | J46: =$B46*I46 -> 0 | L46: =$B46*K46 -> 0 | N46: =$B46*M46 -> 0 | P46: =$B46*O46 -> 0 | Q46: 1 | R46: =$B46*Q46 -> 31 | T46: =$B46*S46 -> 0 | U46: 4 | V46: =$B46*U46 -> 124 | X46: =$B46*W46 -> 0 | Z46: =$B46*Y46 -> 0 | AB46: =$B46*AA46 -> 0 | AC46: 2 | AD46: =$B46*AC46 -> 62 | AF46: =$B46*AE46 -> 0 | AG46: 1 | AH46: =$B46*AG46 -> 31 | AJ46: =$B46*AI46 -> 0 | AL46: =$B46*AK46 -> 0 | AM46: 57 | AN46: =$B46*AM46 -> 1767 | AO46: 16 | AP46: =$B46*AO46 -> 496
B47: 32 | D47: =$B47*C47 -> 0 | F47: =$B47*E47 -> 0 | H47: =$B47*G47 -> 0 | J47: =$B47*I47 -> 0 | L47: =$B47*K47 -> 0 | N47: =$B47*M47 -> 0 | P47: =$B47*O47 -> 0 | R47: =$B47*Q47 -> 0 | T47: =$B47*S47 -> 0 | U47: 2 | V47: =$B47*U47 -> 64 | X47: =$B47*W47 -> 0 | Z47: =$B47*Y47 -> 0 | AB47: =$B47*AA47 -> 0 | AD47: =$B47*AC47 -> 0 | AF47: =$B47*AE47 -> 0 | AH47: =$B47*AG47 -> 0 | AJ47: =$B47*AI47 -> 0 | AL47: =$B47*AK47 -> 0 | AM47: 42 | AN47: =$B47*AM47 -> 1344 | AO47: 18 | AP47: =$B47*AO47 -> 576
B48: 33 | D48: =$B48*C48 -> 0 | F48: =$B48*E48 -> 0 | H48: =$B48*G48 -> 0 | J48: =$B48*I48 -> 0 | L48: =$B48*K48 -> 0 | N48: =$B48*M48 -> 0 | P48: =$B48*O48 -> 0 | R48: =$B48*Q48 -> 0 | T48: =$B48*S48 -> 0 | V48: =$B48*U48 -> 0 | X48: =$B48*W48 -> 0 | Z48: =$B48*Y48 -> 0 | AB48: =$B48*AA48 -> 0 | AD48: =$B48*AC48 -> 0 | AF48: =$B48*AE48 -> 0 | AH48: =$B48*AG48 -> 0 | AJ48: =$B48*AI48 -> 0 | AL48: =$B48*AK48 -> 0 | AM48: 26 | AN48: =$B48*AM48 -> 858 | AO48: 6 | AP48: =$B48*AO48 -> 198
B49: 34 | D49: =$B49*C49 -> 0 | F49: =$B49*E49 -> 0 | H49: =$B49*G49 -> 0 | J49: =$B49*I49 -> 0 | L49: =$B49*K49 -> 0 | N49: =$B49*M49 -> 0 | P49: =$B49*O49 -> 0 | R49: =$B49*Q49 -> 0 | T49: =$B49*S49 -> 0 | V49: =$B49*U49 -> 0 | X49: =$B49*W49 -> 0 | Z49: =$B49*Y49 -> 0 | AB49: =$B49*AA49 -> 0 | AD49: =$B49*AC49 -> 0 | AF49: =$B49*AE49 -> 0 | AH49: =$B49*AG49 -> 0 | AJ49: =$B49*AI49 -> 0 | AL49: =$B49*AK49 -> 0 | AM49: 13 | AN49: =$B49*AM49 -> 442 | AO49: 12 | AP49: =$B49*AO49 -> 408
B50: 35 | D50: =$B50*C50 -> 0 | F50: =$B50*E50 -> 0 | H50: =$B50*G50 -> 0 | J50: =$B50*I50 -> 0 | L50: =$B50*K50 -> 0 | N50: =$B50*M50 -> 0 | P50: =$B50*O50 -> 0 | R50: =$B50*Q50 -> 0 | T50: =$B50*S50 -> 0 | V50: =$B50*U50 -> 0 | X50: =$B50*W50 -> 0 | Z50: =$B50*Y50 -> 0 | AB50: =$B50*AA50 -> 0 | AD50: =$B50*AC50 -> 0 | AF50: =$B50*AE50 -> 0 | AH50: =$B50*AG50 -> 0 | AJ50: =$B50*AI50 -> 0 | AL50: =$B50*AK50 -> 0 | AM50: 8 | AN50: =$B50*AM50 -> 280 | AO50: 2 | AP50: =$B50*AO50 -> 70
B51: 36 | D51: =$B51*C51 -> 0 | F51: =$B51*E51 -> 0 | H51: =$B51*G51 -> 0 | J51: =$B51*I51 -> 0 | L51: =$B51*K51 -> 0 | N51: =$B51*M51 -> 0 | P51: =$B51*O51 -> 0 | R51: =$B51*Q51 -> 0 | T51: =$B51*S51 -> 0 | V51: =$B51*U51 -> 0 | X51: =$B51*W51 -> 0 | Z51: =$B51*Y51 -> 0 | AB51: =$B51*AA51 -> 0 | AD51: =$B51*AC51 -> 0 | AF51: =$B51*AE51 -> 0 | AH51: =$B51*AG51 -> 0 | AJ51: =$B51*AI51 -> 0 | AL51: =$B51*AK51 -> 0 | AM51: 6 | AN51: =$B51*AM51 -> 216 | AO51: 5 | AP51: =$B51*AO51 -> 180
B52: 37 | D52: =$B52*C52 -> 0 | F52: =$B52*E52 -> 0 | H52: =$B52*G52 -> 0 | J52: =$B52*I52 -> 0 | L52: =$B52*K52 -> 0 | N52: =$B52*M52 -> 0 | P52: =$B52*O52 -> 0 | R52: =$B52*Q52 -> 0 | T52: =$B52*S52 -> 0 | V52: =$B52*U52 -> 0 | X52: =$B52*W52 -> 0 | Z52: =$B52*Y52 -> 0 | AB52: =$B52*AA52 -> 0 | AD52: =$B52*AC52 -> 0 | AF52: =$B52*AE52 -> 0 | AH52: =$B52*AG52 -> 0 | AJ52: =$B52*AI52 -> 0 | AL52: =$B52*AK52 -> 0 | AM52: 2 | AN52: =$B52*AM52 -> 74 | AO52: 2 | AP52: =$B52*AO52 -> 74
B53: 38 | D53: =$B53*C53 -> 0 | F53: =$B53*E53 -> 0 | H53: =$B53*G53 -> 0 | J53: =$B53*I53 -> 0 | L53: =$B53*K53 -> 0 | N53: =$B53*M53 -> 0 | P53: =$B53*O53 -> 0 | R53: =$B53*Q53 -> 0 | T53: =$B53*S53 -> 0 | V53: =$B53*U53 -> 0 | X53: =$B53*W53 -> 0 | Z53: =$B53*Y53 -> 0 | AB53: =$B53*AA53 -> 0 | AD53: =$B53*AC53 -> 0 | AF53: =$B53*AE53 -> 0 | AH53: =$B53*AG53 -> 0 | AJ53: =$B53*AI53 -> 0 | AL53: =$B53*AK53 -> 0 | AM53: 3 | AN53: =$B53*AM53 -> 114 | AO53: 1 | AP53: =$B53*AO53 -> 38
B54: 39 | D54: =$B54*C54 -> 0 | F54: =$B54*E54 -> 0 | H54: =$B54*G54 -> 0 | J54: =$B54*I54 -> 0 | L54: =$B54*K54 -> 0 | N54: =$B54*M54 -> 0 | P54: =$B54*O54 -> 0 | R54: =$B54*Q54 -> 0 | T54: =$B54*S54 -> 0 | V54: =$B54*U54 -> 0 | X54: =$B54*W54 -> 0 | Z54: =$B54*Y54 -> 0 | AB54: =$B54*AA54 -> 0 | AD54: =$B54*AC54 -> 0 | AF54: =$B54*AE54 -> 0 | AH54: =$B54*AG54 -> 0 | AJ54: =$B54*AI54 -> 0 | AL54: =$B54*AK54 -> 0 | AM54: 0 | AN54: =$B54*AM54 -> 0 | AO54: 0 | AP54: =$B54*AO54 -> 0
B55: 40 | D55: =$B55*C55 -> 0 | F55: =$B55*E55 -> 0 | H55: =$B55*G55 -> 0 | J55: =$B55*I55 -> 0 | L55: =$B55*K55 -> 0 | N55: =$B55*M55 -> 0 | P55: =$B55*O55 -> 0 | R55: =$B55*Q55 -> 0 | T55: =$B55*S55 -> 0 | V55: =$B55*U55 -> 0 | X55: =$B55*W55 -> 0 | Z55: =$B55*Y55 -> 0 | AB55: =$B55*AA55 -> 0 | AD55: =$B55*AC55 -> 0 | AF55: =$B55*AE55 -> 0 | AH55: =$B55*AG55 -> 0 | AJ55: =$B55*AI55 -> 0 | AL55: =$B55*AK55 -> 0 | AM55: 0 | AN55: =$B55*AM55 -> 0 | AO55: 0 | AP55: =$B55*AO55 -> 0
C56: =SUM(C7:C47) -> 8760 | D56: =SUM(D6:D47)/$C$56 -> 15.520205 | E56: =SUM(E7:E47) -> 8760 | F56: =SUM(F6:F47)/$C$56 -> 15.274315 | G56: =SUM(G7:G47) -> 8760 | H56: =SUM(H6:H47)/$C$56 -> 13.536758 | I56: =SUM(I7:I47) -> 8760 | J56: =SUM(J6:J47)/$C$56 -> 14.932991 | K56: =SUM(K7:K47) -> 8760 | L56: =SUM(L6:L47)/$C$56 -> 12.184132 | M56: =SUM(M7:M47) -> 8760 | N56: =SUM(N6:N47)/$C$56 -> 11.666553 | O56: =SUM(O7:O47) -> 8760 | P56: =SUM(P6:P47)/$C$56 -> 13.594292 | Q56: =SUM(Q7:Q47) -> 8760 | R56: =SUM(R6:R47)/$C$56 -> 14.02089 | S56: =SUM(S7:S47) -> 8760 | T56: =SUM(T6:T47)/$C$56 -> 13.155023 | U56: =SUM(U7:U47) -> 8760 | V56: =SUM(V6:V47)/$C$56 -> 12.442123 | W56: =SUM(W7:W47) -> 8760 | X56: =SUM(X6:X47)/$C$56 -> 12.834018 | Y56: =SUM(Y7:Y47) -> 8760 | Z56: =SUM(Z6:Z47)/$C$56 -> 12.905936 | AA56: =SUM(AA7:AA47) -> 8760 | AB56: =SUM(AB6:AB47)/$C$56 -> 11.413699 | AC56: =SUM(AC7:AC47) -> 8760 | AD56: =SUM(AD6:AD47)/$C$56 -> 11.323516 | AE56: =SUM(AE7:AE47) -> 8760 | AF56: =SUM(AF6:AF47)/$C$56 -> 9.4969178 | AG56: =SUM(AG7:AG47) -> 8759 | AH56: =SUM(AH6:AH47)/$C$56 -> 9.4558219 | AI56: =SUM(AI7:AI47) -> 8760 | AJ56: =SUM(AJ6:AJ47)/$C$56 -> 10.788242 | AK56: =SUM(AK7:AK47) -> 8760 | AL56: =SUM(AL6:AL47)/$C$56 -> 9.9902968 | AM56: 0 | AN56: =SUM(AN6:AN47)/$C$56 -> 13.152397 | AO56: 0 | AP56: =SUM(AP6:AP47)/$C$56 -> 18.07911
D57: 15.520205 | E57: 8760 | F57: 15.274315 | G57: 8760 | H57: 13.536758 | I57: 8760 | J57: 14.932991 | K57: 8760 | L57: 12.184132 | M57: 8760 | N57: 11.666553 | O57: 8760 | P57: 13.594292 | Q57: 8760 | R57: 14.02089 | S57: 8760 | T57: 13.155023 | U57: 8760 | V57: 12.442123 | W57: 8760 | X57: 12.834018 | Y57: 8760 | Z57: 12.905936 | AA57: 8760 | AB57: 11.413699 | AC57: 8760 | AD57: 11.323516 | AE57: 8760 | AF57: 9.4969178 | AG57: 8759 | AH57: 9.4558219 | AI57: 8760 | AJ57: 10.788242 | AK57: 8760 | AL57: 9.9902968 | AM57: 0 | AN57: 13.152397 | AO57: 0 | AP57: 18.07911
C59: Area | D59: Average temperature
C60: Central otago | D60: 9.4558219
C61: Queenstown-Lakes | D61: 9.4969178
C62: Invercargill | D62: 9.9902968
C63: Dunedin | D63: 10.788242
C64: Christchurch | D64: 11.323516
C65: West Coast | D65: 11.413699
C66: Taupo | D66: 11.666553
C67: Rototura | D67: 12.184132
C68: Wairarapa | D68: 12.442123
C69: Wellington | D69: 12.834018
C70: Nelson-Walborough | D70: 12.905936
C71: Canberra | D71: 13.152397
... C79: Sydney | D79: 18.07911
C81: Temperature | D81: Northland | E81: Auckland | F81: Hamilton | G81: Bay of Plenty | H81: Rototura | I81: Taupo | J81: New Plymouth | K81: East Coast | L81: Manawatu | M81: Wairarapa | N81: Wellington | O81: Nelson-Walborough | P81: West Coast | Q81: Christchurch | R81: Queenstown-Lakes | S81: Central otago | T81: Dunedin | U81: Invercargill | V81: Canberra | W81: Sydney | X81: Melbourne | AB81: Canberra | AH81: Melbourne | AN81: Auckland | AT81: Dunedin | AZ81: Time of day | BA81: Canberra | BB81: Melbourne | BC81: Auckland | BD81: Dunedin | BE81: Difference Auckland - Dunedin | BF81: Difference (Melbourne-Canberra) | BG81: Difference (Canberra-Dunedin) | BH81: Difference (Melbourne-Dunedin)
C82: -9 | S82: 1 | V82: 0 | W82: 0 | X82: 0 | AB82: Date | AC82: hour | AD82: DB temp/10 | AE82: Month | AF82: rounded °C | AH82: Date | AI82: hour | AJ82: DB temp/10 | AK82: Month | AL82: rounded °C | AN82: Date | AO82: hour | AP82: DB temp/10 | AQ82: Month | AR82: rounded °C | AT82: Date | AU82: hour | AV82: DB temp/10 | AW82: Month | AX82: rounded °C | AZ82: 0 | BA82: =AVERAGEIF($AC$83:$AC$8842,AZ82,$AF$83:$AF$8842) -> 10.413699 | BB82: =AVERAGEIF($AI$83:$AI$8842,AZ82,$AL$83:$AL$8842) -> 14.254795 | BC82: =AVERAGEIF($AO$83:$AO$8842,AZ82,$AR$83:$AR$8842) -> 13.841096 | BD82: =AVERAGEIF($AU$83:$AU$8842,AZ82,$AX$83:$AX$8842) -> 9.5287671 | BE82: =BC82-BD82 -> 4.3123288 | BF82: =BB82-BA82 -> 3.8410959 | BG82: =BA82-BD82 -> 0.88493151 | BH82: =BB82-BD82 -> 4.7260274
C83: -8 | S83: 1 | V83: 0 | W83: 0 | X83: 0 | AB83: 38353 | AC83: 0 | AD83: 160 | AE83: January | AF83: 16 | AH83: 38353 | AI83: 0 | AJ83: 215 | AK83: January | AL83: 22 | AN83: 39083 | AO83: 0 | AP83: 120 | AQ83: January | AR83: 12 | AT83: 38353 | AU83: 0 | AV83: 108 | AW83: January | AX83: 11 | AZ83: 1 | BA83: =AVERAGEIF($AC$83:$AC$8842,AZ83,$AF$83:$AF$8842) -> 9.8657534 | BB83: =AVERAGEIF($AI$83:$AI$8842,AZ83,$AL$83:$AL$8842) -> 13.832877 | BC83: =AVERAGEIF($AO$83:$AO$8842,AZ83,$AR$83:$AR$8842) -> 13.646575 | BD83: =AVERAGEIF($AU$83:$AU$8842,AZ83,$AX$83:$AX$8842) -> 9.4219178 | BE83: =BC83-BD83 -> 4.2246575 | BF83: =BB83-BA83 -> 3.9671233 | BG83: =BA83-BD83 -> 0.44383562 | BH83: =BB83-BD83 -> 4.4109589
C84: -7 | S84: 8 | V84: 0 | W84: 0 | X84: 0 | AB84: 38353 | AC84: 1 | AD84: 148 | AE84: January | AF84: 15 | AH84: 38353 | AI84: 1 | AJ84: 223 | AK84: January | AL84: 22 | AN84: 39083 | AO84: 1 | AP84: 113 | AQ84: January | AR84: 11 | AT84: 38353 | AU84: 1 | AV84: 88 | AW84: January | AX84: 9 | AZ84: 2 | BA84: =AVERAGEIF($AC$83:$AC$8842,AZ84,$AF$83:$AF$8842) -> 9.3671233 | BB84: =AVERAGEIF($AI$83:$AI$8842,AZ84,$AL$83:$AL$8842) -> 13.484932 | BC84: =AVERAGEIF($AO$83:$AO$8842,AZ84,$AR$83:$AR$8842) -> 13.517808 | BD84: =AVERAGEIF($AU$83:$AU$8842,AZ84,$AX$83:$AX$8842) -> 9.2493151 | BE84: =BC84-BD84 -> 4.2684932 | BF84: =BB84-BA84 -> 4.1178082 | BG84: =BA84-BD84 -> 0.11780822 | BH84: =BB84-BD84 -> 4.2356164
C85: -6 | Q85: 1 | R85: 3 | S85: 29 | V85: 3 | W85: 0 | X85: 0 | AB85: 38353 | AC85: 2 | AD85: 133 | AE85: January | AF85: 13 | AH85: 38353 | AI85: 2 | AJ85: 215 | AK85: January | AL85: 22 | AN85: 39083 | AO85: 2 | AP85: 100 | AQ85: January | AR85: 10 | AT85: 38353 | AU85: 2 | AV85: 94 | AW85: January | AX85: 9 | AZ85: 3 | BA85: =AVERAGEIF($AC$83:$AC$8842,AZ85,$AF$83:$AF$8842) -> 8.9671233 | BB85: =AVERAGEIF($AI$83:$AI$8842,AZ85,$AL$83:$AL$8842) -> 13.175342 | BC85: =AVERAGEIF($AO$83:$AO$8842,AZ85,$AR$83:$AR$8842) -> 13.4 | BD85: =AVERAGEIF($AU$83:$AU$8842,AZ85,$AX$83:$AX$8842) -> 9.0821918 | BE85: =BC85-BD85 -> 4.3178082 | BF85: =BB85-BA85 -> 4.2082192 | BG85: =BA85-BD85 -> -0.11506849 | BH85: =BB85-BD85 -> 4.0931507
C86: -5 | I86: 3 | Q86: 5 | R86: 18 | S86: 63 | U86: 2 | V86: 14 | W86: 0 | X86: 0 | AB86: 38353 | AC86: 3 | AD86: 125 | AE86: January | AF86: 13 | AH86: 38353 | AI86: 3 | AJ86: 210 | AK86: January | AL86: 21 | AN86: 39083 | AO86: 3 | AP86: 100 | AQ86: January | AR86: 10 | AT86: 38353 | AU86: 3 | AV86: 95 | AW86: January | AX86: 10 | AZ86: 4 | BA86: =AVERAGEIF($AC$83:$AC$8842,AZ86,$AF$83:$AF$8842) -> 8.5643836 | BB86: =AVERAGEIF($AI$83:$AI$8842,AZ86,$AL$83:$AL$8842) -> 12.986301 | BC86: =AVERAGEIF($AO$83:$AO$8842,AZ86,$AR$83:$AR$8842) -> 13.282192 | BD86: =AVERAGEIF($AU$83:$AU$8842,AZ86,$AX$83:$AX$8842) -> 8.9424658 | BE86: =BC86-BD86 -> 4.339726 | BF86: =BB86-BA86 -> 4.4219178 | BG86: =BA86-BD86 -> -0.37808219 | BH86: =BB86-BD86 -> 4.0438356
C87: -4 | H87: 1 | I87: 15 | Q87: 15 | R87: 37 | S87: 74 | U87: 3 | V87: 23 | W87: 0 | X87: 0 | AB87: 38353 | AC87: 4 | AD87: 124 | AE87: January | AF87: 12 | AH87: 38353 | AI87: 4 | AJ87: 201 | AK87: January | AL87: 20 | AN87: 39083 | AO87: 4 | AP87: 95 | AQ87: January | AR87: 10 | AT87: 38353 | AU87: 4 | AV87: 96 | AW87: January | AX87: 10 | AZ87: 5 | BA87: =AVERAGEIF($AC$83:$AC$8842,AZ87,$AF$83:$AF$8842) -> 8.2575342 | BB87: =AVERAGEIF($AI$83:$AI$8842,AZ87,$AL$83:$AL$8842) -> 12.813699 | BC87: =AVERAGEIF($AO$83:$AO$8842,AZ87,$AR$83:$AR$8842) -> 13.30137 | BD87: =AVERAGEIF($AU$83:$AU$8842,AZ87,$AX$83:$AX$8842) -> 8.8876712 | BE87: =BC87-BD87 -> 4.4136986 | BF87: =BB87-BA87 -> 4.5561644 | BG87: =BA87-BD87 -> -0.63013699 | BH87: =BB87-BD87 -> 3.9260274
C88: -3 | F88: 2 | H88: 9 | I88: 29 | L88: 1 | M88: 15 | Q88: 37 | R88: 55 | S88: 101 | U88: 20 | V88: 46 | W88: 0 | X88: 0 | AB88: 38353 | AC88: 5 | AD88: 113 | AE88: January | AF88: 11 | AH88: 38353 | AI88: 5 | AJ88: 194 | AK88: January | AL88: 19 | AN88: 39083 | AO88: 5 | AP88: 110 | AQ88: January | AR88: 11 | AT88: 38353 | AU88: 5 | AV88: 102 | AW88: January | AX88: 10 | AZ88: 6 | BA88: =AVERAGEIF($AC$83:$AC$8842,AZ88,$AF$83:$AF$8842) -> 8.5178082 | BB88: =AVERAGEIF($AI$83:$AI$8842,AZ88,$AL$83:$AL$8842) -> 12.80274 | BC88: =AVERAGEIF($AO$83:$AO$8842,AZ88,$AR$83:$AR$8842) -> 13.745205 | BD88: =AVERAGEIF($AU$83:$AU$8842,AZ88,$AX$83:$AX$8842) -> 9.2739726 | BE88: =BC88-BD88 -> 4.4712329 | BF88: =BB88-BA88 -> 4.2849315 | BG88: =BA88-BD88 -> -0.75616438 | BH88: =BB88-BD88 -> 3.5287671
C89: -2 | F89: 16 | H89: 23 | I89: 67 | K89: 2 | L89: 7 | M89: 37 | O89: 1 | P89: 3 | Q89: 60 | R89: 110 | S89: 134 | U89: 23 | V89: 57 | W89: 0 | X89: 0 | AB89: 38353 | AC89: 6 | AD89: 127 | AE89: January | AF89: 13 | AH89: 38353 | AI89: 6 | AJ89: 188 | AK89: January | AL89: 19 | AN89: 39083 | AO89: 6 | AP89: 130 | AQ89: January | AR89: 13 | AT89: 38353 | AU89: 6 | AV89: 108 | AW89: January | AX89: 11 | AZ89: 7 | BA89: =AVERAGEIF($AC$83:$AC$8842,AZ89,$AF$83:$AF$8842) -> 9.4821918 | BB89: =AVERAGEIF($AI$83:$AI$8842,AZ89,$AL$83:$AL$8842) -> 13.246575 | BC89: =AVERAGEIF($AO$83:$AO$8842,AZ89,$AR$83:$AR$8842) -> 14.542466 | BD89: =AVERAGEIF($AU$83:$AU$8842,AZ89,$AX$83:$AX$8842) -> 9.9287671 | BE89: =BC89-BD89 -> 4.6136986 | BF89: =BB89-BA89 -> 3.7643836 | BG89: =BA89-BD89 -> -0.44657534 | BH89: =BB89-BD89 -> 3.3178082
C90: -1 | F90: 25 | H90: 34 | I90: 91 | J90: 1 | K90: 6 | L90: 8 | M90: 72 | O90: 11 | P90: 13 | Q90: 63 | R90: 182 | S90: 211 | T90: 11 | U90: 38 | V90: 73 | W90: 0 | X90: 0 | AB90: 38353 | AC90: 7 | AD90: 161 | AE90: January | AF90: 16 | AH90: 38353 | AI90: 7 | AJ90: 184 | AK90: January | AL90: 18 | AN90: 39083 | AO90: 7 | AP90: 145 | AQ90: January | AR90: 15 | AT90: 38353 | AU90: 7 | AV90: 113 | AW90: January | AX90: 11 | AZ90: 8 | BA90: =AVERAGEIF($AC$83:$AC$8842,AZ90,$AF$83:$AF$8842) -> 11.345205 | BB90: =AVERAGEIF($AI$83:$AI$8842,AZ90,$AL$83:$AL$8842) -> 14.049315 | BC90: =AVERAGEIF($AO$83:$AO$8842,AZ90,$AR$83:$AR$8842) -> 15.523288 | BD90: =AVERAGEIF($AU$83:$AU$8842,AZ90,$AX$83:$AX$8842) -> 10.772603 | BE90: =BC90-BD90 -> 4.7506849 | BF90: =BB90-BA90 -> 2.7041096 | BG90: =BA90-BD90 -> 0.57260274 | BH90: =BB90-BD90 -> 3.2767123
C91: 0 | F91: 44 | G91: 1 | H91: 44 | I91: 110 | J91: 3 | K91: 25 | L91: 6 | M91: 106 | O91: 32 | P91: 48 | Q91: 110 | R91: 226 | S91: 229 | T91: 23 | U91: 48 | V91: 81 | W91: 0 | X91: 0 | AB91: 38353 | AC91: 8 | AD91: 200 | AE91: January | AF91: 20 | AH91: 38353 | AI91: 8 | AJ91: 179 | AK91: January | AL91: 18 | AN91: 39083 | AO91: 8 | AP91: 140 | AQ91: January | AR91: 14 | AT91: 38353 | AU91: 8 | AV91: 124 | AW91: January | AX91: 12 | AZ91: 9 | BA91: =AVERAGEIF($AC$83:$AC$8842,AZ91,$AF$83:$AF$8842) -> 13.389041 | BB91: =AVERAGEIF($AI$83:$AI$8842,AZ91,$AL$83:$AL$8842) -> 15.063014 | BC91: =AVERAGEIF($AO$83:$AO$8842,AZ91,$AR$83:$AR$8842) -> 16.405479 | BD91: =AVERAGEIF($AU$83:$AU$8842,AZ91,$AX$83:$AX$8842) -> 11.676712 | BE91: =BC91-BD91 -> 4.7287671 | BF91: =BB91-BA91 -> 1.6739726 | BG91: =BA91-BD91 -> 1.7123288 | BH91: =BB91-BD91 -> 3.3863014
C92: 1 | F92: 53 | G92: 4 | H92: 87 | I92: 128 | J92: 16 | K92: 34 | L92: 19 | M92: 129 | O92: 70 | P92: 75 | Q92: 117 | R92: 252 | S92: 283 | T92: 55 | U92: 88 | V92: 123 | W92: 0 | X92: 0 | AB92: 38353 | AC92: 9 | AD92: 229 | AE92: January | AF92: 23 | AH92: 38353 | AI92: 9 | AJ92: 178 | AK92: January | AL92: 18 | AN92: 39083 | AO92: 9 | AP92: 160 | AQ92: January | AR92: 16 | AT92: 38353 | AU92: 9 | AV92: 123 | AW92: January | AX92: 12 | AZ92: 10 | BA92: =AVERAGEIF($AC$83:$AC$8842,AZ92,$AF$83:$AF$8842) -> 15.227397 | BB92: =AVERAGEIF($AI$83:$AI$8842,AZ92,$AL$83:$AL$8842) -> 16.408219 | BC92: =AVERAGEIF($AO$83:$AO$8842,AZ92,$AR$83:$AR$8842) -> 17.147945 | BD92: =AVERAGEIF($AU$83:$AU$8842,AZ92,$AX$83:$AX$8842) -> 12.326027 | BE92: =BC92-BD92 -> 4.8219178 | BF92: =BB92-BA92 -> 1.1808219 | BG92: =BA92-BD92 -> 2.9013699 | BH92: =BB92-BD92 -> 4.0821918
C93: 2 | E93: 2 | F93: 69 | G93: 11 | H93: 91 | I93: 126 | J93: 36 | K93: 56 | L93: 48 | M93: 132 | N93: 5 | O93: 86 | P93: 106 | Q93: 175 | R93: 303 | S93: 356 | T93: 74 | U93: 143 | V93: 128 | W93: 0 | X93: 1 | AB93: 38353 | AC93: 10 | AD93: 269 | AE93: January | AF93: 27 | AH93: 38353 | AI93: 10 | AJ93: 175 | AK93: January | AL93: 18 | AN93: 39083 | AO93: 10 | AP93: 167 | AQ93: January | AR93: 17 | AT93: 38353 | AU93: 10 | AV93: 129 | AW93: January | AX93: 13 | AZ93: 11 | BA93: =AVERAGEIF($AC$83:$AC$8842,AZ93,$AF$83:$AF$8842) -> 16.747945 | BB93: =AVERAGEIF($AI$83:$AI$8842,AZ93,$AL$83:$AL$8842) -> 17.575342 | BC93: =AVERAGEIF($AO$83:$AO$8842,AZ93,$AR$83:$AR$8842) -> 17.515068 | BD93: =AVERAGEIF($AU$83:$AU$8842,AZ93,$AX$83:$AX$8842) -> 12.821918 | BE93: =BC93-BD93 -> 4.6931507 | BF93: =BB93-BA93 -> 0.82739726 | BG93: =BA93-BD93 -> 3.9260274 | BH93: =BB93-BD93 -> 4.7534247
C94: 3 | D94: 3 | E94: 5 | F94: 115 | G94: 47 | H94: 139 | I94: 142 | J94: 54 | K94: 92 | L94: 68 | M94: 199 | N94: 11 | O94: 99 | P94: 197 | Q94: 181 | R94: 336 | S94: 360 | T94: 127 | U94: 216 | V94: 170 | W94: 0 | X94: 11 | AB94: 38353 | AC94: 11 | AD94: 289 | AE94: January | AF94: 29 | AH94: 38353 | AI94: 11 | AJ94: 174 | AK94: January | AL94: 17 | AN94: 39083 | AO94: 11 | AP94: 140 | AQ94: January | AR94: 14 | AT94: 38353 | AU94: 11 | AV94: 121 | AW94: January | AX94: 12 | AZ94: 12 | BA94: =AVERAGEIF($AC$83:$AC$8842,AZ94,$AF$83:$AF$8842) -> 17.890411 | BB94: =AVERAGEIF($AI$83:$AI$8842,AZ94,$AL$83:$AL$8842) -> 18.509589 | BC94: =AVERAGEIF($AO$83:$AO$8842,AZ94,$AR$83:$AR$8842) -> 17.805479 | BD94: =AVERAGEIF($AU$83:$AU$8842,AZ94,$AX$83:$AX$8842) -> 13.024658 | BE94: =BC94-BD94 -> 4.7808219 | BF94: =BB94-BA94 -> 0.61917808 | BG94: =BA94-BD94 -> 4.8657534 | BH94: =BB94-BD94 -> 5.4849315
C95: 4 | D95: 9 | E95: 17 | F95: 129 | G95: 76 | H95: 177 | I95: 191 | J95: 73 | K95: 144 | L95: 117 | M95: 214 | N95: 54 | O95: 177 | P95: 222 | Q95: 277 | R95: 400 | S95: 417 | T95: 186 | U95: 324 | V95: 184 | W95: 0 | X95: 21 | AB95: 38353 | AC95: 12 | AD95: 298 | AE95: January | AF95: 30 | AH95: 38353 | AI95: 12 | AJ95: 171 | AK95: January | AL95: 17 | AN95: 39083 | AO95: 12 | AP95: 180 | AQ95: January | AR95: 18 | AT95: 38353 | AU95: 12 | AV95: 118 | AW95: January | AX95: 12 | AZ95: 13 | BA95: =AVERAGEIF($AC$83:$AC$8842,AZ95,$AF$83:$AF$8842) -> 18.794521 | BB95: =AVERAGEIF($AI$83:$AI$8842,AZ95,$AL$83:$AL$8842) -> 18.953425 | BC95: =AVERAGEIF($AO$83:$AO$8842,AZ95,$AR$83:$AR$8842) -> 17.890411 | BD95: =AVERAGEIF($AU$83:$AU$8842,AZ95,$AX$83:$AX$8842) -> 13.093151 | BE95: =BC95-BD95 -> 4.7972603 | BF95: =BB95-BA95 -> 0.15890411 | BG95: =BA95-BD95 -> 5.7013699 | BH95: =BB95-BD95 -> 5.860274
C96: 5 | D96: 22 | E96: 34 | F96: 176 | G96: 113 | H96: 201 | I96: 252 | J96: 108 | K96: 154 | L96: 149 | M96: 273 | N96: 102 | O96: 201 | P96: 286 | Q96: 331 | R96: 449 | S96: 394 | T96: 246 | U96: 414 | V96: 236 | W96: 1 | X96: 39 | AB96: 38353 | AC96: 13 | AD96: 302 | AE96: January | AF96: 30 | AH96: 38353 | AI96: 13 | AJ96: 181 | AK96: January | AL96: 18 | AN96: 39083 | AO96: 13 | AP96: 193 | AQ96: January | AR96: 19 | AT96: 38353 | AU96: 13 | AV96: 115 | AW96: January | AX96: 12 | AZ96: 14 | BA96: =AVERAGEIF($AC$83:$AC$8842,AZ96,$AF$83:$AF$8842) -> 19.208219 | BB96: =AVERAGEIF($AI$83:$AI$8842,AZ96,$AL$83:$AL$8842) -> 19.323288 | BC96: =AVERAGEIF($AO$83:$AO$8842,AZ96,$AR$83:$AR$8842) -> 17.764384 | BD96: =AVERAGEIF($AU$83:$AU$8842,AZ96,$AX$83:$AX$8842) -> 12.90137 | BE96: =BC96-BD96 -> 4.8630137 | BF96: =BB96-BA96 -> 0.11506849 | BG96: =BA96-BD96 -> 6.3068493 | BH96: =BB96-BD96 -> 6.4219178
C97: 6 | D97: 37 | E97: 80 | F97: 199 | G97: 138 | H97: 261 | I97: 314 | J97: 178 | K97: 172 | L97: 221 | M97: 350 | N97: 178 | O97: 247 | P97: 379 | Q97: 368 | R97: 418 | S97: 444 | T97: 386 | U97: 534 | V97: 279 | W97: 10 | X97: 100 | AB97: 38353 | AC97: 14 | AD97: 305 | AE97: January | AF97: 31 | AH97: 38353 | AI97: 14 | AJ97: 190 | AK97: January | AL97: 19 | AN97: 39083 | AO97: 14 | AP97: 190 | AQ97: January | AR97: 19 | AT97: 38353 | AU97: 14 | AV97: 114 | AW97: January | AX97: 11 | AZ97: 15 | BA97: =AVERAGEIF($AC$83:$AC$8842,AZ97,$AF$83:$AF$8842) -> 19.191781 | BB97: =AVERAGEIF($AI$83:$AI$8842,AZ97,$AL$83:$AL$8842) -> 19.309589 | BC97: =AVERAGEIF($AO$83:$AO$8842,AZ97,$AR$83:$AR$8842) -> 17.468493 | BD97: =AVERAGEIF($AU$83:$AU$8842,AZ97,$AX$83:$AX$8842) -> 12.50411 | BE97: =BC97-BD97 -> 4.9643836 | BF97: =BB97-BA97 -> 0.11780822 | BG97: =BA97-BD97 -> 6.6876712 | BH97: =BB97-BD97 -> 6.8054795
